Workbook

Sheet VISION_BOARD
A1: VISION_BOARD — PANEL DE VISIÓN MAESTRO
J2: KPIs
J3: Objetivos | K3: =COUNTA(A5:A14) -> 10
A4: Categoría | B4: Objetivo 2042 | C4: Imagen / Referencia | D4: Ruta (09_PANEL_VISION) | E4: Fecha incorporación | F4: Estado | G4: Última revisión | H4: Observaciones | J4: Activos | K4: =COUNTIF(F5:F14,"Activo") -> 10
A5: Patrimonio | B5: Casa en Pirque | C5: CASA_PIRQUE.jpg | D5: 09_PANEL_VISION/Casa | F5: Activo | J5: Conseguidos | K5: =COUNTIF(F5:F14,"Conseguido") -> 0
A6: Empresas | B6: Oficina Alonso de Córdova | C6: OFICINA_ALONSO.jpg | D6: 09_PANEL_VISION/Oficina | F6: Activo | J6: Avance | K6: =IF(K3=0,0,K5/K3) -> 0
A7: Empresas | B7: Miner Global Connect | C7: MGC.jpg | D7: 09_PANEL_VISION/MGC | F7: Activo
A8: Empresas | B8: Latitud Norte Holding | C8: LNH.jpg | D8: 09_PANEL_VISION/LNH | F8: Activo
A9: Salud | B9: Salud y longevidad | C9: SALUD.jpg | D9: 09_PANEL_VISION/Salud | F9: Activo
A10: Familia | B10: Tiempo con la familia | C10: FAMILIA.jpg | D10: 09_PANEL_VISION/Familia | F10: Activo
A11: Finanzas | B11: Patrimonio e inversiones | C11: PATRIMONIO.jpg | D11: 09_PANEL_VISION/Finanzas | F11: Activo
A12: Viajes | B12: Viajes internacionales | C12: VIAJES.jpg | D12: 09_PANEL_VISION/Viajes | F12: Activo
A13: Vehículos | B13: Flota objetivo | C13: VEHICULOS.jpg | D13: 09_PANEL_VISION/Vehiculos | F13: Activo
A14: Legado | B14: Fundación y protectora de animales | C14: LEGADO.jpg | D14: 09_PANEL_VISION/Legado | F14: Activo

Sheet SERPAT TURNOS
A1: SERPAT_TURNOS - MODULO MAESTRO
P3: KPIs
P4: Trabajados | Q4: =COUNTIF(C11:C41,"<>Libre") -> 23
P5: Libres | Q5: =COUNTIF(C11:C41,"Libre") -> 8
P6: Horas | Q6: =SUM(J11:J41) -> 193
A10: Fecha | B10: Día | C10: Turno | D10: Tipo | E10: Salida Casa | F10: Ingreso | G10: Colación | H10: Salida | I10: Llegada Casa | J10: Trabajadas | K10: Nocturnas | L10: Extras | M10: Estado | N10: Observaciones
A11: 2026-07-01 | B11: Mié | C11: M | D11: Mañana | F11: 0.33333333 | H11: 0.70833333 | J11: 9 | K11: =IF(C11="N",8,0) -> 0 | L11: 0 | M11: Pendiente
A12: 2026-07-02 | B12: Jue | C12: T | D12: Tarde | F12: 0.5 | H12: 0.875 | J12: 9 | K12: =IF(C12="N",8,0) -> 0 | L12: 0 | M12: Pendiente
A13: 2026-07-03 | B13: Vie | C13: T | D13: Tarde | F13: 0.5 | H13: 0.875 | J13: 9 | K13: =IF(C13="N",8,0) -> 0 | L13: 0 | M13: Pendiente
A14: 2026-07-04 | B14: Sáb | C14: Libre | D14: Libre | J14: =IF(C14="Libre",0,8) -> 0 | K14: =IF(C14="N",8,0) -> 0 | L14: =MAX(J14-8,0) -> 0 | M14: Pendiente
A15: 2026-07-05 | B15: Dom | C15: M | D15: Mañana | F15: 0.33333333 | H15: 0.6875 | J15: 8.5 | K15: =IF(C15="N",8,0) -> 0 | L15: 0 | M15: Pendiente
A16: 2026-07-06 | B16: Lun | C16: T | D16: Tarde | F16: 0.5 | H16: 0.875 | J16: 9 | K16: =IF(C16="N",8,0) -> 0 | L16: 0 | M16: Pendiente
A17: 2026-07-07 | B17: Mar | C17: T | D17: Tarde | F17: 0.5 | H17: 0.875 | J17: 9 | K17: =IF(C17="N",8,0) -> 0 | L17: 0 | M17: Pendiente
A18: 2026-07-08 | B18: Mié | C18: T | D18: Tarde | F18: 0.5 | H18: 0.875 | J18: 9 | K18: =IF(C18="N",8,0) -> 0 | L18: 0 | M18: Pendiente
A19: 2026-07-09 | B19: Jue | C19: T | D19: Tarde | F19: 0.52083333 | H19: 0.875 | J19: 9 | K19: =IF(C19="N",8,0) -> 0 | L19: 0 | M19: Pendiente
A20: 2026-07-10 | B20: Vie | C20: TEX | D20: Compensado | J20: 0 | K20: =IF(C20="N",8,0) -> 0 | L20: =MAX(J20-8,0) -> 0 | M20: Pendiente
A21: 2026-07-11 | B21: Sáb | C21: Libre | D21: Libre | J21: =IF(C21="Libre",0,8) -> 0 | K21: =IF(C21="N",8,0) -> 0 | L21: =MAX(J21-8,0) -> 0 | M21: Pendiente
A22: 2026-07-12 | B22: Dom | C22: Libre | D22: Libre | J22: =IF(C22="Libre",0,8) -> 0 | K22: =IF(C22="N",8,0) -> 0 | L22: =MAX(J22-8,0) -> 0 | M22: Pendiente
A23: 2026-07-13 | B23: Lun | C23: N | D23: Noche | F23: 0.875 | H23: 0.33333333 | J23: 11 | K23: 9 | L23: 2 | M23: Pendiente
A24: 2026-07-14 | B24: Mar | C24: N | D24: Noche | F24: 0.875 | H24: 0.33333333 | J24: 11 | K24: 9 | L24: 2 | M24: Pendiente
A25: 2026-07-15 | B25: Mié | C25: N | D25: Noche | F25: 0.875 | H25: 0.33333333 | J25: 11 | K25: 9 | L25: 2 | M25: Pendiente
A26: 2026-07-16 | B26: Jue | C26: Libre | D26: Libre | J26: =IF(C26="Libre",0,8) -> 0 | K26: =IF(C26="N",8,0) -> 0 | L26: =MAX(J26-8,0) -> 0 | M26: Pendiente
A27: 2026-07-17 | B27: Vie | C27: T | D27: Tarde | F27: 0.52083333 | H27: 0.875 | J27: 9 | K27: =IF(C27="N",8,0) -> 0 | L27: 0 | M27: Pendiente
A28: 2026-07-18 | B28: Sáb | C28: Libre | D28: Libre | J28: =IF(C28="Libre",0,8) -> 0 | K28: =IF(C28="N",8,0) -> 0 | L28: =MAX(J28-8,0) -> 0 | M28: Pendiente
A29: 2026-07-19 | B29: Dom | C29: N | D29: Noche | F29: 0.875 | H29: 0.33333333 | J29: 11 | K29: 9 | L29: 2 | M29: Pendiente
A30: 2026-07-20 | B30: Lun | C30: Libre | D30: Libre | J30: =IF(C30="Libre",0,8) -> 0 | K30: =IF(C30="N",8,0) -> 0 | L30: =MAX(J30-8,0) -> 0 | M30: Pendiente
A31: 2026-07-21 | B31: Mar | C31: TEX | D31: Compensado | J31: 0 | K31: =IF(C31="N",8,0) -> 0 | L31: =MAX(J31-8,0) -> 0 | M31: Pendiente
A32: 2026-07-22 | B32: Mié | C32: T | D32: Tarde | F32: 0.52083333 | H32: 0.875 | J32: 8.5 | K32: =IF(C32="N",8,0) -> 0 | L32: 0 | M32: Pendiente
A33: 2026-07-23 | B33: Jue | C33: N | D33: Noche | F33: 0.875 | H33: 0.33333333 | J33: 11 | K33: 9 | L33: 2 | M33: Pendiente
A34: 2026-07-24 | B34: Vie | C34: N | D34: Noche | F34: 0.875 | H34: 0.33333333 | J34: 11 | K34: 9 | L34: 2 | M34: Pendiente
A35: 2026-07-25 | B35: Sáb | C35: N | D35: Noche | F35: 0.875 | H35: 0.33333333 | J35: 11 | K35: 9 | L35: 2 | M35: Pendiente
A36: 2026-07-26 | B36: Dom | C36: Libre | D36: Libre | J36: =IF(C36="Libre",0,8) -> 0 | K36: =IF(C36="N",8,0) -> 0 | L36: =MAX(J36-8,0) -> 0 | M36: Pendiente
A37: 2026-07-27 | B37: Lun | C37: TEX | D37: Compensado | J37: 0 | K37: =IF(C37="N",8,0) -> 0 | L37: =MAX(J37-8,0) -> 0 | M37: Pendiente
A38: 2026-07-28 | B38: Mar | C38: Libre | D38: Libre | J38: =IF(C38="Libre",0,8) -> 0 | K38: =IF(C38="N",8,0) -> 0 | L38: =MAX(J38-8,0) -> 0 | M38: Pendiente
A39: 2026-07-29 | B39: Mié | C39: T | D39: Tarde | F39: 0.5 | H39: 0.875 | J39: 9 | K39: =IF(C39="N",8,0) -> 0 | L39: 0 | M39: Pendiente
A40: 2026-07-30 | B40: Jue | C40: T | D40: Tarde | F40: 0.5 | H40: 0.875 | J40: 9 | K40: =IF(C40="N",8,0) -> 0 | L40: 0 | M40: Pendiente
A41: 2026-07-31 | B41: Vie | C41: T | D41: Tarde | F41: 0.5 | H41: 0.875 | J41: 9 | K41: =IF(C41="N",8,0) -> 0 | L41: 0 | M41: Pendiente

Sheet PENDIENTES
A1: PENDIENTES - GESTOR MAESTRO
P2: KPIs
P3: Pendientes | Q3: =COUNTIF(F5:F200,"Pendiente") -> 3
A4: ID | B4: Área | C4: Subárea | D4: Tarea | E4: Prioridad | F4: Estado | G4: Fecha Creación | H4: Fecha Límite | I4: Fecha Cierre | J4: Días Abiertos | K4: Avance % | L4: Evidencia | M4: Observaciones | P4: En proceso | Q4: =COUNTIF(F5:F200,"En proceso") -> 0
A5: P-0001 | B5: Universidad | C5: Cálculo II | E5: Alta | F5: Pendiente | J5: =IF(G5="","",TODAY()-G5) | K5: 0 | P5: Completados | Q5: =COUNTIF(F5:F200,"Completado") -> 0
A6: P-0002 | B6: Salud | C6: Cardiología | E6: Crítica | F6: Pendiente | J6: =IF(G6="","",TODAY()-G6) | K6: 0 | P6: Críticos | Q6: =COUNTIF(E5:E200,"Crítica") -> 1
A7: P-0003 | B7: SERPAT | C7: Turnos | E7: Media | F7: Pendiente | J7: =IF(G7="","",TODAY()-G7) | K7: 0
J8: =IF(G8="","",TODAY()-G8) | K8: 0
J9: =IF(G9="","",TODAY()-G9) | K9: 0
J10: =IF(G10="","",TODAY()-G10) | K10: 0
J11: =IF(G11="","",TODAY()-G11) | K11: 0
J12: =IF(G12="","",TODAY()-G12) | K12: 0
J13: =IF(G13="","",TODAY()-G13) | K13: 0
J14: =IF(G14="","",TODAY()-G14) | K14: 0
J15: =IF(G15="","",TODAY()-G15) | K15: 0
J16: =IF(G16="","",TODAY()-G16) | K16: 0
J17: =IF(G17="","",TODAY()-G17) | K17: 0
J18: =IF(G18="","",TODAY()-G18) | K18: 0
J19: =IF(G19="","",TODAY()-G19) | K19: 0
... J54: =IF(G54="","",TODAY()-G54) | K54: 0

Sheet DESARROLLO_PERSONAL
A1: SISTEMA IDENTIDAD
A3: IDENTIDAD
A4: Misión | B4: Construir una vida extraordinaria mediante disciplina, sistemas, aprendizaje continuo y creación de patrimonio.
A5: Visión 2042 | B5: Holding internacional, patrimonio sólido, salud, liderazgo, legado y libertad.
A6: Propósito | B6: Convertir cada día en capital acumulado para Robinson 2042.
A7: Ley 001 | B7: Nunca romper la cadena. Si no puedes avanzar al 100%, avanza al 20%; si no puedes al 20%, avanza al 5%; nunca cero.
A8: Valores | B8: Disciplina, Integridad, Responsabilidad, Aprendizaje, Perseverancia, Humildad, Familia, Excelencia.
A9: Manifiesto | B9: No improvisar. Ejecutar. Construir. Pensar en décadas, actuar hoy.
A11: BIBLIOTECA MAESTRA
A12: Leyendo | B12: Hábitos Atómicos - James Clear | C12: Columna1 | D12: Columna2 | E12: Columna3 | F12: Columna4 | G12: Columna5 | H12: Columna6 | I12: Columna7 | J12: Columna8
A13: Capítulo Actual | B13: 14
A14: Estado | B14: En progreso
A15: Próximos libros | B15: Los 7 Hábitos; Deep Work; Principios; El Inversor Inteligente; Good to Great; Pensar Rápido Pensar Despacio
A17: HÁBITOS
A18: Lectura | B18: 30 min diarios
A19: Gratitud | B19: Diaria
A20: Visualización | B20: Diaria
A21: Ejercicio | B21: 3-5 veces/semana
A22: Inglés | B22: 30 min diarios
A23: Planificación | B23: Diaria
A25: CARÁCTER
A26: Disciplina | B26: Construir mediante ejecución diaria
A27: Constancia | B27: Nunca romper la cadena
A28: Liderazgo | B28: Predicar con el ejemplo
A29: Comunicación | B29: Mejorar continuamente
A30: Paciencia | B30: Pensar a largo plazo
A31: Autocontrol | B31: Dominar emociones
A32: Orden | B32: Todo tiene un sistema
A33: Resiliencia | B33: Aprender de cada dificultad

Sheet 00_GENERADOR_DIA
A1: 00_GENERADOR_DIA — PARAMETROS Y SALIDA PARA MOTOR EXTERNO
A2: PROPÓSITO | B2: Esta hoja NO calcula el día. Python/Codex leerá parámetros, generará cronograma y escribirá salida aquí.
A3: REGLA | B3: No usar fórmulas largas ni dependencias frágiles. Compatible Excel/WPS.
A5: PARÁMETROS EDITABLES
A6: Campo | B6: Valor | C6: Tipo | D6: Fuente futura | E6: Uso del motor | F6: Observación
A7: Fecha del día | B7: 46200 | C7: Fecha | D7: Manual / 20_Registro_Diario | E7: Define día a generar | F7: Editar para probar otra fecha
A8: Tipo día | B8: Turno de Noche | C8: Lista | D8: 20_Registro_Diario | E8: Activa plantilla de jornada | F8: Turno de Noche / Mañana / Tarde / Libre / TEX
A9: Turno SERPAT | B9: 21:00–08:00 | C9: Texto | D9: Calendario laboral | E9: Arma bloques SERPAT | F9: Completar según Shifter
A10: Semana académica | B10: Semana 4 | C10: Texto | D10: 66_T2_Calendario | E10: Trae contenidos | F10: Motor reemplaza por valor real
A11: Prioridad académica | B11: Probabilidad y Estadística | C11: Texto | D11: 62_T2_Evaluaciones | E11: Define primer ramo | F11: Motor calcula por ponderación/plazo
A12: Evaluación crítica | B12: EV-010 / EV-006 / EV-014 — plazo domingo 28 | C12: Texto | D12: 62_T2_Evaluaciones | E12: Genera recordatorio | F12: Motor trae evaluaciones vigentes
A13: Prioridad empresa | B13: MGC / CaptaPropIA / LNH según seguimiento | C13: Texto | D13: 30/33/70/71/76/82 | E13: Define bloque empresa | F13: Motor trae seguimiento pendiente
A14: Nivel energía | B14: Pendiente | C14: Lista | D14: H02_Registro_Salud | E14: Ajusta intensidad | F14: Alto / Medio / Bajo / Pendiente
A15: Presión / alerta salud | B15: Pendiente | C15: Lista | D15: H03_Presión_Log | E15: Activa salud | F15: Normal / Alta / Pendiente
A16: Cierre de mes | B16: No | C16: Lista | D16: Control mensual | E16: Activa cierre mensual | F16: Sí / No
A18: CRONOGRAMA GENERADO POR MOTOR
A19: Orden | B19: Hora inicio | C19: Hora fin | D19: Área | E19: Bloque | F19: Objetivo / instrucción
A20: 1
A21: 2
A22: 3
A23: 4
A24: 5
A25: 6
A26: 7
A27: 8
A28: 9
A29: 10
A30: 11
A31: 12
... A59: 40
A61: SALIDA DOCUMENTAL — COPIAR A WORD

Sheet 00_MOTOR_VIDA_REAL
A1: 00_MOTOR_VIDA_REAL — MAPA OFICIAL DE FUENTES DEL MOTOR
A2: PROPÓSITO | B2: Esta hoja NO calcula. Define qué hojas del Excel C31 debe leer el motor externo Python/Codex.
A3: REGLA | B3: No usar fórmulas aquí. Solo tabla limpia, estable y compatible con Excel/WPS.
A5: ID | B5: Sección | C5: Hoja fuente C31 | D5: Tipo de dato | E5: Campos esperados | F5: Documento alimentado | G5: Uso del motor | H5: Activo | I5: Obligatorio | J5: Observación
A6: M-001 | B6: Vida Real | C6: 20_Registro_Diario | D6: Registro diario | E6: Fecha; tipo día; turno; observaciones | F6: Vida Real; Ancla | G6: Determina apertura, cierre y tipo de jornada | H6: Sí | I6: Sí | J6: Fuente principal del día
A7: M-002 | B7: KPIs | C7: 21_KPI_Diario | D7: Indicadores | E7: Finanzas; Universidad; Salud; Empresas; Excel; Ancla | F7: Vida Real; Ancla | G7: Ajusta cierre y preguntas correctivas | H7: Sí | I7: Sí | J7: Si KPI bajo, activar Ancla crítica
A8: M-003 | B8: Control mensual | C8: 25_Control_Junio / 02_Control_Junio | D8: Control mensual | E8: Fecha; avance; cumplimiento; observaciones | F8: Vida Real; Cierre mensual | G8: Activa cierre mensual y continuidad | H8: Sí | I8: Sí | J8: Usar la hoja vigente según mes
A9: M-004 | B9: Alertas | C9: 90_Alertas_Correcciones | D9: Alertas | E9: Área; indicador; estado; causa; acción | F9: Vida Real; Ancla | G9: Inserta correcciones obligatorias | H9: Sí | I9: Sí | J9: Alerta crítica sube prioridad
A10: M-005 | B10: Universidad ramos | C10: 61_T2_Ramos / 55_T2_CONTENIDOS | D10: Maestro académico | E10: Ramo; unidad; contenido; prioridad; estado | F10: Vida Real | G10: Define qué estudiar | H10: Sí | I10: Sí | J10: No usar materia genérica
A11: M-006 | B11: Universidad evaluaciones | C11: 62_T2_Evaluaciones / 57_T2_EVALUACIONES | D11: Evaluaciones | E11: ID; ramo; porcentaje; fecha; estado; plazo | F11: Vida Real; Ancla | G11: Genera recordatorios de prueba/entrega | H11: Sí | I11: Sí | J11: Evaluación cercana manda prioridad
A12: M-007 | B12: Universidad bloques | C12: 63_T2_Bloques / 56_T2_BLOQUES | D12: Historial estudio | E12: Fecha; ramo; tema; avance; evidencia | F12: Vida Real | G12: Permite continuar donde quedó | H12: Sí | I12: Sí | J12: Debe completarse después de estudiar
A13: M-008 | B13: Universidad errores | C13: 64_T2_Errores / 58_T2_ERRORES | D13: Banco errores | E13: Ramo; tema; error; causa; corrección; estado | F13: Vida Real; Ancla | G13: Obliga a corregir errores abiertos | H13: Sí | I13: Sí | J13: Errores abiertos se reinsertan
A14: M-009 | B14: Calendario académico | C14: 66_T2_Calendario | D14: Calendario | E14: Fecha; semana; clase; contenido; evaluación | F14: Vida Real | G14: Ubica semana y contenidos exactos | H14: Sí | I14: Sí | J14: Base para materia del día
A15: M-010 | B15: Salud diaria | C15: H02_Registro_Salud | D15: Registro salud | E15: Sueño; energía; síntomas; recuperación | F15: Vida Real; Ancla | G15: Ajusta intensidad y descanso | H15: Sí | I15: Sí | J15: Si falta dato, exigir registro
A16: M-011 | B16: Presión arterial | C16: H03_Presión_Log | D16: Registro presión | E16: Hora; presión; pulso; observación | F16: Vida Real; Ancla | G16: Activa bloque de control médico | H16: Sí | I16: Sí | J16: Prioridad salud si presión alta
... A29: M-024 | B29: Generador día | C29: 00_GENERADOR_DIA | D29: Salida/preview | E29: Parámetros; cronograma; salida | F29: Word; Vida Real | G29: Recibe salida del motor externo | H29: Sí | I29: Sí | J29: El motor escribe aquí

Sheet 00_REGLAS_VIDA_REAL
A1: 00_REGLAS_VIDA_REAL — REGLAS OPERATIVAS DEL MOTOR
A2: PROPÓSITO | B2: Esta hoja NO calcula. Define reglas que Python/Codex aplicará para decidir bloques, prioridades y cronograma.
A3: REGLA | B3: No usar fórmulas aquí. Las reglas son datos estructurados para el motor externo.
A5: ID Regla | B5: Área | C5: Condición | D5: Operador | E5: Valor | F5: Prioridad | G5: Bloques activados | H5: Acción del motor | I5: Activa | J5: Fuente | K5: Resultado esperado | L5: No hacer
A6: R-001 | B6: SERPAT | C6: Tipo día | D6: igual | E6: Turno de Noche | F6: 100 | G6: SER-NOCHE | H6: Generar jornada completa: entrega turno anterior, traslado, sueño, salud, estudio, preparación, traslado, turno, entrega día siguiente y cierre post-turno | I6: Sí | J6: 20_Registro_Diario | K6: Día no se cierra antes de SERPAT | L6: Cerrar a media tarde
A7: R-002 | B7: SERPAT | C7: Tipo día | D7: igual | E7: Turno de Mañana | F7: 90 | G7: SER-MANANA | H7: Generar despertar temprano, preparación, trabajo, recuperación, estudio mínimo y cierre nocturno | I7: Sí | J7: 20_Registro_Diario | K7: Día de mantenimiento bien cerrado | L7: Planificar como día libre
A8: R-003 | B8: SERPAT | C8: Tipo día | D8: igual | E8: Turno de Tarde | F8: 90 | G8: SER-TARDE | H8: Generar estudio/empresas en la mañana, preparación al turno, trabajo y cierre liviano | I8: Sí | J8: 20_Registro_Diario | K8: Universidad antes de fatiga | L8: Dejar lo crítico para la noche
A9: R-004 | B9: SERPAT | C9: Tipo día | D9: igual | E9: Libre | F9: 85 | G9: LIBRE | H9: Generar día profundo: universidad fuerte, finanzas, empresas, salud, Ancla y preparación | I9: Sí | J9: 20_Registro_Diario | K9: Avance fuerte sin dispersión | L9: Dormir o improvisar todo el día
A10: R-005 | B10: SERPAT | C10: Tipo día | D10: igual | E10: TEX | F10: 80 | G10: TEX | H10: Generar día de trabajo extra: mantener cadena mínima y no sobrecargar | I10: Sí | J10: 20_Registro_Diario | K10: Continuidad protegida | L10: Exigir intensidad completa
A11: R-006 | B11: Universidad | C11: Evaluación vence en | D11: menor o igual | E11: 7 días | F11: 98 | G11: UNI-EVAL | H11: Insertar recordatorio de evaluación antes del bloque universitario | I11: Sí | J11: 62_T2_Evaluaciones | K11: No perder plazos | L11: Ocultar evaluaciones cercanas
A12: R-007 | B12: Universidad | C12: Evaluación vence en | D12: menor o igual | E12: 2 días | F12: 100 | G12: UNI-CRITICO | H12: Subir prioridad del ramo, reducir empresas y reforzar entrega/prueba | I12: Sí | J12: 62_T2_Evaluaciones | K12: Riesgo académico controlado | L12: Trabajar empresas primero
A13: R-008 | B13: Universidad | C13: Mayor ponderación | D13: igual | E13: Sí | F13: 95 | G13: UNI-PRIORIDAD | H13: Priorizar ramo de mayor impacto si el plazo es cercano | I13: Sí | J13: 62_T2_Evaluaciones | K13: Estudio alineado con nota | L13: Estudiar por gusto
A14: R-009 | B14: Universidad | C14: Último avance | D14: existe | E14: Sí | F14: 92 | G14: UNI-SEGUIMIENTO | H14: Continuar desde último tema, ejercicio, duda o error registrado | I14: Sí | J14: 63_T2_Bloques | K14: No reiniciar desde cero | L14: Repetir contenido sin memoria
A15: R-010 | B15: Universidad | C15: Error abierto | D15: existe | E15: Sí | F15: 94 | G15: UNI-ERRORES | H15: Insertar corrección de error antes de contenido nuevo | I15: Sí | J15: 64_T2_Errores | K15: Error convertido en aprendizaje | L15: Acumular dudas
A16: R-011 | B16: Salud | C16: Turno | D16: igual | E16: Noche | F16: 95 | G16: SAL-NOCHE | H16: Priorizar sueño, presión, alimentación e hidratación | I16: Sí | J16: H02/H03 | K16: Capital biológico protegido | L16: Sacrificar sueño
A17: R-012 | B17: Salud | C17: Presión | D17: igual | E17: Alta | F17: 100 | G17: SAL-ALERTA | H17: Bajar intensidad, registrar presión, agregar observación y posible acción médica | I17: Sí | J17: H03_Presión_Log | K17: Riesgo salud visible | L17: Forzar el plan
... A27: R-022 | B27: Documento | C27: Salida Word | D27: igual | E27: Siempre | F27: 100 | G27: SALIDA-WORD | H27: Generar texto con hora, objetivo, actividad, registro, continuidad y evidencia | I27: Sí | J27: 00_PLANTILLAS_BLOQUES | K27: Vida Real ejecutable | L27: Resumen genérico

Sheet 00_PLANTILLAS_BLOQUES
A1: 00_PLANTILLAS_BLOQUES — BIBLIOTECA OPERATIVA SIN FÓRMULAS
A2: PROPÓSITO | B2: Biblioteca de bloques. El motor externo selecciona filas según reglas y arma Vida Real.
A3: REGLA | B3: No usar fórmulas aquí. Cada fila debe ser un bloque reutilizable.
A5: ID Bloque | B5: Activo | C5: Tipo día permitido | D5: Orden noche | E5: Orden mañana | F5: Orden tarde | G5: Orden libre | H5: Duración min | I5: Área | J5: Nombre bloque | K5: Objetivo | L5: Actividad paso a paso | M5: Registro obligatorio | N5: Continuidad documental | O5: Evidencia mínima | P5: Materia / contenido | Q5: Evaluación / plazo | R5: Seguimiento requerido | S5: Regla mínimo
A6: SER-ENTREGA | B6: Sí | C6: Turno de Noche | D6: 1 | H6: 20 | I6: SERPAT | J6: SALIDA / ENTREGA DEL TURNO | K6: Cerrar correctamente el turno nocturno anterior. | L6: Entregar novedades; revisar observaciones; guardar elementos personales; salir del recinto. | M6: No corresponde | N6: Capítulo 10 — Sistema Laboral SERPAT | O6: ✓ Turno entregado correctamente. ✓ Sin observaciones pendientes. | P6: No aplica | Q6: No aplica | R6: Registrar mentalmente novedades relevantes. | S6: Si hubo incidente, registrar en cierre.
A7: REC-CASA | B7: Sí | C7: Turno de Noche | D7: 2 | H7: 50 | I7: Salud | J7: TRASLADO · LLEGADA A CASA · PREPARACIÓN DEL DESCANSO | K7: Iniciar recuperación física inmediatamente después del turno. | L7: Trasladarse al domicilio; guardar mochila; retirar uniforme; hidratarse; aseo; cerrar cortinas; preparar dormitorio; acostarse. | M7: No corresponde | N7: Capítulo 6 — Sistema Salud | O7: ✓ Recuperación iniciada. ✓ Dormitorio preparado. | P7: No aplica | Q7: No aplica | R7: No usar redes ni abrir tareas estratégicas. | S7: Resolver solo urgencias reales.
A8: SUE-PRINCIPAL | B8: Sí | C8: Turno de Noche | D8: 3 | H8: 320 | I8: Salud | J8: SUEÑO PRINCIPAL | K8: Recuperar energía para sostener la jornada y/o siguiente turno. | L8: Dormir; teléfono en silencio; dormitorio oscuro; evitar interrupciones. | M8: No corresponde | N8: Capítulo 6 — Sistema Salud | O8: ✓ Sueño principal completado. | P8: No aplica | Q8: No aplica | R8: Registrar horas de sueño al despertar. | S8: Si no se logra dormir, reducir intensidad posterior.
A9: SAL-DESPERTAR | B9: Sí | C9: Todos | D9: 4 | E9: 1 | F9: 1 | G9: 1 | H9: 30 | I9: Salud | J9: DESPERTAR · HIGIENE · CONTROL DE SALUD | K9: Iniciar o reiniciar el día con orden y medición de salud. | L9: Levantarse; tender cama; hidratarse; estirar; ducharse; vestirse; tomar medicamento; medir presión; registrar energía. | M9: H02_Registro_Salud; H03_Presión_Log | N9: Capítulo 6 — Sistema Salud | O9: ✓ Día iniciado correctamente. ✓ Salud registrada. | P9: No aplica | Q9: No aplica | R9: Si presión alta, bajar intensidad y registrar observación. | S9: Si no hay tensiómetro, registrar energía y síntomas.
A10: ALI-DESAYUNO | B10: Sí | C10: Todos | E10: 2 | F10: 2 | G10: 2 | H10: 30 | I10: Salud | J10: DESAYUNO / ALIMENTACIÓN | K10: Preparar energía física para sostener la jornada. | L10: Preparar alimentación; hidratarse; ordenar espacio; evaluar energía posterior. | M10: H02_Registro_Salud | N10: Capítulo 6 — Sistema Salud | O10: ✓ Alimentación registrada. ✓ Hidratación realizada. | P10: No aplica | Q10: No aplica | R10: Registrar alimentación y energía posterior. | S10: Evitar gasto hormiga.
A11: SIS-APERTURA | B11: Sí | C11: Todos | D11: 6 | E11: 3 | F11: 3 | G11: 3 | H11: 20 | I11: Sistema | J11: APERTURA OFICIAL DEL SISTEMA | K11: Conocer el estado real antes de ejecutar. | L11: Abrir Excel C31; revisar Dashboard; KPI Diario; calendario laboral; calendario académico; alertas; finanzas; universidad; empresas; salud. | M11: 20_Registro_Diario; 21_KPI_Diario; 25_Control_Junio / 02_Control_Junio; 90_Alertas_Correcciones | N11: Capítulo 3 — Sistema Excel C31 | O11: ✓ Sistema aperturado. ✓ Prioridades confirmadas. | P11: No aplica | Q11: No aplica | R11: Confirmar prioridad académica, laboral y financiera. | S11: Si no alcanza, registrar objetivo y riesgo mínimo.
A12: EVA-REVISION | B12: Sí | C12: Todos | D12: 7 | E12: 4 | F12: 4 | G12: 4 | H12: 15 | I12: Universidad | J12: RECORDATORIO DE EVALUACIONES | K12: Evitar perder pruebas o entregas con plazo cercano. | L12: Abrir Canvas y 62_T2_Evaluaciones; confirmar estado de evaluaciones; revisar pendiente, enviado o por corregir. | M12: 62_T2_Evaluaciones; 66_T2_Calendario; 90_Alertas_Correcciones | N12: Capítulo 4 — Sistema Universidad | O12: ✓ Plazos confirmados. ✓ Riesgo académico visible. | P12: Según ramos activos. | Q12: Según evaluaciones vigentes. | R12: Anotar estado real: pendiente/enviado/revisar nota. | S12: Si hay pendiente crítico, desplazar empresas.
A13: UNI-PROB | B13: Sí | C13: Todos | D13: 8 | E13: 5 | F13: 5 | G13: 5 | H13: 80 | I13: Universidad | J13: PROBABILIDAD Y ESTADÍSTICA | K13: Trabajar el ramo académico de mayor prioridad o evaluación próxima. | L13: Ingresar a Canvas; abrir contenido de la semana; revisar último avance; resolver ejercicios; corregir errores; registrar dudas y avance. | M13: 61_T2_Ramos; 62_T2_Evaluaciones; 63_T2_Bloques; 64_T2_Errores; 65_T2_Dashboard; 66_T2_Calendario | N13: Capítulo 4 — Sistema Universidad | O13: ✓ Bloque universitario completado. ✓ Errores registrados. ✓ Avance actualizado. | P13: Motor debe traer tema exacto desde 66_T2_Calendario y último avance desde 63_T2_Bloques. | Q13: Motor debe traer evaluación vigente desde 62_T2_Evaluaciones. | R13: Registrar dónde quedé, dudas, errores y próxima acción. | S13: Mínimo 5 ejercicios + 1 error corregido.
A14: UNI-COM | B14: Sí | C14: Todos | D14: 9 | E14: 6 | F14: 6 | G14: 6 | H14: 40 | I14: Universidad | J14: COMUNICACIÓN Y ARGUMENTACIÓN | K14: Mantener continuidad argumentativa y preparar actividades de la semana. | L14: Ingresar a Canvas; revisar instrucciones; leer pauta o rúbrica; organizar actividad; registrar fechas importantes y avance. | M14: 61_T2_Ramos; 62_T2_Evaluaciones; 63_T2_Bloques | N14: Capítulo 4 — Sistema Universidad | O14: ✓ Semana organizada. ✓ Actividades registradas. | P14: Motor debe traer actividad exacta desde Canvas/66 si está registrada. | Q14: Motor debe traer evaluación o tarea vigente. | R14: Registrar pendiente exacto: tesis, argumento, conclusión, formato o entrega. | S14: Si hay entrega cercana, cerrar versión antes de empresas.
A15: UNI-CALC | B15: Sí | C15: Todos | D15: 10 | E15: 7 | F15: 7 | G15: 7 | H15: 30 | I15: Universidad | J15: CÁLCULO II | K15: Mantener continuidad matemática evitando pérdida de ritmo. | L15: Abrir Cuaderno Master; revisar contenido de la semana; resolver ejercicios; registrar errores; verificar procedimiento. | M15: 61_T2_Ramos; 63_T2_Bloques; 64_T2_Errores | N15: Capítulo 4 — Sistema Universidad | O15: ✓ Ejercicios desarrollados. ✓ Registro actualizado. | P15: Motor debe traer tema exacto desde 66_T2_Calendario. | Q15: Si hay evaluación, registrar prioridad. | R15: Registrar ejercicio donde quedé y error principal. | S15: Mínimo 2 ejercicios bien verificados.
A16: UNI-FIS | B16: Sí | C16: Todos | D16: 11 | E16: 8 | F16: 8 | G16: 8 | H16: 25 | I16: Universidad | J16: FÍSICA MECÁNICA | K16: Mantener continuidad física y registrar dudas. | L16: Abrir guía; resolver ejercicios programados; registrar dudas para la siguiente sesión. | M16: 61_T2_Ramos; 63_T2_Bloques; 64_T2_Errores | N16: Capítulo 4 — Sistema Universidad | O16: ✓ Física actualizada. ✓ Registro completado. | P16: Motor debe traer tema exacto desde 66_T2_Calendario. | Q16: Si hay evaluación, registrar avance. | R16: Registrar duda concreta y próximo ejercicio. | S16: Mínimo 1 ejercicio completo.
A17: EMP-MGC | B17: Sí | C17: Todos | D17: 12 | E17: 9 | F17: 9 | G17: 9 | H17: 30 | I17: Empresas | J17: MINER GLOBAL CONNECT — CRM Y SEGUIMIENTO | K17: Mantener viva la red estratégica y la inteligencia comercial minera. | L17: Abrir CRM; revisar contactos activos, seguimientos pendientes, oportunidades y mercado; actualizar próxima acción; no abrir negocios nuevos sin evidencia. | M17: 30_MGC_CRM; 33_Seguimientos; 40_Estudio_Empresas; 70_Mercado_MGC | N17: Sistema Empresas — MGC | O17: ✓ CRM actualizado. ✓ Seguimiento programado. | P17: No aplica | Q17: No aplica | R17: Registrar próximo contacto, fecha y acción exacta. | S17: Si universidad crítica, limitar a continuidad mínima.
A18: EMP-HOLDING | B18: Sí | C18: Todos | D18: 13 | E18: 10 | F18: 10 | G18: 10 | H18: 30 | I18: Empresas | J18: LATITUD NORTE HOLDING / LNR / CAPTAPROPIA | K18: Sincronizar proyectos estratégicos sin dispersión. | L18: Revisar LNH, LNR o CaptaPropIA según prioridad; registrar avance, dificultad y siguiente acción; no abrir nuevas líneas. | M18: 71_Mercado_LNR; 76_CaptaPropIA; 82_LNH_Corporate_System | N18: Sistema Empresas / Holding | O18: ✓ Proyecto actualizado. ✓ Siguiente acción definida. | P18: No aplica | Q18: No aplica | R18: Registrar fase, avance, bloqueo y siguiente paso. | S18: No cambiar planificación semanal por impulso.
A19: FIN-DIARIO | B19: Sí | C19: Todos | D19: 14 | E19: 11 | F19: 11 | G19: 11 | H19: 20 | I19: Finanzas | J19: FINANZAS PERSONALES | K19: Mantener caja, gastos, deuda e inversiones visibles. | L19: Registrar ingresos, gastos, pagos, movimientos bancarios, inversiones, saldo disponible y obligaciones pendientes. | M19: 11_Ingresos; 12_Gastos; 13_Deudas; 18_Conciliacion_Bancaria_V3; 25_Control_Junio / 02_Control_Junio | N19: Capítulo 7 — Sistema Finanzas | O19: ✓ Finanzas sincronizadas. ✓ Caja actualizada. | P19: No aplica | Q19: No aplica | R19: Registrar sin movimiento si no hubo gasto. | S19: Si caja baja, activar alerta de gasto.
A20: SAL-ACTIVIDAD | B20: Sí | C20: Todos | E20: 12 | F20: 12 | G20: 12 | H20: 35 | I20: Salud | J20: ACTIVIDAD FÍSICA · PRESIÓN · ENERGÍA | K20: Proteger capital biológico y reiniciar seguimiento de salud. | L20: Caminar o movilidad; respiración; tomar presión si corresponde; registrar energía, pulso, actividad y observaciones. | M20: H02_Registro_Salud; H03_Presión_Log | N20: Capítulo 6 — Sistema Salud | O20: ✓ Actividad registrada. ✓ Energía medida. | P20: No aplica | Q20: No aplica | R20: Registrar efecto físico y mental. | S20: Si hay presión alta, bajar intensidad.
A21: ANCLA | B21: Sí | C21: Todos | E21: 13 | F21: 13 | G21: 13 | H21: 35 | I21: Ancla | J21: ANCLA MENTAL | K21: Corregir ejecución y preparar mentalmente el siguiente bloque o día. | L21: Abrir Ancla Mental; registrar avance, error, decisión estratégica, riesgo, aprendizaje, foco de mañana y prioridad única. | M21: Ancla Mental; 21_KPI_Diario; 90_Alertas_Correcciones | N21: Sistema Ancla Mental | O21: ✓ Ancla actualizada. ✓ Dirección estratégica definida. | P21: No aplica | Q21: No aplica | R21: Preguntas deben salir del KPI o alerta crítica. | S21: No hacer Ancla genérica si hay alertas.
A22: PREP-MANANA | B22: Sí | C22: Todos | E22: 14 | F22: 14 | G22: 14 | H22: 30 | I22: Sistema | J22: PREPARACIÓN DEL DÍA SIGUIENTE | K22: Dejar preparada la siguiente jornada sin improvisación. | L22: Revisar calendario laboral, calendario académico, evaluaciones, alertas, finanzas y documentos abiertos; definir lista obligatoria del día siguiente. | M22: 66_T2_Calendario; 62_T2_Evaluaciones; 90_Alertas_Correcciones; 20_Registro_Diario | N22: Vida Real / Plan diario | O22: ✓ Día siguiente preparado. ✓ Riesgos visibles. | P22: No aplica | Q22: No aplica | R22: Registrar prioridad única del día siguiente. | S22: No cerrar sin preparar mañana.
A23: SER-PREP | B23: Sí | C23: Turno de Noche | D23: 15 | H23: 10 | I23: SERPAT | J23: PREPARACIÓN PARA SERPAT | K23: Salir del domicilio completamente preparado. | L23: Vestir uniforme; preparar mochila, colación, agua, credencial, llaves, teléfono, cargador; verificar domicilio cerrado. | M23: No corresponde | N23: Capítulo 10 — Sistema Laboral SERPAT | O23: ✓ Todo preparado. ✓ Sin pendientes antes de salir. | P23: No aplica | Q23: No aplica | R23: Verificar salida puntual. | S23: No improvisar antes del turno.
A24: SER-TRASLADO | B24: Sí | C24: Turno de Noche | D24: 16 | H24: 60 | I24: SERPAT | J24: TRASLADO A SERPAT | K24: Llegar con anticipación para iniciar el turno sin improvisaciones. | L24: Salir; trasladarse; evitar distracciones; preparar mentalmente turno; llegar; ingresar; revisar novedades; preparar puesto. | M24: No corresponde | N24: Capítulo 10 — Sistema Laboral SERPAT | O24: ✓ Llegada anticipada. ✓ Novedades revisadas. | P24: No aplica | Q24: No aplica | R24: Registrar mentalmente novedades para entrega. | S24: Prioridad seguridad y puntualidad.
A25: SER-PUESTO | B25: Sí | C25: Turno de Noche | D25: 17 | H25: 40 | I25: SERPAT | J25: PREPARACIÓN OPERACIONAL DEL TURNO | K25: Comenzar el turno completamente preparado. | L25: Revisar servicio, protocolos, equipos, llaves, radio, libro de novedades y elementos de seguridad; recibir turno. | M25: No corresponde | N25: Manual Operacional SERPAT | O25: ✓ Puesto operativo. ✓ Inicio preparado. | P25: No aplica | Q25: No aplica | R25: Aclarar dudas antes del inicio oficial. | S25: No entrar desordenado al servicio.
A26: SER-TURNO-NOCHE | B26: Sí | C26: Turno de Noche | D26: 18 | H26: 660 | I26: SERPAT | J26: SERPAT — TURNO NOCTURNO | K26: Ejecutar turno nocturno con profesionalismo y energía administrada. | L26: Cumplir responsabilidades; mantener atención; hidratarse; consumir colación; registrar mentalmente novedades; conducta profesional. | M26: No corresponde | N26: Sistema Laboral SERPAT | O26: ✓ Turno ejecutado correctamente. ✓ Continuidad operacional. | P26: No aplica | Q26: No aplica | R26: Novedades para entrega del día siguiente. | S26: Sin incidentes atribuibles a gestión personal.
A27: SER-ENTREGA-SIG | B27: Sí | C27: Turno de Noche | D27: 19 | H27: 20 | I27: SERPAT | J27: ENTREGA DEL TURNO — DÍA SIGUIENTE | K27: Cerrar correctamente la jornada laboral asegurando continuidad del servicio. | L27: Informar novedades; entregar puesto; responder consultas; verificar observaciones; despedirse formalmente; salir del recinto. | M27: No corresponde | N27: Sistema Laboral SERPAT | O27: ✓ Turno entregado correctamente. ✓ Sin observaciones pendientes. | P27: No aplica | Q27: No aplica | R27: Registrar si hubo novedad relevante. | S27: No dejar observaciones pendientes.
A28: REC-SIG | B28: Sí | C28: Turno de Noche | D28: 20 | H28: 50 | I28: Salud | J28: TRASLADO · LLEGADA AL DOMICILIO — DÍA SIGUIENTE | K28: Comenzar recuperación posterior al turno. | L28: Trasladarse al domicilio; guardar mochila; separar uniforme; hidratarse; aseo personal; preparar dormitorio. | M28: No corresponde | N28: Capítulo 6 — Sistema Salud | O28: ✓ Recuperación iniciada. ✓ Dormitorio preparado. | P28: No aplica | Q28: No aplica | R28: No abrir tareas estratégicas si hay fatiga. | S28: Priorizar sueño.
A29: CIE-POST | B29: Sí | C29: Turno de Noche | D29: 21 | H29: 10 | I29: Cierre | J29: CIERRE OPERACIONAL POST-TURNO | K29: Cerrar el día con evidencia si la energía lo permite. | L29: Actualizar Registro Diario y KPI; registrar cumplimiento, pendientes, aprendizaje, error, decisión siguiente; abrir Ancla Mental. | M29: 20_Registro_Diario; 21_KPI_Diario; Ancla Mental | N29: Vida Real / Ancla | O29: ✓ Día cerrado o postergado con criterio. | P29: No aplica | Q29: No aplica | R29: Si fatiga alta, postergar al primer bloque operativo. | S29: No registrar apurado.
A30: CIERRE-MES | B30: Sí | C30: Todos | E30: 15 | F30: 15 | G30: 15 | H30: 45 | I30: Cierre mensual | J30: CIERRE DE MES / PREPARACIÓN CIERRE | K30: Preparar o ejecutar cierre mensual según fecha. | L30: Revisar ingresos, gastos, deudas, inversión, conciliación, KPI, alertas, universidad, salud y empresas; registrar conclusiones y pendientes. | M30: 24_KPI_Mensual_V4; 25_Control_Junio / 02_Control_Junio; 90_Alertas_Correcciones; 11_Ingresos; 12_Gastos; 13_Deudas | N30: Cierre mensual | O30: ✓ Cierre mensual preparado o ejecutado. | P30: No aplica | Q30: Fin de mes si corresponde. | R30: Registrar conclusiones y acción correctiva. | S30: No cerrar mes sin revisar finanzas.
A31: CIE-DIA | B31: Sí | C31: Todos | E31: 16 | F31: 16 | G31: 16 | H31: 30 | I31: Cierre | J31: CIERRE OPERACIONAL DEL DÍA | K31: Cerrar la jornada con evidencia completa. | L31: Actualizar Registro Diario y KPI Diario; registrar cumplimiento, porcentaje de ejecución, terminados, pendientes, aprendizaje, corrección y prioridad siguiente. | M31: 20_Registro_Diario; 21_KPI_Diario; Ancla Mental | N31: Vida Real / Ancla | O31: ✓ Día cerrado. ✓ Sistema preparado. | P31: No aplica | Q31: No aplica | R31: Cerrar solo cuando la jornada real terminó. | S31: No cerrar antes de SERPAT si hay turno.

Sheet 03_Objetivos_Metas_V4
A1: OBJETIVOS, METAS Y CAPITAL REAL — MAYO 2026
A3: Objetivo maestro | B3: Instalar el Sistema Robinson: control financiero, universidad manejable, CRM operativo, inteligencia de mercado y capital real.
A5: Área | B5: Meta concreta | C5: Cifra / estándar | D5: Fuente / hoja | E5: Resultado actual | F5: % cumplimiento | G5: Estado | H5: Comentario
A6: Caja mínima | B6: Mantener caja mínima operativa | C6: 100000 | D6: 10_Apertura / 14_Inversiones | E6: =SUM('10_Apertura'!C3:C8)+SUMIFS('14_Inversiones'!G:G,'14_Inversiones'!A:A,">=2026-05-01") -> 15732.92 | F6: =IFERROR(E6/C6,0) -> 0.1573292 | G6: =IF(F6>=1,"🟢 Cumple","🟡 Bajo meta") -> 🟡 Bajo meta | H6: Caja real + caja/inversiones líquidas registradas.
A7: Inversión mínima | B7: Mantener inversión mínima activa | C7: 50000 | D7: 14_Inversiones | E7: =SUM('14_Inversiones'!D5:D103) -> 0 | F7: =IFERROR(E7/C7,0) -> 0 | G7: =IF(F7>=1,"🟢 Cumple","🟡 Bajo meta") -> 🟡 Bajo meta | H7: Meta inicial; puede subir en junio.
A8: Registro financiero | B8: Registrar ingresos y gastos | C8: 1 | D8: 11_Ingresos / 12_Gastos | E8: =IF(COUNTA('12_Gastos'!A5:A403)>0,1,0) -> 1 | F8: =E8/C8 -> 1 | G8: =IF(F8>=1,"🟢 Activo","🔴 Sin registro") -> 🟢 Activo | H8: Debe ser 100% real.
A9: Conciliación | B9: Hacer conciliación semanal | C9: 4 | D9: 15_Conciliacion | G9: Manual | H9: Registrar cada semana al cierre.
A10: Empresas analizadas | B10: Analizar 25 a 40 empresas/contactos | C10: 25 | D10: 40_Estudio_Empresas | E10: =COUNTA('40_Estudio_Empresas'!A3:A202) -> 200 | F10: =IFERROR(E10/C10,0) -> 8 | G10: =IF(F10>=1,"🟢 Cumple","🟡 En construcción") -> 🟢 Cumple | H10: No volumen vacío: calidad.
A11: CRM operativo | B11: CRM con contactos clasificados | C11: 1 | D11: 30_MGC_CRM | E11: =IF(COUNTA('30_MGC_CRM'!E5:E213)>0,1,0) -> 1 | F11: =E11/C11 -> 1 | G11: =IF(F11>=1,"🟢 Activo","🔴 Sin CRM") -> 🟢 Activo | H11: Solo empresas/personas ya evaluadas.
A12: Universidad | B12: Mantener bloques de estudio reales | C12: 12 | D12: 51_Bloques_Estudio | E12: =COUNTA('51_Bloques_Estudio'!A5:A204) -> 95 | F12: =IFERROR(E12/C12,0) -> 7.9166667 | G12: =IF(F12>=1,"🟢 Cumple","🟡 En riesgo") -> 🟢 Cumple | H12: Cálculo y Química primero.
A13: Continuidad | B13: Registrar 20 días o más | C13: 20 | D13: 20_Registro_CEO_V4 | E13: =COUNT('20_Registro_CEO_V4'!K5:K34) -> 28 | F13: =IFERROR(E13/C13,0) -> 1.4 | G13: =IF(F13>=1,"🟢 Fuerte","🟡 Medio") -> 🟢 Fuerte | H13: Una fila por día.

Sheet 94_Auditoria_Operativa_C31
A1: 94 AUDITORÍA OPERATIVA C31 — HOJAS VISIBLES / OCULTAS
A2: Objetivo: dejar encendidas sólo las hojas operativas que se usan en el sistema actual. Las hojas antiguas, históricas, backups, referencias y versiones anteriores quedan ocultas al final.
A4: Total hojas | B4: 148
A5: Hojas visibles operativas | B5: 77
A6: Hojas ocultas / referencia / legacy | B6: 71
A7: Criterio | B7: Visible = uso operativo actual. Oculta = histórico, backup, versión anterior, auditoría vieja, plantilla o referencia.
A10: HOJAS VISIBLES | B10: Bloque | C10: Estado | D10: Motivo | E10: Acción
A11: 94_Auditoria_Operativa_C31 | B11: Control / Auditoría | C11: Visible | D11: Uso operativo actual | E11: Mantener encendida
A12: 00_MAPA_OPERATIVO_FINAL | B12: Control / Auditoría | C12: Visible | D12: Uso operativo actual | E12: Mantener encendida
A13: 00_INDICE_OPERATIVO | B13: Control / Auditoría | C13: Visible | D13: Uso operativo actual | E13: Mantener encendida
A14: SEC_01_CEO_CONTROL | B14: Separador operativo | C14: Visible | D14: Uso operativo actual | E14: Mantener encendida
A15: 04_Score_Ejecutivo_Consolidado | B15: Control / Auditoría | C15: Visible | D15: Uso operativo actual | E15: Mantener encendida
A16: 90_Alertas_Correcciones | B16: Control / Auditoría | C16: Visible | D16: Uso operativo actual | E16: Mantener encendida
A17: SEC_02_FINANZAS | B17: Separador operativo | C17: Visible | D17: Uso operativo actual | E17: Mantener encendida
A18: 09_Posicion_Actual | B18: Control / Auditoría | C18: Visible | D18: Uso operativo actual | E18: Mantener encendida
A19: 10_Patrimonio_Financiero | B19: Finanzas | C19: Visible | D19: Uso operativo actual | E19: Mantener encendida
A20: 11_Ingresos | B20: Finanzas | C20: Visible | D20: Uso operativo actual | E20: Mantener encendida
A21: 12_Gastos | B21: Finanzas | C21: Visible | D21: Uso operativo actual | E21: Mantener encendida
... A160: 93_Auditoria_Conciliacion | B160: Otro | C160: Oculta | D160: Histórico / backup / versión anterior / referencia | E160: Apagada al final

Sheet 00_MAPA_OPERATIVO_FINAL
A1: SECCIÓN
A2: 01_CEO_CONTROL
A3: 01_CEO_CONTROL | B3: 04_Score_Ejecutivo_Consolidado | C3: MAESTRA / OPERATIVA | D3: visible | E3: Control ejecutivo central | F3: Debe permanecer visible dentro del sistema operativo 2026
A4: 01_CEO_CONTROL | B4: 09_Posicion_Actual | C4: MAESTRA / OPERATIVA | D4: visible | E4: Control ejecutivo central | F4: Debe permanecer visible dentro del sistema operativo 2026 | G4: Columna1 | H4: Columna2 | I4: Columna3
A5: 01_CEO_CONTROL | B5: 90_Alertas_Correcciones | C5: MAESTRA / OPERATIVA | D5: visible | E5: Control ejecutivo central | F5: Debe permanecer visible dentro del sistema operativo 2026
A6: 02_FINANZAS | B6: 10_Patrimonio_Financiero | C6: MAESTRA / OPERATIVA | D6: visible | E6: Caja, patrimonio, inversiones, deudas y conciliación | F6: Debe permanecer visible dentro del sistema operativo 2026
A7: 02_FINANZAS | B7: 11_Ingresos | C7: MAESTRA / OPERATIVA | D7: visible | E7: Caja, patrimonio, inversiones, deudas y conciliación | F7: Debe permanecer visible dentro del sistema operativo 2026
A8: 02_FINANZAS | B8: 12_Gastos | C8: MAESTRA / OPERATIVA | D8: visible | E8: Caja, patrimonio, inversiones, deudas y conciliación | F8: Debe permanecer visible dentro del sistema operativo 2026
A9: 02_FINANZAS | B9: 13_Deudas | C9: MAESTRA / OPERATIVA | D9: visible | E9: Caja, patrimonio, inversiones, deudas y conciliación | F9: Debe permanecer visible dentro del sistema operativo 2026
A10: 02_FINANZAS | B10: 14_Inversiones | C10: MAESTRA / OPERATIVA | D10: visible | E10: Caja, patrimonio, inversiones, deudas y conciliación | F10: Debe permanecer visible dentro del sistema operativo 2026
A11: 02_FINANZAS | B11: 18_Conciliacion_Bancaria_V2 | C11: MAESTRA / OPERATIVA | D11: visible | E11: Caja, patrimonio, inversiones, deudas y conciliación | F11: Debe permanecer visible dentro del sistema operativo 2026
A12: 03_VIDA_REAL_SALUD | B12: 20_Registro_Diario | C12: MAESTRA / OPERATIVA | D12: visible | E12: Calidad de vida, energía, cumplimiento, hábitos y Divina Obsesión | F12: Debe permanecer visible dentro del sistema operativo 2026
A13: 03_VIDA_REAL_SALUD | B13: 21_KPI_Diario | C13: MAESTRA / OPERATIVA | D13: visible | E13: Calidad de vida, energía, cumplimiento, hábitos y Divina Obsesión | F13: Debe permanecer visible dentro del sistema operativo 2026
A14: 03_VIDA_REAL_SALUD | B14: 22_KPI_Semanal_V4 | C14: MAESTRA / OPERATIVA | D14: visible | E14: Calidad de vida, energía, cumplimiento, hábitos y Divina Obsesión | F14: Debe permanecer visible dentro del sistema operativo 2026
A15: 03_VIDA_REAL_SALUD | B15: 23_Domingo_CEO | C15: MAESTRA / OPERATIVA | D15: visible | E15: Calidad de vida, energía, cumplimiento, hábitos y Divina Obsesión | F15: Debe permanecer visible dentro del sistema operativo 2026
A16: 03_VIDA_REAL_SALUD | B16: 24_KPI_Mensual_V4 | C16: MAESTRA / OPERATIVA | D16: visible | E16: Calidad de vida, energía, cumplimiento, hábitos y Divina Obsesión | F16: Debe permanecer visible dentro del sistema operativo 2026
... A58: SEPARADOR | B58: SEC_07_LNH_CORPORATE | C58: SECCIÓN | D58: visible | E58: Orden visual por módulos | F58: Separador visible
A60: HOJAS OCULTAS / HISTÓRICAS
A61: HISTÓRICO / OCULTO | B61: 51_Bloques_Estudio | C61: OCULTA | D61: hidden | E61: Respaldo / duplicado / versión anterior | F61: No se elimina información
A62: HISTÓRICO / OCULTO | B62: 54_Ramos_Activos | C62: OCULTA | D62: hidden | E62: Respaldo / duplicado / versión anterior | F62: No se elimina información
A63: HISTÓRICO / OCULTO | B63: 53_Errores_Aprendizaje | C63: OCULTA | D63: hidden | E63: Respaldo / duplicado / versión anterior | F63: No se elimina información
A64: HISTÓRICO / OCULTO | B64: 55_Evaluaciones | C64: OCULTA | D64: hidden | E64: Respaldo / duplicado / versión anterior | F64: No se elimina información
A65: HISTÓRICO / OCULTO | B65: 58_Dashboard_Academico | C65: OCULTA | D65: hidden | E65: Respaldo / duplicado / versión anterior | F65: No se elimina información
A66: HISTÓRICO / OCULTO | B66: CLASIFICACION_MANUAL | C66: OCULTA | D66: hidden | E66: Respaldo / duplicado / versión anterior | F66: No se elimina información
A67: HISTÓRICO / OCULTO | B67: 00_Dashboard_V4 | C67: OCULTA | D67: hidden | E67: Respaldo / duplicado / versión anterior | F67: No se elimina información
A68: HISTÓRICO / OCULTO | B68: FASE_03_LIMPIEZA | C68: OCULTA | D68: hidden | E68: Respaldo / duplicado / versión anterior | F68: No se elimina información
A69: HISTÓRICO / OCULTO | B69: 00_Indice_V6 | C69: OCULTA | D69: hidden | E69: Respaldo / duplicado / versión anterior | F69: No se elimina información
A70: HISTÓRICO / OCULTO | B70: 01_Score_Mayo | C70: OCULTA | D70: hidden | E70: Respaldo / duplicado / versión anterior | F70: No se elimina información
A71: HISTÓRICO / OCULTO | B71: 03_Objetivos_Metas_V4 | C71: OCULTA | D71: hidden | E71: Respaldo / duplicado / versión anterior | F71: No se elimina información
A72: HISTÓRICO / OCULTO | B72: 19_Mapa_Sistema | C72: OCULTA | D72: hidden | E72: Respaldo / duplicado / versión anterior | F72: No se elimina información
... A118: HISTÓRICO / OCULTO | B118: 99_HISTORICO_DEPURADO | C118: OCULTA | D118: hidden | E118: Respaldo / duplicado / versión anterior | F118: No se elimina información

Sheet 00_INDICE_OPERATIVO
A1: FASE O1 - INDICE OPERATIVO
A3: CEO & CONTROL
B4: 20_Registro_Diario
B5: 21_KPI_Diario
B6: 22_KPI_Semanal_V4
B7: 24_KPI_Mensual_V4
B8: AUDITORIA_TOTAL_EXCEL_V7_1
A10: FINANZAS
B11: 11_Ingresos
B12: 12_Gastos
B13: 13_Deudas
B14: 14_Inversiones
B15: 09_Posicion_Actual
B16: 10_Patrimonio_Financiero
B17: 18_Conciliacion_Bancaria_V2
A19: UNIVERSIDAD
B20: 50_Universidad_Master
B21: 54_Ramos_Activos
B22: 55_Evaluaciones
B23: 56_Notas
B24: 57_Matriz_Prioridad
B25: 58_Dashboard_Academico
B26: 59_Control_Trimestral
A28: EMPRESAS
B29: 30_MGC_CRM
B30: 31_Red_Holding
B31: 32_Oportunidades
B32: 33_Seguimientos
B33: 40_Estudio_Empresas
B34: 41_Clasificacion_Empresas
B35: 42_Mapa_Mercado
A37: MARKET INTELLIGENCE
B38: 70_Mercado_MGC
B39: 71_Mercado_LNR
B40: 72_Competencia
B41: 73_Campañas
B42: 74_Analisis_Web
B43: 75_Redes_Sociales
B44: 76_CaptaPropIA
A46: NUEVAS FASES OPERATIVAS CAPTAPROPIA / LNH
A47: 79_CaptaPropIA_Fase_C3 | B47: Hoja funcional creada: tabla, formulas, validaciones, dashboard y filtros.
A48: 80_CaptaPropIA_Fase_C4 | B48: Hoja funcional creada: tabla, formulas, validaciones, dashboard y filtros.
A49: 81_CaptaPropIA_Fase_C5 | B49: Hoja funcional creada: tabla, formulas, validaciones, dashboard y filtros.
A50: 82_LNH_Corporate_System | B50: Hoja funcional creada: tabla, formulas, validaciones, dashboard y filtros.

Sheet 00_Indice_V6
A1: ÍNDICE OPERATIVO V6 — SISTEMA ROBINSON CONSOLIDADO
A3: Área | B3: Hoja principal | C3: Función | D3: Estado V6 | E3: Uso | F3: Nota
A4: Dashboard | B4: 00_Dashboard_V4 | C4: Panel ejecutivo consolidado | D4: Núcleo | E4: Abrir primero | F4: Reemplaza dashboards antiguos eliminados
A5: Objetivos | B5: 03_Objetivos_Metas_V4 | C5: Metas mensuales y capital real | D5: Núcleo | E5: Revisión semanal | F5: Conectado a hojas clave
A6: Registro diario | B6: 20_Registro_CEO_V4 | C6: 1 fila = 1 día | D6: Núcleo | E6: Uso diario | F6: Fuente principal de KPI
A7: KPI semanal | B7: 22_KPI_Semanal_V4 | C7: Promedio semanal correcto | D7: Núcleo | E7: Domingo CEO | F7: Separado nota/%/días
A8: KPI mensual | B8: 24_KPI_Mensual_V4 | C8: Score ejecutivo mayo | D8: Núcleo | E8: Cierre mensual | F8: Score limitado a 100%
A9: Balance | B9: 16_Balance_8Col_V4 | C9: Balance 8 columnas | D9: Núcleo | E9: Cierre mensual | F9: Reemplaza balance antiguo eliminado
A10: Deudas | B10: 13_Deudas | C10: Control deuda real | D10: Finanzas | E10: Actualizar pagos/cargos | F10: Reconstruida V6
A11: Conciliación | B11: 15_Conciliacion | C11: Banco real vs Excel | D11: Finanzas | E11: Cierre semanal | F11: Agregar saldos reales
A12: Empresas | B12: 40_Estudio_Empresas | C12: Investigación profunda | D12: Mercado | E12: Antes de CRM | F12: Alimenta oportunidades
A13: Oportunidades | B13: 32_Oportunidades | C13: Pipeline desde empresas A/B | D13: Mercado | E13: Seguimiento | F13: Conectada a estudio
A14: Universidad | B14: 51/53/55/54/58 | C14: Bloques, errores, evaluaciones | D14: Universidad | E14: Diario/semanal | F14: Mantener separado del Ancla
... A111: FASE FIN V7 | B111: 14_Inversiones_BACKUP_V6_8 | C111: Respaldo inversiones | D111: Histórico | E111: Consulta | F111: No editar
A113: Regla V7 | B113: Movimiento ≠ Posición ≠ Rentabilidad ≠ Patrimonio
A115: AUDITORÍA | B115: AUDITORIA_TOTAL_EXCEL_V7_1 | C115: Auditoría completa del libro | D115: Activo | E115: Revisión general | F115: No borrar
A116: CONCLUSIÓN | B116: Excel V7.1 | C116: Sistema de medición amplio y estructuralmente completo | D116: Activo | E116: Pendiente principal: uso y datos reales

Sheet 05_Estructura_Mensual_2026
A1: 05 ESTRUCTURA MENSUAL 2026 — EXCEL MAESTRO, NO ARCHIVOS MENSUALES
A2: Regla: un solo Excel maestro anual. Cada mes funciona como ciclo: Apertura → Registro → Cierre. El historial, patrimonio, CRM, universidad y red se conservan en el mismo archivo.
A4: Mes | B4: Apertura | C4: Registro diario | D4: Finanzas | E4: Empresas / Holding | F4: Universidad | G4: Divina Obsesión | H4: Conciliación | I4: Cierre | J4: Estado | K4: Próximo paso
A5: Mayo | B5: 10_Apertura | C5: 20_Registro_CEO_V4 / 20_Registro_Diario | D5: 11_Ingresos / 12_Gastos / 13_Deudas / 14_Inversiones | E5: 40→41→32→33→30 | F5: 50-58 Universidad | G5: 20 Registro + 21 KPI + 44 Salud | H5: 15_Conciliacion / 18_Conciliacion_Bancaria_V2 | I5: 17_Cierre_Mayo | J5: Cerrado / en revisión | K5: Completar cierre y traspaso a junio
A6: Junio | B6: 25_Control_Junio | C6: 20_Registro_CEO_V4 / 20_Registro_Diario | D6: Ingresos/Gastos por mes = junio | E6: LNH + MGC + LNR + CaptaPropIA | F6: Inicio T2 | G6: Ancla + Salud + Energía | H6: 18_Conciliacion_Bancaria_V2 | I6: Control mensual junio | J6: Activo | K6: Registrar apertura y metas junio
A7: Julio | B7: 26_Control_Julio | C7: 20_Registro_CEO_V4 / 20_Registro_Diario | D7: Ingresos/Gastos por mes = julio | E7: Holding + red + oportunidades | F7: T2 seguimiento | G7: Ancla + KPI personal | H7: 18_Conciliacion_Bancaria_V2 | I7: Control mensual julio | J7: No iniciado | K7: Copiar saldos de cierre junio
A8: Agosto | B8: 27_Control_Agosto | C8: 20_Registro_CEO_V4 / 20_Registro_Diario | D8: Ingresos/Gastos por mes = agosto | E8: Holding + red + oportunidades | F8: T2/T3 según calendario | G8: Ancla + KPI personal | H8: 18_Conciliacion_Bancaria_V2 | I8: Control mensual agosto | J8: No iniciado | K8: Copiar saldos de cierre julio
A9: Septiembre | B9: Ciclo mensual | C9: Registro anual | D9: Ingresos/Gastos por mes | E9: Holding | F9: Universidad | G9: Ancla | H9: Conciliación | I9: Cierre mensual | J9: No iniciado | K9: Preparar cuando corresponda
A10: Octubre | B10: Ciclo mensual | C10: Registro anual | D10: Ingresos/Gastos por mes | E10: Holding | F10: Universidad | G10: Ancla | H10: Conciliación | I10: Cierre mensual | J10: No iniciado | K10: Preparar cuando corresponda
A11: Noviembre | B11: Ciclo mensual | C11: Registro anual | D11: Ingresos/Gastos por mes | E11: Holding | F11: Universidad | G11: Ancla | H11: Conciliación | I11: Cierre mensual | J11: No iniciado | K11: Preparar cuando corresponda
A12: Diciembre | B12: Ciclo mensual | C12: Registro anual | D12: Ingresos/Gastos por mes | E12: Holding | F12: Universidad | G12: Ancla | H12: Conciliación | I12: Cierre anual | J12: No iniciado | K12: Cerrar año 2026

Sheet SEC_01_CEO_CONTROL
A1: CEO & CONTROL CENTRAL
A2: Sección operativa visible. Las hojas históricas/duplicadas fueron enviadas al final y ocultadas.

Sheet 20_Registro_Diario
A1: 20 Registro Diario | N1: Lista Tipo Día | O1: Uso
A2: Registro de ejecución diaria conectado a KPI y Dashboard. | N2: Libre | O2: Día sin turno
N3: Compensado | O3: Día compensado
A4: Fecha | B4: Tipo Día | C4: Dinero | D4: Trabajo | E4: Universidad | F4: Red / MGC | G4: Salud | H4: Acción clave | I4: Nota /10 | J4: Gasto diario | K4: Semana | L4: Comentario | N4: Permiso Administrativo | O4: Permiso
A5: 46143 | B5: Turno de Noche | C5: Sí | D5: Sí | E5: No | F5: Sí | G5: No | H5: Apertura del mes de Mayo | I5: 10 | J5: 421955 | K5: =IF(A5="","", "Semana "&(WEEKNUM(A5,2)-WEEKNUM(DATE(YEAR(A5),MONTH(A5),1),2)+1)) -> Semana 1 | L5: Se realizo la apertura y correciones al excel del mes de mayo | N5: Vacaciones | O5: Vacaciones
A6: 46144 | B6: Turno de Noche | C6: Sí | D6: No | E6: No | F6: No | G6: No | H6: Revision de consolidacion | I6: 10 | J6: =IF(A6="","",SUMIF('12_Gastos'!A:A,A6,'12_Gastos'!D:D)) -> 74130 | K6: =IF(A6="","", "Semana "&(WEEKNUM(A6,2)-WEEKNUM(DATE(YEAR(A6),MONTH(A6),1),2)+1)) -> Semana 1 | L6: Se realizacion de ingreso de consolidacion y comparativa de lo qye tengo, versus lo que deberia tener | N6: Turno de Mañana | O6: 08:00-17:00
A7: 46145 | B7: Turno de Noche | C7: Sí | D7: Sí | E7: Sí | F7: No | G7: No | H7: Registro de gastos | I7: 10 | J7: =IF(A7="","",SUMIF('12_Gastos'!A:A,A7,'12_Gastos'!D:D)) -> 8490 | K7: =IF(A7="","", "Semana "&(WEEKNUM(A7,2)-WEEKNUM(DATE(YEAR(A7),MONTH(A7),1),2)+1)) -> Semana 1 | L7: Se ingresaron los gastos hechos en el dia | N7: Turno de Tarde | O7: 12:00-21:00
A8: 46146 | B8: Libre | C8: Sí | D8: Sí | E8: No | F8: No | G8: No | H8: Registro de ingresos y gastos | I8: 10 | J8: =IF(A8="","",SUMIF('12_Gastos'!A:A,A8,'12_Gastos'!D:D)) -> 52017 | K8: =IF(A8="","", "Semana "&(WEEKNUM(A8,2)-WEEKNUM(DATE(YEAR(A8),MONTH(A8),1),2)+1)) -> Semana 2 | L8: Se actualizo el ultimo ingreso y gastos | N8: Turno de Noche | O8: 21:00-08:00
A9: 46147 | B9: Libre | C9: Sí | D9: Sí | E9: No | F9: Sí | G9: No | H9: Ingreso de contacto CRM | I9: 10 | J9: 456770 | K9: =IF(A9="","", "Semana "&(WEEKNUM(A9,2)-WEEKNUM(DATE(YEAR(A9),MONTH(A9),1),2)+1)) -> Semana 2 | L9: Se probo el sistema, inclyendo Ancla de registro pero hay eficiencias
A10: 46148 | B10: Libre | C10: Sí | D10: Sí | E10: Sí | F10: No | G10: No | H10: Revision de actividades | I10: 10 | J10: =IF(A10="","",SUMIF('12_Gastos'!A:A,A10,'12_Gastos'!D:D)) -> 25290 | K10: =IF(A10="","", "Semana "&(WEEKNUM(A10,2)-WEEKNUM(DATE(YEAR(A10),MONTH(A10),1),2)+1)) -> Semana 2 | L10: Turno extra, solo ingresos y revision de actividades
A11: 46149 | B11: Libre | C11: Sí | D11: Sí | E11: Sí | F11: No | G11: No | H11: Trabajos y pruebas | I11: 10 | J11: =IF(A11="","",SUMIF('12_Gastos'!A:A,A11,'12_Gastos'!D:D)) -> 231720 | K11: =IF(A11="","", "Semana "&(WEEKNUM(A11,2)-WEEKNUM(DATE(YEAR(A11),MONTH(A11),1),2)+1)) -> Semana 2 | L11: Revision de pruebas y trabajos para el fin de semana
A12: 46150 | B12: Turno de Mañana | C12: Sí | D12: Sí | E12: No | F12: No | G12: No | H12: Revision de actividades | I12: 10 | J12: =IF(A12="","",SUMIF('12_Gastos'!A:A,A12,'12_Gastos'!D:D)) -> 29100 | K12: =IF(A12="","", "Semana "&(WEEKNUM(A12,2)-WEEKNUM(DATE(YEAR(A12),MONTH(A12),1),2)+1)) -> Semana 2 | L12: Turno de dia solo reviosn de actividades
A13: 46151 | B13: Turno de Mañana | C13: Sí | D13: Sí | E13: No | F13: No | G13: No | H13: Revision de actividades | I13: 10 | J13: =IF(A13="","",SUMIF('12_Gastos'!A:A,A13,'12_Gastos'!D:D)) -> 5000 | K13: =IF(A13="","", "Semana "&(WEEKNUM(A13,2)-WEEKNUM(DATE(YEAR(A13),MONTH(A13),1),2)+1)) -> Semana 2 | L13: Turno de dia solo reviosn de actividades
A14: 46152 | B14: Turno de Mañana | C14: Sí | D14: Sí | E14: Sí | F14: No | G14: No | H14: Revision de actividades | I14: 10 | J14: =IF(A14="","",SUMIF('12_Gastos'!A:A,A14,'12_Gastos'!D:D)) -> 18000 | K14: =IF(A14="","", "Semana "&(WEEKNUM(A14,2)-WEEKNUM(DATE(YEAR(A14),MONTH(A14),1),2)+1)) -> Semana 2 | L14: Entrega depruebas y trabajos
A15: 46153 | B15: Turno de Mañana | C15: Sí | D15: Sí | E15: No | F15: No | G15: No | H15: Revision de actividades | I15: 10 | J15: =IF(A15="","",SUMIF('12_Gastos'!A:A,A15,'12_Gastos'!D:D)) -> 37225 | K15: =IF(A15="","", "Semana "&(WEEKNUM(A15,2)-WEEKNUM(DATE(YEAR(A15),MONTH(A15),1),2)+1)) -> Semana 3 | L15: Turno de dia solo reviosn de actividades
A16: 46154 | B16: Libre | C16: Sí | D16: No | E16: No | F16: No | G16: No | H16: Re estrucutracion de GPT | I16: 10 | J16: =IF(A16="","",SUMIF('12_Gastos'!A:A,A16,'12_Gastos'!D:D)) -> 13169 | K16: =IF(A16="","", "Semana "&(WEEKNUM(A16,2)-WEEKNUM(DATE(YEAR(A16),MONTH(A16),1),2)+1)) -> Semana 3 | L16: Inicio de reestrcturacion de gpt
A17: 46155 | B17: Libre | C17: Sí | D17: No | E17: No | F17: No | G17: No | H17: Re estrucutracion de GPT | I17: 10 | J17: =IF(A17="","",SUMIF('12_Gastos'!A:A,A17,'12_Gastos'!D:D)) -> 9310 | K17: =IF(A17="","", "Semana "&(WEEKNUM(A17,2)-WEEKNUM(DATE(YEAR(A17),MONTH(A17),1),2)+1)) -> Semana 3 | L17: Inicio de reestrcturacion de gpt
A18: 46156 | B18: Libre | C18: Sí | D18: Sí | E18: No | F18: No | G18: No | H18: Turno extra | I18: 10 | J18: =IF(A18="","",SUMIF('12_Gastos'!A:A,A18,'12_Gastos'!D:D)) -> 15619 | K18: =IF(A18="","", "Semana "&(WEEKNUM(A18,2)-WEEKNUM(DATE(YEAR(A18),MONTH(A18),1),2)+1)) -> Semana 3 | L18: Turno extra, revision de actividades
A19: 46157 | B19: Libre | C19: Sí | D19: Sí | E19: No | F19: No | G19: No | H19: Pago de compromisos | I19: 10 | J19: =IF(A19="","",SUMIF('12_Gastos'!A:A,A19,'12_Gastos'!D:D)) -> 54065 | K19: =IF(A19="","", "Semana "&(WEEKNUM(A19,2)-WEEKNUM(DATE(YEAR(A19),MONTH(A19),1),2)+1)) -> Semana 3 | L19: Pago de compromisos y revision de actividades, turno extra
A20: 46158 | B20: Turno de Noche | C20: Sí | D20: Sí | E20: Sí | F20: No | G20: No | H20: Pago de compromisos | I20: 10 | J20: =IF(A20="","",SUMIF('12_Gastos'!A:A,A20,'12_Gastos'!D:D)) -> 92910 | K20: =IF(A20="","", "Semana "&(WEEKNUM(A20,2)-WEEKNUM(DATE(YEAR(A20),MONTH(A20),1),2)+1)) -> Semana 3 | L20: Pago de compromisos y revision de actividades, estudio
A21: 46159 | B21: Turno de Noche | C21: Sí | D21: Sí | E21: Sí | F21: No | G21: No | H21: Trabajos y pruebas | I21: 10 | J21: =IF(A21="","",SUMIF('12_Gastos'!A:A,A21,'12_Gastos'!D:D)) -> 850 | K21: =IF(A21="","", "Semana "&(WEEKNUM(A21,2)-WEEKNUM(DATE(YEAR(A21),MONTH(A21),1),2)+1)) -> Semana 3 | L21: Entrega de trabajos y pruebas
... A52: 46190 | B52: Turno de Noche | C52: Sí | D52: Sí | E52: Sí | F52: No | G52: No | H52: Estudio de Probabilidad y estadisticas | I52: 10 | J52: =IF(A52="","",SUMIF('12_Gastos'!A:A,A52,'12_Gastos'!D:D)) -> 18910 | K52: =IF(A52="","", "Semana "&(WEEKNUM(A52,2)-WEEKNUM(DATE(YEAR(A52),MONTH(A52),1),2)+1)) -> Semana 3 | L52: Redaccion del manual de estudio completo
A53: 46191 | B53: Libre | C53: Sí | D53: No | E53: Sí | F53: No | G53: Sí | H53: Revision de excel, correccion del mismo | I53: 10 | K53: =IF(A53="","", "Semana "&(WEEKNUM(A53,2)-WEEKNUM(DATE(YEAR(A53),MONTH(A53),1),2)+1)) -> Semana 3 | L53: Registro de estudios, toma de presion y nuevo formato
A54: 46192 | B54: Compensado | C54: Sí | D54: No | E54: No | F54: No | G54: No | H54: Finiquito y comras | I54: 8 | K54: =IF(A54="","", "Semana "&(WEEKNUM(A54,2)-WEEKNUM(DATE(YEAR(A54),MONTH(A54),1),2)+1)) -> Semana 3 | L54: Retiro y cobro de finiquito y compra
A55: 46193 | B55: Libre | C55: Sí | D55: No | E55: No | F55: No | G55: No | H55: Compras y preparacion dia padre | I55: 7 | J55: =IF(A55="","",SUMIF('12_Gastos'!A:A,A55,'12_Gastos'!D:D)) -> 0 | K55: =IF(A55="","", "Semana "&(WEEKNUM(A55,2)-WEEKNUM(DATE(YEAR(A55),MONTH(A55),1),2)+1)) -> Semana 3 | L55: Compras y preparacion dia del padre
A56: 46194 | B56: Turno de Noche | C56: Sí | D56: Sí | E56: Sí | F56: No | G56: No | H56: Pruebas | I56: 5 | J56: =IF($A56="","",SUMIF('12_Gastos'!$A:$A,$A56,'12_Gastos'!$D:$D)) -> 202150 | K56: =IF($A56="","","Semana "&(WEEKNUM($A56,2)-WEEKNUM(DATE(YEAR($A56),MONTH($A56),1),2)+1)) -> Semana 3 | L56: Pruebas universidad
A57: 46195 | B57: Libre | C57: Sí | D57: No | E57: Sí | F57: Sí | G57: No | H57: Estudios | I57: 10 | J57: =IF(A56="","",SUMIF('12_Gastos'!A:A,A56,'12_Gastos'!D:D)) -> 202150 | K57: =IF(A56="","", "Semana "&(WEEKNUM(A56,2)-WEEKNUM(DATE(YEAR(A56),MONTH(A56),1),2)+1)) -> Semana 3 | L57: Registros
A58: 46196 | B58: Turno de Tarde | C58: Sí | D58: Sí | E58: Sí | F58: Sí | G58: Sí | H58: Estudios, trabajo, registro | I58: 10 | J58: =IF(A58="","",SUMIF('12_Gastos'!A:A,A58,'12_Gastos'!D:D)) -> 2200 | K58: =IF(A58="","", "Semana "&(WEEKNUM(A58,2)-WEEKNUM(DATE(YEAR(A58),MONTH(A58),1),2)+1)) -> Semana 4 | L58: dia nomal
A59: 46197 | B59: Turno de Mañana | C59: Sí | D59: Sí | E59: No | F59: No | G59: No | H59: Trabajo en actualizar vida diaria | I59: 7 | J59: =IF(A59="","",SUMIF('12_Gastos'!A:A,A59,'12_Gastos'!D:D)) -> 5000 | K59: =IF(A59="","", "Semana "&(WEEKNUM(A59,2)-WEEKNUM(DATE(YEAR(A59),MONTH(A59),1),2)+1)) -> Semana 4 | L59: dia nomal
A60: 46198 | B60: Turno de Noche | C60: Sí | D60: Sí | E60: No | F60: No | G60: No | H60: Probabilidad y estadistica | I60: 9 | J60: =IF(A60="","",SUMIF('12_Gastos'!A:A,A60,'12_Gastos'!D:D)) -> 2400 | K60: =IF(A60="","", "Semana "&(WEEKNUM(A60,2)-WEEKNUM(DATE(YEAR(A60),MONTH(A60),1),2)+1)) -> Semana 4 | L60: dia nomal
A61: 46199 | B61: Turno de Noche | C61: Sí | D61: Sí | E61: Sí | F61: No | G61: No | H61: Probabilidad y estadistica | I61: 7 | J61: =IF(A61="","",SUMIF('12_Gastos'!A:A,A61,'12_Gastos'!D:D)) -> 4800 | K61: =IF(A61="","", "Semana "&(WEEKNUM(A61,2)-WEEKNUM(DATE(YEAR(A61),MONTH(A61),1),2)+1)) -> Semana 4 | L61: dia nomal
A62: 46200 | B62: Turno de Noche | C62: Sí | D62: Sí | E62: Sí | F62: No | G62: Sí | H62: Estudios en general | I62: 10 | J62: =IF(A62="","",SUMIF('12_Gastos'!A:A,A62,'12_Gastos'!D:D)) -> 13400 | K62: =IF(A62="","", "Semana "&(WEEKNUM(A62,2)-WEEKNUM(DATE(YEAR(A62),MONTH(A62),1),2)+1)) -> Semana 4 | L62: dia nomal
A63: 46201 | B63: Libre | C63: Sí | D63: Sí | E63: Sí | F63: No | G63: No | H63: Entrega de pruebas y trabajos | I63: 10 | J63: =IF(A63="","",SUMIF('12_Gastos'!A:A,A63,'12_Gastos'!D:D)) -> 800 | K63: =IF(A63="","", "Semana "&(WEEKNUM(A63,2)-WEEKNUM(DATE(YEAR(A63),MONTH(A63),1),2)+1)) -> Semana 4 | L63: dia nomal
A64: 46202 | B64: Libre | C64: Sí | D64: Sí | E64: Sí | F64: Sí | G64: Sí | H64: Estudios, pagos de cuentas | I64: 10 | J64: =IF(A64="","",SUMIF('12_Gastos'!A:A,A64,'12_Gastos'!D:D)) -> 3100 | K64: =IF(A64="","", "Semana "&(WEEKNUM(A64,2)-WEEKNUM(DATE(YEAR(A64),MONTH(A64),1),2)+1)) -> Semana 5 | L64: dia nomal
J65: =IF(A65="","",SUMIF('12_Gastos'!A:A,A65,'12_Gastos'!D:D)) | K65: =IF(A65="","", "Semana "&(WEEKNUM(A65,2)-WEEKNUM(DATE(YEAR(A65),MONTH(A65),1),2)+1))
J66: =IF(A66="","",SUMIF('12_Gastos'!A:A,A66,'12_Gastos'!D:D)) | K66: =IF(A66="","", "Semana "&(WEEKNUM(A66,2)-WEEKNUM(DATE(YEAR(A66),MONTH(A66),1),2)+1))
J67: =IF(A67="","",SUMIF('12_Gastos'!A:A,A67,'12_Gastos'!D:D)) | K67: =IF(A67="","", "Semana "&(WEEKNUM(A67,2)-WEEKNUM(DATE(YEAR(A67),MONTH(A67),1),2)+1))
J68: =IF(A68="","",SUMIF('12_Gastos'!A:A,A68,'12_Gastos'!D:D)) | K68: =IF(A68="","", "Semana "&(WEEKNUM(A68,2)-WEEKNUM(DATE(YEAR(A68),MONTH(A68),1),2)+1))
J69: =IF(A69="","",SUMIF('12_Gastos'!A:A,A69,'12_Gastos'!D:D)) | K69: =IF(A69="","", "Semana "&(WEEKNUM(A69,2)-WEEKNUM(DATE(YEAR(A69),MONTH(A69),1),2)+1))
J70: =IF(A70="","",SUMIF('12_Gastos'!A:A,A70,'12_Gastos'!D:D)) | K70: =IF(A70="","", "Semana "&(WEEKNUM(A70,2)-WEEKNUM(DATE(YEAR(A70),MONTH(A70),1),2)+1))
J71: =IF(A71="","",SUMIF('12_Gastos'!A:A,A71,'12_Gastos'!D:D)) | K71: =IF(A71="","", "Semana "&(WEEKNUM(A71,2)-WEEKNUM(DATE(YEAR(A71),MONTH(A71),1),2)+1))
J72: =IF(A72="","",SUMIF('12_Gastos'!A:A,A72,'12_Gastos'!D:D)) | K72: =IF(A72="","", "Semana "&(WEEKNUM(A72,2)-WEEKNUM(DATE(YEAR(A72),MONTH(A72),1),2)+1))
J73: =IF(A73="","",SUMIF('12_Gastos'!A:A,A73,'12_Gastos'!D:D)) | K73: =IF(A73="","", "Semana "&(WEEKNUM(A73,2)-WEEKNUM(DATE(YEAR(A73),MONTH(A73),1),2)+1))
J74: =IF(A74="","",SUMIF('12_Gastos'!A:A,A74,'12_Gastos'!D:D)) | K74: =IF(A74="","", "Semana "&(WEEKNUM(A74,2)-WEEKNUM(DATE(YEAR(A74),MONTH(A74),1),2)+1))
J75: =IF(A75="","",SUMIF('12_Gastos'!A:A,A75,'12_Gastos'!D:D)) | K75: =IF(A75="","", "Semana "&(WEEKNUM(A75,2)-WEEKNUM(DATE(YEAR(A75),MONTH(A75),1),2)+1))
J76: =IF(A76="","",SUMIF('12_Gastos'!A:A,A76,'12_Gastos'!D:D)) | K76: =IF(A76="","", "Semana "&(WEEKNUM(A76,2)-WEEKNUM(DATE(YEAR(A76),MONTH(A76),1),2)+1))
... J182: =IF(A182="","",SUMIF('12_Gastos'!A:A,A182,'12_Gastos'!D:D)) | K182: =IF(A182="","", "Semana "&(WEEKNUM(A182,2)-WEEKNUM(DATE(YEAR(A182),MONTH(A182),1),2)+1))
K183: =IF(A183="","", "Semana "&(WEEKNUM(A183,2)-WEEKNUM(DATE(YEAR(A183),MONTH(A183),1),2)+1))
K184: =IF(A184="","", "Semana "&(WEEKNUM(A184,2)-WEEKNUM(DATE(YEAR(A184),MONTH(A184),1),2)+1))
K185: =IF(A185="","", "Semana "&(WEEKNUM(A185,2)-WEEKNUM(DATE(YEAR(A185),MONTH(A185),1),2)+1))
K186: =IF(A186="","", "Semana "&(WEEKNUM(A186,2)-WEEKNUM(DATE(YEAR(A186),MONTH(A186),1),2)+1))
K187: =IF(A187="","", "Semana "&(WEEKNUM(A187,2)-WEEKNUM(DATE(YEAR(A187),MONTH(A187),1),2)+1))
K188: =IF(A188="","", "Semana "&(WEEKNUM(A188,2)-WEEKNUM(DATE(YEAR(A188),MONTH(A188),1),2)+1))
K189: =IF(A189="","", "Semana "&(WEEKNUM(A189,2)-WEEKNUM(DATE(YEAR(A189),MONTH(A189),1),2)+1))
K190: =IF(A190="","", "Semana "&(WEEKNUM(A190,2)-WEEKNUM(DATE(YEAR(A190),MONTH(A190),1),2)+1))
K191: =IF(A191="","", "Semana "&(WEEKNUM(A191,2)-WEEKNUM(DATE(YEAR(A191),MONTH(A191),1),2)+1))
K192: =IF(A192="","", "Semana "&(WEEKNUM(A192,2)-WEEKNUM(DATE(YEAR(A192),MONTH(A192),1),2)+1))
K193: =IF(A193="","", "Semana "&(WEEKNUM(A193,2)-WEEKNUM(DATE(YEAR(A193),MONTH(A193),1),2)+1))
K194: =IF(A194="","", "Semana "&(WEEKNUM(A194,2)-WEEKNUM(DATE(YEAR(A194),MONTH(A194),1),2)+1))
... K204: =IF(A204="","", "Semana "&(WEEKNUM(A204,2)-WEEKNUM(DATE(YEAR(A204),MONTH(A204),1),2)+1))

Sheet 21_KPI_Diario
A1: 21 KPI DIARIO V7 — DINÁMICO DESDE REGISTRO DIARIO
A2: Mide conducta diaria desde 20_Registro_Diario. Las filas se calculan automáticamente según fecha y campos Sí/No.
A4: Fecha | B4: Dinero | C4: Trabajo | D4: Universidad | E4: Red / MGC | F4: Salud | G4: KPI Nota (1-10) | H4: KPI Cumplimiento | I4: Estado cumplimiento | J4: Acción dinero | K4: KPI Universidad | L4: KPI Sistema | M4: Estado día | N4: KPI Score
A5: =IF(OR('20_Registro_Diario'!A5="",'20_Registro_Diario'!A5=0),"",'20_Registro_Diario'!A5) -> 46143 | B5: =IF(A5="","",--(LOWER('20_Registro_Diario'!C5)="sí")) -> 1 | C5: =IF(A5="","",--(LOWER('20_Registro_Diario'!D5)="sí")) -> 1 | D5: =IF(A5="","",--(LOWER('20_Registro_Diario'!E5)="sí")) -> 0 | E5: =IF(A5="","",--(LOWER('20_Registro_Diario'!F5)="sí")) -> 1 | F5: =IF(A5="","",--(LOWER('20_Registro_Diario'!G5)="sí")) -> 0 | G5: =IF(A5="","",IFERROR('20_Registro_Diario'!I5,0)) -> 10 | H5: =IF(A5="","",IFERROR(SUM(B5:F5)/5,0)) -> 0.6 | I5: =IF(A5="","",IF(H5>=0.8,"🟢 Fuerte",IF(H5>=0.5,"🟡 En proceso","🔴 Riesgo"))) -> 🟡 En proceso | J5: =IF(A5="","",IF(B5=1,"Sí","No")) -> Sí | K5: =IF(A5="","",IF(D5=1,"Con universidad","Sin universidad")) -> Sin universidad | L5: =IF(A5="","",IF(H5>=0.8,"Alto",IF(H5>=0.5,"Medio","Bajo"))) -> Medio | M5: =IF(A5="","",IF(H5>=0.8,"🟢 Fuerte",IF(H5>=0.5,"🟡 Día útil","🔴 Revisar"))) -> 🟡 Día útil | N5: =IF(A5="","",H5*100) -> 60
A6: =IF(OR('20_Registro_Diario'!A6="",'20_Registro_Diario'!A6=0),"",'20_Registro_Diario'!A6) -> 46144 | B6: =IF(A6="","",--(LOWER('20_Registro_Diario'!C6)="sí")) -> 1 | C6: =IF(A6="","",--(LOWER('20_Registro_Diario'!D6)="sí")) -> 0 | D6: =IF(A6="","",--(LOWER('20_Registro_Diario'!E6)="sí")) -> 0 | E6: =IF(A6="","",--(LOWER('20_Registro_Diario'!F6)="sí")) -> 0 | F6: =IF(A6="","",--(LOWER('20_Registro_Diario'!G6)="sí")) -> 0 | G6: =IF(A6="","",IFERROR('20_Registro_Diario'!I6,0)) -> 10 | H6: =IF(A6="","",IFERROR(SUM(B6:F6)/5,0)) -> 0.2 | I6: =IF(A6="","",IF(H6>=0.8,"🟢 Fuerte",IF(H6>=0.5,"🟡 En proceso","🔴 Riesgo"))) -> 🔴 Riesgo | J6: =IF(A6="","",IF(B6=1,"Sí","No")) -> Sí | K6: =IF(A6="","",IF(D6=1,"Con universidad","Sin universidad")) -> Sin universidad | L6: =IF(A6="","",IF(H6>=0.8,"Alto",IF(H6>=0.5,"Medio","Bajo"))) -> Bajo | M6: =IF(A6="","",IF(H6>=0.8,"🟢 Fuerte",IF(H6>=0.5,"🟡 Día útil","🔴 Revisar"))) -> 🔴 Revisar | N6: =IF(A6="","",H6*100) -> 20
A7: =IF(OR('20_Registro_Diario'!A7="",'20_Registro_Diario'!A7=0),"",'20_Registro_Diario'!A7) -> 46145 | B7: =IF(A7="","",--(LOWER('20_Registro_Diario'!C7)="sí")) -> 1 | C7: =IF(A7="","",--(LOWER('20_Registro_Diario'!D7)="sí")) -> 1 | D7: =IF(A7="","",--(LOWER('20_Registro_Diario'!E7)="sí")) -> 1 | E7: =IF(A7="","",--(LOWER('20_Registro_Diario'!F7)="sí")) -> 0 | F7: =IF(A7="","",--(LOWER('20_Registro_Diario'!G7)="sí")) -> 0 | G7: =IF(A7="","",IFERROR('20_Registro_Diario'!I7,0)) -> 10 | H7: =IF(A7="","",IFERROR(SUM(B7:F7)/5,0)) -> 0.6 | I7: =IF(A7="","",IF(H7>=0.8,"🟢 Fuerte",IF(H7>=0.5,"🟡 En proceso","🔴 Riesgo"))) -> 🟡 En proceso | J7: =IF(A7="","",IF(B7=1,"Sí","No")) -> Sí | K7: =IF(A7="","",IF(D7=1,"Con universidad","Sin universidad")) -> Con universidad | L7: =IF(A7="","",IF(H7>=0.8,"Alto",IF(H7>=0.5,"Medio","Bajo"))) -> Medio | M7: =IF(A7="","",IF(H7>=0.8,"🟢 Fuerte",IF(H7>=0.5,"🟡 Día útil","🔴 Revisar"))) -> 🟡 Día útil | N7: =IF(A7="","",H7*100) -> 60
A8: =IF(OR('20_Registro_Diario'!A8="",'20_Registro_Diario'!A8=0),"",'20_Registro_Diario'!A8) -> 46146 | B8: =IF(A8="","",--(LOWER('20_Registro_Diario'!C8)="sí")) -> 1 | C8: =IF(A8="","",--(LOWER('20_Registro_Diario'!D8)="sí")) -> 1 | D8: =IF(A8="","",--(LOWER('20_Registro_Diario'!E8)="sí")) -> 0 | E8: =IF(A8="","",--(LOWER('20_Registro_Diario'!F8)="sí")) -> 0 | F8: =IF(A8="","",--(LOWER('20_Registro_Diario'!G8)="sí")) -> 0 | G8: =IF(A8="","",IFERROR('20_Registro_Diario'!I8,0)) -> 10 | H8: =IF(A8="","",IFERROR(SUM(B8:F8)/5,0)) -> 0.4 | I8: =IF(A8="","",IF(H8>=0.8,"🟢 Fuerte",IF(H8>=0.5,"🟡 En proceso","🔴 Riesgo"))) -> 🔴 Riesgo | J8: =IF(A8="","",IF(B8=1,"Sí","No")) -> Sí | K8: =IF(A8="","",IF(D8=1,"Con universidad","Sin universidad")) -> Sin universidad | L8: =IF(A8="","",IF(H8>=0.8,"Alto",IF(H8>=0.5,"Medio","Bajo"))) -> Bajo | M8: =IF(A8="","",IF(H8>=0.8,"🟢 Fuerte",IF(H8>=0.5,"🟡 Día útil","🔴 Revisar"))) -> 🔴 Revisar | N8: =IF(A8="","",H8*100) -> 40
A9: =IF(OR('20_Registro_Diario'!A9="",'20_Registro_Diario'!A9=0),"",'20_Registro_Diario'!A9) -> 46147 | B9: =IF(A9="","",--(LOWER('20_Registro_Diario'!C9)="sí")) -> 1 | C9: =IF(A9="","",--(LOWER('20_Registro_Diario'!D9)="sí")) -> 1 | D9: =IF(A9="","",--(LOWER('20_Registro_Diario'!E9)="sí")) -> 0 | E9: =IF(A9="","",--(LOWER('20_Registro_Diario'!F9)="sí")) -> 1 | F9: =IF(A9="","",--(LOWER('20_Registro_Diario'!G9)="sí")) -> 0 | G9: =IF(A9="","",IFERROR('20_Registro_Diario'!I9,0)) -> 10 | H9: =IF(A9="","",IFERROR(SUM(B9:F9)/5,0)) -> 0.6 | I9: =IF(A9="","",IF(H9>=0.8,"🟢 Fuerte",IF(H9>=0.5,"🟡 En proceso","🔴 Riesgo"))) -> 🟡 En proceso | J9: =IF(A9="","",IF(B9=1,"Sí","No")) -> Sí | K9: =IF(A9="","",IF(D9=1,"Con universidad","Sin universidad")) -> Sin universidad | L9: =IF(A9="","",IF(H9>=0.8,"Alto",IF(H9>=0.5,"Medio","Bajo"))) -> Medio | M9: =IF(A9="","",IF(H9>=0.8,"🟢 Fuerte",IF(H9>=0.5,"🟡 Día útil","🔴 Revisar"))) -> 🟡 Día útil | N9: =IF(A9="","",H9*100) -> 60
A10: =IF(OR('20_Registro_Diario'!A10="",'20_Registro_Diario'!A10=0),"",'20_Registro_Diario'!A10) -> 46148 | B10: =IF(A10="","",--(LOWER('20_Registro_Diario'!C10)="sí")) -> 1 | C10: =IF(A10="","",--(LOWER('20_Registro_Diario'!D10)="sí")) -> 1 | D10: =IF(A10="","",--(LOWER('20_Registro_Diario'!E10)="sí")) -> 1 | E10: =IF(A10="","",--(LOWER('20_Registro_Diario'!F10)="sí")) -> 0 | F10: =IF(A10="","",--(LOWER('20_Registro_Diario'!G10)="sí")) -> 0 | G10: =IF(A10="","",IFERROR('20_Registro_Diario'!I10,0)) -> 10 | H10: =IF(A10="","",IFERROR(SUM(B10:F10)/5,0)) -> 0.6 | I10: =IF(A10="","",IF(H10>=0.8,"🟢 Fuerte",IF(H10>=0.5,"🟡 En proceso","🔴 Riesgo"))) -> 🟡 En proceso | J10: =IF(A10="","",IF(B10=1,"Sí","No")) -> Sí | K10: =IF(A10="","",IF(D10=1,"Con universidad","Sin universidad")) -> Con universidad | L10: =IF(A10="","",IF(H10>=0.8,"Alto",IF(H10>=0.5,"Medio","Bajo"))) -> Medio | M10: =IF(A10="","",IF(H10>=0.8,"🟢 Fuerte",IF(H10>=0.5,"🟡 Día útil","🔴 Revisar"))) -> 🟡 Día útil | N10: =IF(A10="","",H10*100) -> 60
A11: =IF(OR('20_Registro_Diario'!A11="",'20_Registro_Diario'!A11=0),"",'20_Registro_Diario'!A11) -> 46149 | B11: =IF(A11="","",--(LOWER('20_Registro_Diario'!C11)="sí")) -> 1 | C11: =IF(A11="","",--(LOWER('20_Registro_Diario'!D11)="sí")) -> 1 | D11: =IF(A11="","",--(LOWER('20_Registro_Diario'!E11)="sí")) -> 1 | E11: =IF(A11="","",--(LOWER('20_Registro_Diario'!F11)="sí")) -> 0 | F11: =IF(A11="","",--(LOWER('20_Registro_Diario'!G11)="sí")) -> 0 | G11: =IF(A11="","",IFERROR('20_Registro_Diario'!I11,0)) -> 10 | H11: =IF(A11="","",IFERROR(SUM(B11:F11)/5,0)) -> 0.6 | I11: =IF(A11="","",IF(H11>=0.8,"🟢 Fuerte",IF(H11>=0.5,"🟡 En proceso","🔴 Riesgo"))) -> 🟡 En proceso | J11: =IF(A11="","",IF(B11=1,"Sí","No")) -> Sí | K11: =IF(A11="","",IF(D11=1,"Con universidad","Sin universidad")) -> Con universidad | L11: =IF(A11="","",IF(H11>=0.8,"Alto",IF(H11>=0.5,"Medio","Bajo"))) -> Medio | M11: =IF(A11="","",IF(H11>=0.8,"🟢 Fuerte",IF(H11>=0.5,"🟡 Día útil","🔴 Revisar"))) -> 🟡 Día útil | N11: =IF(A11="","",H11*100) -> 60
A12: =IF(OR('20_Registro_Diario'!A12="",'20_Registro_Diario'!A12=0),"",'20_Registro_Diario'!A12) -> 46150 | B12: =IF(A12="","",--(LOWER('20_Registro_Diario'!C12)="sí")) -> 1 | C12: =IF(A12="","",--(LOWER('20_Registro_Diario'!D12)="sí")) -> 1 | D12: =IF(A12="","",--(LOWER('20_Registro_Diario'!E12)="sí")) -> 0 | E12: =IF(A12="","",--(LOWER('20_Registro_Diario'!F12)="sí")) -> 0 | F12: =IF(A12="","",--(LOWER('20_Registro_Diario'!G12)="sí")) -> 0 | G12: =IF(A12="","",IFERROR('20_Registro_Diario'!I12,0)) -> 10 | H12: =IF(A12="","",IFERROR(SUM(B12:F12)/5,0)) -> 0.4 | I12: =IF(A12="","",IF(H12>=0.8,"🟢 Fuerte",IF(H12>=0.5,"🟡 En proceso","🔴 Riesgo"))) -> 🔴 Riesgo | J12: =IF(A12="","",IF(B12=1,"Sí","No")) -> Sí | K12: =IF(A12="","",IF(D12=1,"Con universidad","Sin universidad")) -> Sin universidad | L12: =IF(A12="","",IF(H12>=0.8,"Alto",IF(H12>=0.5,"Medio","Bajo"))) -> Bajo | M12: =IF(A12="","",IF(H12>=0.8,"🟢 Fuerte",IF(H12>=0.5,"🟡 Día útil","🔴 Revisar"))) -> 🔴 Revisar | N12: =IF(A12="","",H12*100) -> 40
A13: =IF(OR('20_Registro_Diario'!A13="",'20_Registro_Diario'!A13=0),"",'20_Registro_Diario'!A13) -> 46151 | B13: =IF(A13="","",--(LOWER('20_Registro_Diario'!C13)="sí")) -> 1 | C13: =IF(A13="","",--(LOWER('20_Registro_Diario'!D13)="sí")) -> 1 | D13: =IF(A13="","",--(LOWER('20_Registro_Diario'!E13)="sí")) -> 0 | E13: =IF(A13="","",--(LOWER('20_Registro_Diario'!F13)="sí")) -> 0 | F13: =IF(A13="","",--(LOWER('20_Registro_Diario'!G13)="sí")) -> 0 | G13: =IF(A13="","",IFERROR('20_Registro_Diario'!I13,0)) -> 10 | H13: =IF(A13="","",IFERROR(SUM(B13:F13)/5,0)) -> 0.4 | I13: =IF(A13="","",IF(H13>=0.8,"🟢 Fuerte",IF(H13>=0.5,"🟡 En proceso","🔴 Riesgo"))) -> 🔴 Riesgo | J13: =IF(A13="","",IF(B13=1,"Sí","No")) -> Sí | K13: =IF(A13="","",IF(D13=1,"Con universidad","Sin universidad")) -> Sin universidad | L13: =IF(A13="","",IF(H13>=0.8,"Alto",IF(H13>=0.5,"Medio","Bajo"))) -> Bajo | M13: =IF(A13="","",IF(H13>=0.8,"🟢 Fuerte",IF(H13>=0.5,"🟡 Día útil","🔴 Revisar"))) -> 🔴 Revisar | N13: =IF(A13="","",H13*100) -> 40
A14: =IF(OR('20_Registro_Diario'!A14="",'20_Registro_Diario'!A14=0),"",'20_Registro_Diario'!A14) -> 46152 | B14: =IF(A14="","",--(LOWER('20_Registro_Diario'!C14)="sí")) -> 1 | C14: =IF(A14="","",--(LOWER('20_Registro_Diario'!D14)="sí")) -> 1 | D14: =IF(A14="","",--(LOWER('20_Registro_Diario'!E14)="sí")) -> 1 | E14: =IF(A14="","",--(LOWER('20_Registro_Diario'!F14)="sí")) -> 0 | F14: =IF(A14="","",--(LOWER('20_Registro_Diario'!G14)="sí")) -> 0 | G14: =IF(A14="","",IFERROR('20_Registro_Diario'!I14,0)) -> 10 | H14: =IF(A14="","",IFERROR(SUM(B14:F14)/5,0)) -> 0.6 | I14: =IF(A14="","",IF(H14>=0.8,"🟢 Fuerte",IF(H14>=0.5,"🟡 En proceso","🔴 Riesgo"))) -> 🟡 En proceso | J14: =IF(A14="","",IF(B14=1,"Sí","No")) -> Sí | K14: =IF(A14="","",IF(D14=1,"Con universidad","Sin universidad")) -> Con universidad | L14: =IF(A14="","",IF(H14>=0.8,"Alto",IF(H14>=0.5,"Medio","Bajo"))) -> Medio | M14: =IF(A14="","",IF(H14>=0.8,"🟢 Fuerte",IF(H14>=0.5,"🟡 Día útil","🔴 Revisar"))) -> 🟡 Día útil | N14: =IF(A14="","",H14*100) -> 60
A15: =IF(OR('20_Registro_Diario'!A15="",'20_Registro_Diario'!A15=0),"",'20_Registro_Diario'!A15) -> 46153 | B15: =IF(A15="","",--(LOWER('20_Registro_Diario'!C15)="sí")) -> 1 | C15: =IF(A15="","",--(LOWER('20_Registro_Diario'!D15)="sí")) -> 1 | D15: =IF(A15="","",--(LOWER('20_Registro_Diario'!E15)="sí")) -> 0 | E15: =IF(A15="","",--(LOWER('20_Registro_Diario'!F15)="sí")) -> 0 | F15: =IF(A15="","",--(LOWER('20_Registro_Diario'!G15)="sí")) -> 0 | G15: =IF(A15="","",IFERROR('20_Registro_Diario'!I15,0)) -> 10 | H15: =IF(A15="","",IFERROR(SUM(B15:F15)/5,0)) -> 0.4 | I15: =IF(A15="","",IF(H15>=0.8,"🟢 Fuerte",IF(H15>=0.5,"🟡 En proceso","🔴 Riesgo"))) -> 🔴 Riesgo | J15: =IF(A15="","",IF(B15=1,"Sí","No")) -> Sí | K15: =IF(A15="","",IF(D15=1,"Con universidad","Sin universidad")) -> Sin universidad | L15: =IF(A15="","",IF(H15>=0.8,"Alto",IF(H15>=0.5,"Medio","Bajo"))) -> Bajo | M15: =IF(A15="","",IF(H15>=0.8,"🟢 Fuerte",IF(H15>=0.5,"🟡 Día útil","🔴 Revisar"))) -> 🔴 Revisar | N15: =IF(A15="","",H15*100) -> 40
A16: =IF(OR('20_Registro_Diario'!A16="",'20_Registro_Diario'!A16=0),"",'20_Registro_Diario'!A16) -> 46154 | B16: =IF(A16="","",--(LOWER('20_Registro_Diario'!C16)="sí")) -> 1 | C16: =IF(A16="","",--(LOWER('20_Registro_Diario'!D16)="sí")) -> 0 | D16: =IF(A16="","",--(LOWER('20_Registro_Diario'!E16)="sí")) -> 0 | E16: =IF(A16="","",--(LOWER('20_Registro_Diario'!F16)="sí")) -> 0 | F16: =IF(A16="","",--(LOWER('20_Registro_Diario'!G16)="sí")) -> 0 | G16: =IF(A16="","",IFERROR('20_Registro_Diario'!I16,0)) -> 10 | H16: =IF(A16="","",IFERROR(SUM(B16:F16)/5,0)) -> 0.2 | I16: =IF(A16="","",IF(H16>=0.8,"🟢 Fuerte",IF(H16>=0.5,"🟡 En proceso","🔴 Riesgo"))) -> 🔴 Riesgo | J16: =IF(A16="","",IF(B16=1,"Sí","No")) -> Sí | K16: =IF(A16="","",IF(D16=1,"Con universidad","Sin universidad")) -> Sin universidad | L16: =IF(A16="","",IF(H16>=0.8,"Alto",IF(H16>=0.5,"Medio","Bajo"))) -> Bajo | M16: =IF(A16="","",IF(H16>=0.8,"🟢 Fuerte",IF(H16>=0.5,"🟡 Día útil","🔴 Revisar"))) -> 🔴 Revisar | N16: =IF(A16="","",H16*100) -> 20
... A403: =IF(OR('20_Registro_Diario'!A403="",'20_Registro_Diario'!A403=0),"",'20_Registro_Diario'!A403) | B403: =IF(A403="","",--(LOWER('20_Registro_Diario'!C403)="sí")) | C403: =IF(A403="","",--(LOWER('20_Registro_Diario'!D403)="sí")) | D403: =IF(A403="","",--(LOWER('20_Registro_Diario'!E403)="sí")) | E403: =IF(A403="","",--(LOWER('20_Registro_Diario'!F403)="sí")) | F403: =IF(A403="","",--(LOWER('20_Registro_Diario'!G403)="sí")) | G403: =IF(A403="","",IFERROR('20_Registro_Diario'!I403,0)) | H403: =IF(A403="","",IFERROR(SUM(B403:F403)/5,0)) | I403: =IF(A403="","",IF(H403>=0.8,"🟢 Fuerte",IF(H403>=0.5,"🟡 En proceso","🔴 Riesgo"))) | J403: =IF(A403="","",IF(B403=1,"Sí","No")) | K403: =IF(A403="","",IF(D403=1,"Con universidad","Sin universidad")) | L403: =IF(A403="","",IF(H403>=0.8,"Alto",IF(H403>=0.5,"Medio","Bajo"))) | M403: =IF(A403="","",IF(H403>=0.8,"🟢 Fuerte",IF(H403>=0.5,"🟡 Día útil","🔴 Revisar"))) | N403: =IF(A403="","",H403*100)

Sheet 22_KPI_Semanal_V4
A1: 22 KPI SEMANAL V7 — CICLO MENSUAL 2026 / DINÁMICO
A2: Uso: seleccionar mes activo. La hoja calcula semanas del mes usando 20_Registro_Diario, 11_Ingresos, 12_Gastos, 56_T2_ESTUDIO_Y_ERRORES y 40_Estudio_Empresas. Sirve para junio, julio, agosto y siguientes.
P3: Lista meses
A4: Mes activo | B4: junio | P4: enero
A5: Año activo | B5: 2026 | P5: febrero
A6: Fecha inicio mes | B6: =DATEVALUE("1 "&B4&" "&B5) -> 46174 | P6: marzo
A7: Fecha fin mes | B7: =EOMONTH(B6,0) -> 46203 | P7: abril
A8: Días registrados mes | B8: =COUNTIFS('20_Registro_Diario'!$A$5:$A$403,">="&$B$6,'20_Registro_Diario'!$A$5:$A$403,"<="&$B$7) -> 29 | P8: mayo
P9: junio
A10: Semana | B10: Inicio | C10: Fin | D10: Días calendario | E10: KPI Registro (días) | F10: KPI Cumplimiento | G10: KPI Nota | H10: KPI Score | I10: Gastos | J10: Ingresos | K10: Bloques estudio | L10: Empresas analizadas | M10: Estado KPI | N10: Comentario CEO | P10: julio
A11: Semana 1 | B11: =$B$6+0*7 -> 46174 | C11: =MIN($B$7,B11+6) -> 46180 | D11: =MAX(0,C11-B11+1) -> 7 | E11: =COUNTIFS('20_Registro_Diario'!$A$5:$A$403,">="&B11,'20_Registro_Diario'!$A$5:$A$403,"<="&C11) -> 7 | F11: =IF(E11=0,0,(COUNTIFS('20_Registro_Diario'!$A$5:$A$403,">="&B11,'20_Registro_Diario'!$A$5:$A$403,"<="&C11,'20_Registro_Diario'!$C$5:$C$403,"Sí")+COUNTIFS('20_Registro_Diario'!$A$5:$A$403,">="&B11,'20_Registro_Diario'!$A$5:$A$403,"<="&C11,'20_Registro_Diario'!$D$5:$D$403,"Sí")+COUNTIFS('20_Registro_Diario'!$A$5:$A$403,">="&B11,'20_Registro_Diario'!$A$5:$A$403,"<="&C11,'20_Registro_Diario'!$E$5:$E$403,"Sí")+COUNTIFS('20_Registro_Diario'!$A$5:$A$403,">="&B11,'20_Registro_Diario'!$A$5:$A$403,"<="&C11,'20_Registro_Diario'!$F$5:$F$403,"Sí")+COUNTIFS('20_Registro_Diario'!$A$5:$A$403,">="&B11,'20_Registro_Diario'!$A$5:$A$403,"<="&C11,'20_Registro_Diario'!$G$5:$G$403,"Sí"))/(E11*5)) -> 0.2 | G11: =IFERROR(SUMIFS('20_Registro_Diario'!$I$5:$I$403,'20_Registro_Diario'!$A$5:$A$403,">="&B11,'20_Registro_Diario'!$A$5:$A$403,"<="&C11)/MAX(1,E11),0) -> 8 | H11: =IFERROR(AVERAGE(F11,G11/10),0) -> 0.5 | I11: =SUMIFS('12_Gastos'!$D:$D,'12_Gastos'!$A:$A,">="&B11,'12_Gastos'!$A:$A,"<="&C11) -> 440223 | J11: =SUMIFS('11_Ingresos'!$D:$D,'11_Ingresos'!$A:$A,">="&B11,'11_Ingresos'!$A:$A,"<="&C11) -> 451015.4 | K11: =COUNTIFS('63_T2_Bloques'!$A:$A,">="&B11,'63_T2_Bloques'!$A:$A,"<="&C11) -> 0 | L11: =COUNTIFS('40_Estudio_Empresas'!$B:$B,">="&B11,'40_Estudio_Empresas'!$B:$B,"<="&C11) -> 0 | M11: =IFERROR(IF(H11>=0.8,"🟢 OK",IF(H11>=0.5,"🟡 Medio","🔴 Riesgo")),"🔴 Riesgo") -> 🟡 Medio | P11: agosto
A12: Semana 2 | B12: =$B$6+1*7 -> 46181 | C12: =MIN($B$7,B12+6) -> 46187 | D12: =MAX(0,C12-B12+1) -> 7 | E12: =COUNTIFS('20_Registro_Diario'!$A$5:$A$403,">="&B12,'20_Registro_Diario'!$A$5:$A$403,"<="&C12) -> 7 | F12: =IF(E12=0,0,(COUNTIFS('20_Registro_Diario'!$A$5:$A$403,">="&B12,'20_Registro_Diario'!$A$5:$A$403,"<="&C12,'20_Registro_Diario'!$C$5:$C$403,"Sí")+COUNTIFS('20_Registro_Diario'!$A$5:$A$403,">="&B12,'20_Registro_Diario'!$A$5:$A$403,"<="&C12,'20_Registro_Diario'!$D$5:$D$403,"Sí")+COUNTIFS('20_Registro_Diario'!$A$5:$A$403,">="&B12,'20_Registro_Diario'!$A$5:$A$403,"<="&C12,'20_Registro_Diario'!$E$5:$E$403,"Sí")+COUNTIFS('20_Registro_Diario'!$A$5:$A$403,">="&B12,'20_Registro_Diario'!$A$5:$A$403,"<="&C12,'20_Registro_Diario'!$F$5:$F$403,"Sí")+COUNTIFS('20_Registro_Diario'!$A$5:$A$403,">="&B12,'20_Registro_Diario'!$A$5:$A$403,"<="&C12,'20_Registro_Diario'!$G$5:$G$403,"Sí"))/(E12*5)) -> 0.37142857 | G12: =IFERROR(SUMIFS('20_Registro_Diario'!$I$5:$I$403,'20_Registro_Diario'!$A$5:$A$403,">="&B12,'20_Registro_Diario'!$A$5:$A$403,"<="&C12)/MAX(1,E12),0) -> 10 | H12: =IFERROR(AVERAGE(F12,G12/10),0) -> 0.68571429 | I12: =SUMIFS('12_Gastos'!$D:$D,'12_Gastos'!$A:$A,">="&B12,'12_Gastos'!$A:$A,"<="&C12) -> 71510 | J12: =SUMIFS('11_Ingresos'!$D:$D,'11_Ingresos'!$A:$A,">="&B12,'11_Ingresos'!$A:$A,"<="&C12) -> 2750 | K12: =COUNTIFS('63_T2_Bloques'!$A:$A,">="&B12,'63_T2_Bloques'!$A:$A,"<="&C12) -> 0 | L12: =COUNTIFS('40_Estudio_Empresas'!$B:$B,">="&B12,'40_Estudio_Empresas'!$B:$B,"<="&C12) -> 0 | M12: =IFERROR(IF(H12>=0.8,"🟢 OK",IF(H12>=0.5,"🟡 Medio","🔴 Riesgo")),"🔴 Riesgo") -> 🟡 Medio | P12: septiembre
A13: Semana 3 | B13: =$B$6+2*7 -> 46188 | C13: =MIN($B$7,B13+6) -> 46194 | D13: =MAX(0,C13-B13+1) -> 7 | E13: =COUNTIFS('20_Registro_Diario'!$A$5:$A$403,">="&B13,'20_Registro_Diario'!$A$5:$A$403,"<="&C13) -> 7 | F13: =IF(E13=0,0,(COUNTIFS('20_Registro_Diario'!$A$5:$A$403,">="&B13,'20_Registro_Diario'!$A$5:$A$403,"<="&C13,'20_Registro_Diario'!$C$5:$C$403,"Sí")+COUNTIFS('20_Registro_Diario'!$A$5:$A$403,">="&B13,'20_Registro_Diario'!$A$5:$A$403,"<="&C13,'20_Registro_Diario'!$D$5:$D$403,"Sí")+COUNTIFS('20_Registro_Diario'!$A$5:$A$403,">="&B13,'20_Registro_Diario'!$A$5:$A$403,"<="&C13,'20_Registro_Diario'!$E$5:$E$403,"Sí")+COUNTIFS('20_Registro_Diario'!$A$5:$A$403,">="&B13,'20_Registro_Diario'!$A$5:$A$403,"<="&C13,'20_Registro_Diario'!$F$5:$F$403,"Sí")+COUNTIFS('20_Registro_Diario'!$A$5:$A$403,">="&B13,'20_Registro_Diario'!$A$5:$A$403,"<="&C13,'20_Registro_Diario'!$G$5:$G$403,"Sí"))/(E13*5)) -> 0.48571429 | G13: =IFERROR(SUMIFS('20_Registro_Diario'!$I$5:$I$403,'20_Registro_Diario'!$A$5:$A$403,">="&B13,'20_Registro_Diario'!$A$5:$A$403,"<="&C13)/MAX(1,E13),0) -> 8.5714286 | H13: =IFERROR(AVERAGE(F13,G13/10),0) -> 0.67142857 | I13: =SUMIFS('12_Gastos'!$D:$D,'12_Gastos'!$A:$A,">="&B13,'12_Gastos'!$A:$A,"<="&C13) -> 254230 | J13: =SUMIFS('11_Ingresos'!$D:$D,'11_Ingresos'!$A:$A,">="&B13,'11_Ingresos'!$A:$A,"<="&C13) -> 79750 | K13: =COUNTIFS('63_T2_Bloques'!$A:$A,">="&B13,'63_T2_Bloques'!$A:$A,"<="&C13) -> 0 | L13: =COUNTIFS('40_Estudio_Empresas'!$B:$B,">="&B13,'40_Estudio_Empresas'!$B:$B,"<="&C13) -> 0 | M13: =IFERROR(IF(H13>=0.8,"🟢 OK",IF(H13>=0.5,"🟡 Medio","🔴 Riesgo")),"🔴 Riesgo") -> 🟡 Medio | P13: octubre
A14: Semana 4 | B14: =$B$6+3*7 -> 46195 | C14: =MIN($B$7,B14+6) -> 46201 | D14: =MAX(0,C14-B14+1) -> 7 | E14: =COUNTIFS('20_Registro_Diario'!$A$5:$A$403,">="&B14,'20_Registro_Diario'!$A$5:$A$403,"<="&C14) -> 7 | F14: =IF(E14=0,0,(COUNTIFS('20_Registro_Diario'!$A$5:$A$403,">="&B14,'20_Registro_Diario'!$A$5:$A$403,"<="&C14,'20_Registro_Diario'!$C$5:$C$403,"Sí")+COUNTIFS('20_Registro_Diario'!$A$5:$A$403,">="&B14,'20_Registro_Diario'!$A$5:$A$403,"<="&C14,'20_Registro_Diario'!$D$5:$D$403,"Sí")+COUNTIFS('20_Registro_Diario'!$A$5:$A$403,">="&B14,'20_Registro_Diario'!$A$5:$A$403,"<="&C14,'20_Registro_Diario'!$E$5:$E$403,"Sí")+COUNTIFS('20_Registro_Diario'!$A$5:$A$403,">="&B14,'20_Registro_Diario'!$A$5:$A$403,"<="&C14,'20_Registro_Diario'!$F$5:$F$403,"Sí")+COUNTIFS('20_Registro_Diario'!$A$5:$A$403,">="&B14,'20_Registro_Diario'!$A$5:$A$403,"<="&C14,'20_Registro_Diario'!$G$5:$G$403,"Sí"))/(E14*5)) -> 0.62857143 | G14: =IFERROR(SUMIFS('20_Registro_Diario'!$I$5:$I$403,'20_Registro_Diario'!$A$5:$A$403,">="&B14,'20_Registro_Diario'!$A$5:$A$403,"<="&C14)/MAX(1,E14),0) -> 9 | H14: =IFERROR(AVERAGE(F14,G14/10),0) -> 0.76428571 | I14: =SUMIFS('12_Gastos'!$D:$D,'12_Gastos'!$A:$A,">="&B14,'12_Gastos'!$A:$A,"<="&C14) -> 30900 | J14: =SUMIFS('11_Ingresos'!$D:$D,'11_Ingresos'!$A:$A,">="&B14,'11_Ingresos'!$A:$A,"<="&C14) -> 154000 | K14: =COUNTIFS('63_T2_Bloques'!$A:$A,">="&B14,'63_T2_Bloques'!$A:$A,"<="&C14) -> 0 | L14: =COUNTIFS('40_Estudio_Empresas'!$B:$B,">="&B14,'40_Estudio_Empresas'!$B:$B,"<="&C14) -> 0 | M14: =IFERROR(IF(H14>=0.8,"🟢 OK",IF(H14>=0.5,"🟡 Medio","🔴 Riesgo")),"🔴 Riesgo") -> 🟡 Medio | P14: noviembre
A15: Semana 5 | B15: =$B$6+4*7 -> 46202 | C15: =MIN($B$7,B15+6) -> 46203 | D15: =MAX(0,C15-B15+1) -> 2 | E15: =COUNTIFS('20_Registro_Diario'!$A$5:$A$403,">="&B15,'20_Registro_Diario'!$A$5:$A$403,"<="&C15) -> 1 | F15: =IF(E15=0,0,(COUNTIFS('20_Registro_Diario'!$A$5:$A$403,">="&B15,'20_Registro_Diario'!$A$5:$A$403,"<="&C15,'20_Registro_Diario'!$C$5:$C$403,"Sí")+COUNTIFS('20_Registro_Diario'!$A$5:$A$403,">="&B15,'20_Registro_Diario'!$A$5:$A$403,"<="&C15,'20_Registro_Diario'!$D$5:$D$403,"Sí")+COUNTIFS('20_Registro_Diario'!$A$5:$A$403,">="&B15,'20_Registro_Diario'!$A$5:$A$403,"<="&C15,'20_Registro_Diario'!$E$5:$E$403,"Sí")+COUNTIFS('20_Registro_Diario'!$A$5:$A$403,">="&B15,'20_Registro_Diario'!$A$5:$A$403,"<="&C15,'20_Registro_Diario'!$F$5:$F$403,"Sí")+COUNTIFS('20_Registro_Diario'!$A$5:$A$403,">="&B15,'20_Registro_Diario'!$A$5:$A$403,"<="&C15,'20_Registro_Diario'!$G$5:$G$403,"Sí"))/(E15*5)) -> 1 | G15: =IFERROR(SUMIFS('20_Registro_Diario'!$I$5:$I$403,'20_Registro_Diario'!$A$5:$A$403,">="&B15,'20_Registro_Diario'!$A$5:$A$403,"<="&C15)/MAX(1,E15),0) -> 10 | H15: =IFERROR(AVERAGE(F15,G15/10),0) -> 1 | I15: =SUMIFS('12_Gastos'!$D:$D,'12_Gastos'!$A:$A,">="&B15,'12_Gastos'!$A:$A,"<="&C15) -> 3100 | J15: =SUMIFS('11_Ingresos'!$D:$D,'11_Ingresos'!$A:$A,">="&B15,'11_Ingresos'!$A:$A,"<="&C15) -> 374000 | K15: =COUNTIFS('63_T2_Bloques'!$A:$A,">="&B15,'63_T2_Bloques'!$A:$A,"<="&C15) -> 0 | L15: =COUNTIFS('40_Estudio_Empresas'!$B:$B,">="&B15,'40_Estudio_Empresas'!$B:$B,"<="&C15) -> 0 | M15: =IFERROR(IF(H15>=0.8,"🟢 OK",IF(H15>=0.5,"🟡 Medio","🔴 Riesgo")),"🔴 Riesgo") -> 🟢 OK | P15: diciembre
A18: Resumen mensual | B18: Valor | C18: Estado | D18: Comentario
A19: Días registrados | B19: =SUM(E11:E15) -> 29 | C19: =IF(B19>=20,"🟢 Registrado",IF(B19>=10,"🟡 Parcial","🔴 Bajo")) -> 🟢 Registrado | D19: Desde 20_Registro_Diario
A20: Cumplimiento promedio | B20: =IFERROR(AVERAGE(F11:F15),0) -> 0.53714286 | C20: =IF(B20>=0.8,"🟢 Alto",IF(B20>=0.5,"🟡 Medio","🔴 Bajo")) -> 🟡 Medio | D20: Promedio KPI Cumplimiento
A21: Nota promedio | B21: =IFERROR(SUM(G11:G15)/MAX(1,COUNT(G11:G15)),0) -> 9.1142857 | C21: =IF(B21>=8,"🟢 Alta",IF(B21>=6,"🟡 Media","🔴 Baja")) -> 🟢 Alta | D21: Promedio Nota /10
A22: Score promedio | B22: =IFERROR(SUM(H11:H15)/MAX(1,COUNT(H11:H15)),0) -> 0.72428571 | C22: =IF(B22>=0.8,"🟢 Alto",IF(B22>=0.5,"🟡 Medio","🔴 Bajo")) -> 🟡 Medio | D22: Promedio Score
A23: Gastos mes | B23: =SUM(I11:I15) -> 799963 | C23: =IF(B23<=0,"🟢 Controlado","Revisar") -> Revisar | D23: Desde 12_Gastos
A24: Ingresos mes | B24: =SUM(J11:J15) -> 1061515.4 | C24: =IF(B24>=B23,"🟢 Cubre gastos","🔴 No cubre") -> 🟢 Cubre gastos | D24: Desde 11_Ingresos

Sheet 24_KPI_Mensual_V4
A1: 24 KPI MENSUAL V7 — MES ACTIVO / SISTEMA ROBINSON
A2: KPI mensual dinámico conectado a Registro Diario, Finanzas, Universidad, Empresas y Salud. No queda amarrado a mayo.
P3: Lista meses
A4: Mes activo | B4: junio | P4: enero
A5: Año activo | B5: 2026 | P5: febrero
A6: Fecha inicio | B6: =DATEVALUE("1 "&B4&" "&B5) -> 46174 | P6: marzo
A7: Fecha fin | B7: =EOMONTH(B6,0) -> 46203 | P7: abril
A8: Días registrados | B8: =COUNTIFS('20_Registro_Diario'!$A$5:$A$403,">="&$B$6,'20_Registro_Diario'!$A$5:$A$403,"<="&$B$7) -> 29 | P8: mayo
P9: junio
A10: Área | B10: Meta | C10: Resultado | D10: Cumplimiento % | E10: Estado | F10: Peso | G10: Score | H10: Comentario | I10: KPI Nota | J10: KPI Registro | K10: KPI % | L10: Tipo KPI | M10: Fuente | N10: Comentario técnico | P10: julio
A11: Continuidad | B11: 20 | C11: =COUNTIFS('20_Registro_Diario'!$A$5:$A$403,">="&$B$6,'20_Registro_Diario'!$A$5:$A$403,"<="&$B$7) -> 29 | D11: =IFERROR(MIN(1,C11/B11),0) -> 1 | E11: =IF(D11>=1,"⭐ Dominio",IF(D11>=0.7,"🟢 Cumple",IF(D11>=0.4,"🟡 En proceso","🔴 Riesgo"))) -> ⭐ Dominio | F11: 0.2 | G11: =D11*F11 -> 0.2 | H11: Días registrados en 20_Registro_Diario | I11: =IFERROR(C11,0) -> 29 | J11: =IFERROR(C11,0) -> 29 | K11: =IFERROR(D11*100,0) -> 100 | L11: Registro | M11: 20_Registro_Diario | N11: Continuidad real del mes | P11: agosto
A12: Finanzas | B12: 1 | C12: =IF(AND(COUNTIFS('11_Ingresos'!$A$5:$A$403,">="&$B$6,'11_Ingresos'!$A$5:$A$403,"<="&$B$7)>0,COUNTIFS('12_Gastos'!$A$5:$A$403,">="&$B$6,'12_Gastos'!$A$5:$A$403,"<="&$B$7)>0),1,0) -> 1 | D12: =IFERROR(MIN(1,C12/B12),0) -> 1 | E12: =IF(D12>=1,"⭐ Dominio",IF(D12>=0.7,"🟢 Cumple",IF(D12>=0.4,"🟡 En proceso","🔴 Riesgo"))) -> ⭐ Dominio | F12: 0.2 | G12: =D12*F12 -> 0.2 | H12: Ingresos y gastos del mes activos | I12: =IFERROR(C12,0) -> 1 | J12: =IFERROR(C12,0) -> 1 | K12: =IFERROR(D12*100,0) -> 100 | L12: Cumplimiento | M12: 11/12/18 | N12: Finanzas mide registro real | P12: septiembre
A13: Universidad | B13: 12 | C13: =COUNTIFS('63_T2_Bloques'!$A:$A,">="&$B$6,'63_T2_Bloques'!$A:$A,"<="&$B$7) -> 0 | D13: =IFERROR(MIN(1,C13/B13),0) -> 0 | E13: =IF(D13>=1,"⭐ Dominio",IF(D13>=0.7,"🟢 Cumple",IF(D13>=0.4,"🟡 En proceso","🔴 Riesgo"))) -> 🔴 Riesgo | F13: 0.2 | G13: =D13*F13 -> 0 | H13: Bloques reales de estudio T2 | I13: =IFERROR(C13,0) -> 0 | J13: =IFERROR(C13,0) -> 0 | K13: =IFERROR(D13*100,0) -> 0 | L13: Registro | M13: 56_T2_ESTUDIO_Y_ERRORES | N13: Universidad mide ejecución | P13: octubre
A14: Mercado / Empresas | B14: 10 | C14: =COUNTIFS('40_Estudio_Empresas'!$B:$B,">="&$B$6,'40_Estudio_Empresas'!$B:$B,"<="&$B$7)+COUNTIFS('70_Mercado_MGC'!$A:$A,">="&$B$6,'70_Mercado_MGC'!$A:$A,"<="&$B$7)+COUNTIFS('71_Mercado_LNR'!$A:$A,">="&$B$6,'71_Mercado_LNR'!$A:$A,"<="&$B$7) -> 0 | D14: =IFERROR(MIN(1,C14/B14),0) -> 0 | E14: =IF(D14>=1,"⭐ Dominio",IF(D14>=0.7,"🟢 Cumple",IF(D14>=0.4,"🟡 En proceso","🔴 Riesgo"))) -> 🔴 Riesgo | F14: 0.15 | G14: =D14*F14 -> 0 | H14: Empresas/mercado estudiado | I14: =IFERROR(C14,0) -> 0 | J14: =IFERROR(C14,0) -> 0 | K14: =IFERROR(D14*100,0) -> 0 | L14: Registro | M14: 40/70/71 | N14: MGC, LNR y mercado | P14: noviembre
A15: Salud / Energía | B15: 8 | C15: =IFERROR(COUNTIFS([1]H03_Presión_Log!$A:$A,">="&$B$6,[1]H03_Presión_Log!$A:$A,"<="&$B$7),0) -> 0 | D15: =IFERROR(MIN(1,C15/B15),0) -> 0 | E15: =IF(D15>=1,"⭐ Dominio",IF(D15>=0.7,"🟢 Cumple",IF(D15>=0.4,"🟡 En proceso","🔴 Riesgo"))) -> 🔴 Riesgo | F15: 0.1 | G15: =D15*F15 -> 0 | H15: Control salud/energía | I15: =IFERROR(C15,0) -> 0 | J15: =IFERROR(C15,0) -> 0 | K15: =IFERROR(D15*100,0) -> 0 | L15: Registro | M15: H03/20 | N15: Presión y hábitos | P15: diciembre
A16: Domingo CEO | B16: 4 | C16: =COUNTIF('23_Domingo_CEO'!$A:$A,"<>") -> 8 | D16: =IFERROR(MIN(1,C16/B16),0) -> 1 | E16: =IF(D16>=1,"⭐ Dominio",IF(D16>=0.7,"🟢 Cumple",IF(D16>=0.4,"🟡 En proceso","🔴 Riesgo"))) -> ⭐ Dominio | F16: 0.1 | G16: =D16*F16 -> 0.1 | H16: Cierres semanales | I16: =IFERROR(C16,0) -> 8 | J16: =IFERROR(C16,0) -> 8 | K16: =IFERROR(D16*100,0) -> 100 | L16: Registro | M16: 23_Domingo_CEO | N16: Cierre semanal
A17: Oportunidades | B17: 5 | C17: =0 -> 0 | D17: =IFERROR(MIN(1,C17/B17),0) -> 0 | E17: =IF(D17>=1,"⭐ Dominio",IF(D17>=0.7,"🟢 Cumple",IF(D17>=0.4,"🟡 En proceso","🔴 Riesgo"))) -> 🔴 Riesgo | F17: 0.05 | G17: =D17*F17 -> 0 | H17: Pipeline real | I17: =IFERROR(C17,0) -> 0 | J17: =IFERROR(C17,0) -> 0 | K17: =IFERROR(D17*100,0) -> 0 | L17: Registro | M17: 32_Oportunidades | N17: Oportunidades del mes
A20: SCORE FINAL MES | G20: =SUM(G11:G17) -> 0.5 | H20: =IF(G20>=0.85,"⭐ Dominio",IF(G20>=0.7,"🟢 Meta",IF(G20>=0.45,"🟡 Atención","🔴 Riesgo"))) -> 🟡 Atención | K20: =G20*100 -> 50

Sheet 23_Domingo_CEO
A1: 23 Domingo CEO
A2: Hoja del sistema operativo Robinson 2026.
A4: Semana | B4: Finanzas | C4: Universidad | D4: Red / MGC | E4: Salud | F4: Decisión Semana Siguiente
A5: Semana 2 | B5: Ingresos y Egresos | C5: Solo pruebas del domingo 10 | D5: Contestar mesajes, email y whatsapp | E5: Nada | F5: Retomar con todo, como esta por pauta
A6: Semana 1
A7: Semana 3
A8: Semana 4
A9: Semana 5

Sheet 02_Control_Junio
A1: 02 Control Junio
A2: Hoja del sistema operativo Robinson 2026.
A4: Área | B4: Resultado Mayo | C4: Meta Junio | D4: Acción concreta | E4: Fecha límite | F4: Prioridad | G4: Estado | H4: Observación
A5: Dinero | B5: =IFERROR('24_KPI_Mensual_V4'!$G$20,0) -> 0.5 | F5: Alta | G5: 🟡 En proceso
A6: Caja | B6: =IFERROR('24_KPI_Mensual_V4'!$B$4,"junio") -> junio | C6: 150000 | D6: Recuperar y armar colchon | E6: 46208 | F6: Alta | G6: 🟡 En proceso | H6: Tenia $40,000, recuperar eso y colocarl $60,000 mas
A7: Inversión | B7: 150000 | C7: 650000 | D7: Apoyarse con la rentabilidad | E7: 46208 | F7: Alta | G7: 🟡 En proceso | H7: Hoy tengo $250,000, esperar rentabilidad e inyectar dinero, pero tenemos cambio laboral, por lo tanto estamos mas lentos
A8: Deuda | B8: =IFERROR('24_KPI_Mensual_V4'!$K$20,0) -> 50 | C8: 450000 | D8: Repactar llegar acuerdo | E8: 46208 | F8: Alta | G8: 🟡 En proceso | H8: Al menos pagar un pie para iniciar repactacion, se nos junta la reparacion de la camioneta en le trabajo me lo exigen, y pomerme al dia con Gustabo
A9: Universidad | B9: =IFERROR('24_KPI_Mensual_V4'!$D$13,0) -> 0 | C9: 1 | D9: Retomar estudios | E9: 46189 | F9: Media | G9: =IFERROR(IF(B9>=C9,"🟢 Cumplido",IF(B9>=0.4*C9,"🟡 En proceso","🔴 Riesgo")),"🟡 En proceso") -> 🔴 Riesgo | H9: Tomar vuelito y comenzar ahora estudiar
A10: Red / Empresas / Holding | B10: =IFERROR('24_KPI_Mensual_V4'!$D$14,0) -> 0 | C10: 1 | D10: Iniciar actividades según Vida Real | E10: 46189 | F10: Media | G10: =IFERROR(IF(B10>=C10,"🟢 Cumplido",IF(B10>=0.4*C10,"🟡 En proceso","🔴 Riesgo")),"🟡 En proceso") -> 🔴 Riesgo | H10: Hacer actividades diarias y mover todo
A11: Salud | B11: =IFERROR('24_KPI_Mensual_V4'!$D$15,0) -> 0 | C11: 1 | D11: Registrar informacion | E11: 46189 | F11: Media | G11: =IFERROR(IF(B11>=C11,"🟢 Cumplido",IF(B11>=0.4*C11,"🟡 En proceso","🔴 Riesgo")),"🟡 En proceso") -> 🔴 Riesgo | H11: Accion inmediata
A12: Trabajo | B12: =COUNTIFS('20_Registro_Diario'!$A$5:$A$403,">="&'24_KPI_Mensual_V4'!$B$6,'20_Registro_Diario'!$A$5:$A$403,"<="&'24_KPI_Mensual_V4'!$B$7,'20_Registro_Diario'!$D$5:$D$403,"Sí") -> 16 | C12: 20 | D12: Cambio de empresa | E12: 46181 | F12: Media | G12: =IFERROR(IF(B12>=C12,"🟢 Cumplido",IF(B12>=0.4*C12,"🟡 En proceso","🔴 Riesgo")),"🟡 En proceso") -> 🟡 En proceso | H12: Proceso de adaptacion

Sheet 90_Alertas_Correcciones
A1: 90 ALERTAS Y CORRECCIONES — SISTEMA DE MEJORA CONTINUA
A2: Panel central para detectar desviaciones entre meta, real, resultado y acción correctiva. No reemplaza hojas existentes; consolida señales para revisión diaria/semanal.
A4: Área | B4: Indicador | C4: Meta | D4: Real | E4: Desviación | F4: Estado | G4: Alerta | H4: Causa probable | I4: Acción correctiva | J4: Frecuencia | K4: Fuente | L4: Responsable
A5: CEO / Vida Real | B5: Cumplimiento diario | C5: 1 | D5: 0 | E5: =IFERROR(D5-C5,0) -> -1 | F5: =IF(D5>=C5,"🟢 OK","🔴 Crítico") -> 🔴 Crítico | G5: Revisar si el día se está ejecutando según plan | H5: Falta de registro, energía baja, exceso de carga | I5: Reprogramar bloques pendientes y registrar causa | J5: Diaria | K5: 21_KPI_Diario | L5: Robinson
A6: Finanzas | B6: Gasto mensual | C6: 200000 | D6: 0 | E6: =IFERROR(D6-C6,0) -> -200000 | F6: =IF(D6<=C6,"🟢 OK",IF(D6<=C6*1.25,"🟡 Atención","🔴 Crítico")) -> 🟢 OK | G6: Gasto superior a meta | H6: Gasto hormiga, compras no planificadas | I6: Bloqueo gasto no esencial 7 días | J6: Semanal/Mensual | K6: 12_Gastos | L6: Robinson
A7: Finanzas | B7: Conciliación bancaria | C7: 0 | D7: 0 | E7: =IFERROR(D7-C7,0) -> 0 | F7: =IF(ABS(D7)<=1000,"🟢 OK",IF(ABS(D7)<=50000,"🟡 Atención","🔴 Crítico")) -> 🟢 OK | G7: Diferencia bancaria detectada | H7: Registro incompleto o saldo real no actualizado | I7: Cruzar cartola bancaria vs Excel | J7: Semanal | K7: 18_Conciliacion_Bancaria_V2 | L7: Robinson
A8: Inversiones | B8: Posición actualizada | C8: 1 | D8: 0 | E8: =IFERROR(D8-C8,0) -> -1 | F8: =IF(D8>=C8,"🟢 OK","🔴 Crítico") -> 🔴 Crítico | G8: Actualizar Racional/APV/Banco Estado | H8: No se ingresó posición actual | I8: Actualizar acciones, precio ETF, valor inversión y TC | J8: Mensual | K8: 09_Posicion_Actual | L8: Robinson
A9: Universidad | B9: Evaluaciones atrasadas | C9: 0 | D9: 0 | E9: =IFERROR(D9-C9,0) -> 0 | F9: =IF(D9<=C9,"🟢 OK",IF(D9<=2,"🟡 Atención","🔴 Crítico")) -> 🟢 OK | G9: Evaluación vencida o sin preparación | H9: Fecha no cargada o bloque insuficiente | I9: Reprogramar evaluación y abrir bloques en hoja 56 | J9: Diaria/Semanal | K9: 57_T2_EVALUACIONES_NOTAS | L9: Robinson
A10: Universidad | B10: Horas estudiadas | C10: 12 | D10: 0 | E10: =IFERROR(D10-C10,0) -> -12 | F10: =IF(D10>=C10,"🟢 OK",IF(D10>=C10*0.7,"🟡 Atención","🔴 Crítico")) -> 🔴 Crítico | G10: Horas de estudio bajo meta | H10: Trabajo, cansancio, mala planificación | I10: Agendar bloques reales en 56_T2_ESTUDIO_Y_ERRORES | J10: Semanal | K10: 56_T2_ESTUDIO_Y_ERRORES | L10: Robinson
A11: Universidad | B11: Errores acumulados | C11: 5 | D11: 0 | E11: =IFERROR(D11-C11,0) -> -5 | F11: =IF(D11<=C11,"🟢 OK",IF(D11<=C11*1.5,"🟡 Atención","🔴 Crítico")) -> 🟢 OK | G11: Errores de aprendizaje acumulados | H11: Materia no comprendida o falta de práctica | I11: Registrar error, causa raíz y corrección en hoja 56 | J11: Semanal | K11: 56_T2_ESTUDIO_Y_ERRORES | L11: Robinson
A12: Empresas / MGC | B12: Empresas estudiadas | C12: 3 | D12: 0 | E12: =IFERROR(D12-C12,0) -> -3 | F12: =IF(D12>=C12,"🟢 OK",IF(D12>=C12*0.7,"🟡 Atención","🔴 Crítico")) -> 🔴 Crítico | G12: Bajo análisis empresarial | H12: Falta de bloques de inteligencia | I12: Agendar análisis de empresas prioritarias | J12: Semanal | K12: 40_Estudio_Empresas | L12: Robinson
A13: Market Intelligence | B13: Mercado MGC/LNR poblado | C13: 3 | D13: 0 | E13: =IFERROR(D13-C13,0) -> -3 | F13: =IF(D13>=C13,"🟢 OK",IF(D13>=C13*0.7,"🟡 Atención","🔴 Crítico")) -> 🔴 Crítico | G13: Market Intelligence sin datos suficientes | H13: Estructura existe pero no se está poblando | I13: Registrar empresas, competencia y hallazgos reales | J13: Semanal | K13: 70_Mercado_MGC / 71_Mercado_LNR | L13: Robinson
A14: Campañas / Embudos | B14: Campañas registradas | C14: 1 | D14: 0 | E14: =IFERROR(D14-C14,0) -> -1 | F14: =IF(D14>=C14,"🟢 OK","🔴 Crítico") -> 🔴 Crítico | G14: Sin aprendizaje de campañas | H14: No hay pruebas o análisis de embudos | I14: Registrar campañas observadas o propias | J14: Mensual | K14: 73_Campañas | L14: Robinson
A15: CaptaPropIA | B15: Avance tareas MVP | C15: 0.25 | D15: 0 | E15: =IFERROR(D15-C15,0) -> -0.25 | F15: =IF(D15>=C15,"🟢 OK",IF(D15>=C15*0.7,"🟡 Atención","🔴 Crítico")) -> 🔴 Crítico | G15: MVP bajo avance esperado | H15: Tareas sin prioridad o sin ejecución | I15: Definir siguiente sprint mínimo | J15: Semanal/Mensual | K15: 76_CaptaPropIA | L15: Robinson
A16: Salud / Energía | B16: Control salud | C16: 5 | D16: 0 | E16: =IFERROR(D16-C16,0) -> -5 | F16: =IF(D16>=C16,"🟢 OK",IF(D16>=C16*0.7,"🟡 Atención","🔴 Crítico")) -> 🔴 Crítico | G16: Salud/energía poco registrada | H16: No se mide caminata, descanso o energía | I16: Registrar caminata, sueño, energía y recuperación | J16: Semanal | K16: 44_Salud | L16: Robinson
A22: REVISIÓN MENSUAL CEO | B22: Resultado | C22: Diagnóstico | D22: Decisión | E22: Mes | F22: Comentario
A23: ¿Qué área estuvo más débil?
A24: ¿Qué corrección se aplicará el próximo mes?
A25: ¿Qué hábito se debe reforzar?
A26: ¿Qué gasto se debe cortar o reducir?
A27: ¿Qué ramo o materia requiere refuerzo?
A28: ¿Qué mercado debe investigarse más?
A29: ¿Qué proyecto debe priorizarse?
A31: LNR / Market Intelligence | B31: Auditoría LNR completada | C31: 1 | D31: 1 | E31: =IFERROR(D31-C31,0) -> 0 | F31: =IF(D31>=C31,"🟢 OK","🔴 Crítico") -> 🟢 OK | G31: Existe diagnóstico profundo LNR | H31: Bloque de mercado aún sin datos reales | I31: Poblar 71-75 semanalmente | J31: Semanal | K31: 77_Auditoria_LNR_Mercado | L31: Robinson

Sheet 04_Score_Ejecutivo_Consolidado
A1: 04 SCORE EJECUTIVO CONSOLIDADO 2026 — MASTER ANUAL
A2: Consolida KPI mensual, patrimonio, universidad, empresas, conciliación y estado ejecutivo. No reemplaza los cierres mensuales; los resume.
A4: Mes | B4: Ingresos | C4: Gastos reales | D4: Saldo teórico | E4: Saldo real banco | F4: Diferencia conciliación | G4: Empresas estudiadas | H4: Oportunidades | I4: Universidad KPI | J4: Salud KPI | K4: Score ejecutivo 0-100 | L4: Estado | M4: Cierre | N4: Próxima decisión
A5: mayo | B5: =SUMIF('11_Ingresos'!$K$5:$K$204,A5,'11_Ingresos'!$C$5:$C$204) -> 1130484 | C5: =SUMIFS('12_Gastos'!$D$5:$D$403,'12_Gastos'!$I$5:$I$403,A5,'12_Gastos'!$J$5:$J$403,"Gasto real") -> 0 | D5: =IF(A5='18_Conciliacion_Bancaria_V2'!$B$3,'18_Conciliacion_Bancaria_V2'!B12,IF(A5="mayo",'15_Conciliacion'!B12,0)) -> 1144342 | E5: =IF(A5='18_Conciliacion_Bancaria_V2'!$B$3,'18_Conciliacion_Bancaria_V2'!B22,IF(A5="mayo",'15_Conciliacion'!B22,0)) -> 90470 | F5: =IF(A5='18_Conciliacion_Bancaria_V2'!$B$3,'18_Conciliacion_Bancaria_V2'!B26,IF(A5="mayo",'15_Conciliacion'!B26,0)) -> -1053872 | G5: =COUNTA('40_Estudio_Empresas'!C3:C204) -> 1 | H5: =COUNTIF('32_Oportunidades'!A5:A204,"?*") -> 0 | I5: =IF(A5="mayo",'01_Score_Mayo'!B5,0) -> 0 | J5: =IF(A5="mayo",'01_Score_Mayo'!B8,0) -> 0 | K5: =IFERROR(IF(A5="mayo",'01_Score_Mayo'!I11,AVERAGE(IFERROR(B5/MAX(1,B5+C5),0),IFERROR(G5/25,0),IFERROR(H5/5,0))*100),0) -> 0 | L5: =IF(K5>=90,"⭐ Dominio",IF(K5>=70,"🟢 Cumple",IF(K5>=40,"🟡 En proceso","🔴 Riesgo"))) -> 🔴 Riesgo | M5: Cierre Mayo | N5: =IF(L5="🔴 Riesgo","Revisar prioridad mensual",IF(L5="🟡 En proceso","Completar registros y cierre","Mantener sistema")) -> Revisar prioridad mensual
A6: junio | B6: =SUMIF('11_Ingresos'!$K$5:$K$204,A6,'11_Ingresos'!$C$5:$C$204) -> 1930028 | C6: =SUMIFS('12_Gastos'!$D$5:$D$403,'12_Gastos'!$I$5:$I$403,A6,'12_Gastos'!$J$5:$J$403,"Gasto real") -> 525069 | D6: =IF(A6='18_Conciliacion_Bancaria_V2'!$B$3,'18_Conciliacion_Bancaria_V2'!B12,IF(A6="mayo",'15_Conciliacion'!B12,0)) -> 1453708 | E6: =IF(A6='18_Conciliacion_Bancaria_V2'!$B$3,'18_Conciliacion_Bancaria_V2'!B22,IF(A6="mayo",'15_Conciliacion'!B22,0)) -> 51789 | F6: =IF(A6='18_Conciliacion_Bancaria_V2'!$B$3,'18_Conciliacion_Bancaria_V2'!B26,IF(A6="mayo",'15_Conciliacion'!B26,0)) -> -1401919 | G6: =COUNTA('40_Estudio_Empresas'!C3:C204) -> 1 | H6: =COUNTIF('32_Oportunidades'!A5:A204,"?*") -> 0 | I6: =IF(A6="mayo",'01_Score_Mayo'!B5,0) -> 0 | J6: =IF(A6="mayo",'01_Score_Mayo'!B8,0) -> 0 | K6: =IF(A6="mayo",'01_Score_Mayo'!I11,AVERAGE(IFERROR(B6/MAX(1,B6+C6),0),IFERROR(G6/25,0),IFERROR(H6/5,0))*100) -> 27.537702 | L6: =IF(K6>=90,"⭐ Dominio",IF(K6>=70,"🟢 Cumple",IF(K6>=40,"🟡 En proceso","🔴 Riesgo"))) -> 🔴 Riesgo | M6: =IF(A6="mayo","Cierre Mayo",IF(A6='18_Conciliacion_Bancaria_V2'!$B$3,'18_Conciliacion_Bancaria_V2'!B28,"Pendiente")) -> 🔴 Diferencia crítica | N6: =IF(L6="🔴 Riesgo","Revisar prioridad mensual",IF(L6="🟡 En proceso","Completar registros y cierre","Mantener sistema")) -> Revisar prioridad mensual
A7: julio | B7: =SUMIF('11_Ingresos'!$K$5:$K$204,A7,'11_Ingresos'!$C$5:$C$204) -> 0 | C7: =SUMIFS('12_Gastos'!$D$5:$D$403,'12_Gastos'!$I$5:$I$403,A7,'12_Gastos'!$J$5:$J$403,"Gasto real") -> 0 | D7: =IF(A7='18_Conciliacion_Bancaria_V2'!$B$3,'18_Conciliacion_Bancaria_V2'!B12,IF(A7="mayo",'15_Conciliacion'!B12,0)) -> 0 | E7: =IF(A7='18_Conciliacion_Bancaria_V2'!$B$3,'18_Conciliacion_Bancaria_V2'!B22,IF(A7="mayo",'15_Conciliacion'!B22,0)) -> 0 | F7: =IF(A7='18_Conciliacion_Bancaria_V2'!$B$3,'18_Conciliacion_Bancaria_V2'!B26,IF(A7="mayo",'15_Conciliacion'!B26,0)) -> 0 | G7: =COUNTA('40_Estudio_Empresas'!C3:C204) -> 1 | H7: =COUNTIF('32_Oportunidades'!A5:A204,"?*") -> 0 | I7: =IF(A7="mayo",'01_Score_Mayo'!B5,0) -> 0 | J7: =IF(A7="mayo",'01_Score_Mayo'!B8,0) -> 0 | K7: =IF(A7="mayo",'01_Score_Mayo'!I11,AVERAGE(IFERROR(B7/MAX(1,B7+C7),0),IFERROR(G7/25,0),IFERROR(H7/5,0))*100) -> 1.3333333 | L7: =IF(K7>=90,"⭐ Dominio",IF(K7>=70,"🟢 Cumple",IF(K7>=40,"🟡 En proceso","🔴 Riesgo"))) -> 🔴 Riesgo | M7: =IF(A7="mayo","Cierre Mayo",IF(A7='18_Conciliacion_Bancaria_V2'!$B$3,'18_Conciliacion_Bancaria_V2'!B28,"Pendiente")) -> Pendiente | N7: =IF(L7="🔴 Riesgo","Revisar prioridad mensual",IF(L7="🟡 En proceso","Completar registros y cierre","Mantener sistema")) -> Revisar prioridad mensual
A8: agosto | B8: =SUMIF('11_Ingresos'!$K$5:$K$204,A8,'11_Ingresos'!$C$5:$C$204) -> 0 | C8: =SUMIFS('12_Gastos'!$D$5:$D$403,'12_Gastos'!$I$5:$I$403,A8,'12_Gastos'!$J$5:$J$403,"Gasto real") -> 0 | D8: =IF(A8='18_Conciliacion_Bancaria_V2'!$B$3,'18_Conciliacion_Bancaria_V2'!B12,IF(A8="mayo",'15_Conciliacion'!B12,0)) -> 0 | E8: =IF(A8='18_Conciliacion_Bancaria_V2'!$B$3,'18_Conciliacion_Bancaria_V2'!B22,IF(A8="mayo",'15_Conciliacion'!B22,0)) -> 0 | F8: =IF(A8='18_Conciliacion_Bancaria_V2'!$B$3,'18_Conciliacion_Bancaria_V2'!B26,IF(A8="mayo",'15_Conciliacion'!B26,0)) -> 0 | G8: =COUNTA('40_Estudio_Empresas'!C3:C204) -> 1 | H8: =COUNTIF('32_Oportunidades'!A5:A204,"?*") -> 0 | I8: =IF(A8="mayo",'01_Score_Mayo'!B5,0) -> 0 | J8: =IF(A8="mayo",'01_Score_Mayo'!B8,0) -> 0 | K8: =IF(A8="mayo",'01_Score_Mayo'!I11,AVERAGE(IFERROR(B8/MAX(1,B8+C8),0),IFERROR(G8/25,0),IFERROR(H8/5,0))*100) -> 1.3333333 | L8: =IF(K8>=90,"⭐ Dominio",IF(K8>=70,"🟢 Cumple",IF(K8>=40,"🟡 En proceso","🔴 Riesgo"))) -> 🔴 Riesgo | M8: =IF(A8="mayo","Cierre Mayo",IF(A8='18_Conciliacion_Bancaria_V2'!$B$3,'18_Conciliacion_Bancaria_V2'!B28,"Pendiente")) -> Pendiente | N8: =IF(L8="🔴 Riesgo","Revisar prioridad mensual",IF(L8="🟡 En proceso","Completar registros y cierre","Mantener sistema")) -> Revisar prioridad mensual
A9: septiembre | B9: =SUMIF('11_Ingresos'!$K$5:$K$204,A9,'11_Ingresos'!$C$5:$C$204) -> 0 | C9: =SUMIFS('12_Gastos'!$D$5:$D$403,'12_Gastos'!$I$5:$I$403,A9,'12_Gastos'!$J$5:$J$403,"Gasto real") -> 0 | D9: =IF(A9='18_Conciliacion_Bancaria_V2'!$B$3,'18_Conciliacion_Bancaria_V2'!B12,IF(A9="mayo",'15_Conciliacion'!B12,0)) -> 0 | E9: =IF(A9='18_Conciliacion_Bancaria_V2'!$B$3,'18_Conciliacion_Bancaria_V2'!B22,IF(A9="mayo",'15_Conciliacion'!B22,0)) -> 0 | F9: =IF(A9='18_Conciliacion_Bancaria_V2'!$B$3,'18_Conciliacion_Bancaria_V2'!B26,IF(A9="mayo",'15_Conciliacion'!B26,0)) -> 0 | G9: =COUNTA('40_Estudio_Empresas'!C3:C204) -> 1 | H9: =COUNTIF('32_Oportunidades'!A5:A204,"?*") -> 0 | I9: =IF(A9="mayo",'01_Score_Mayo'!B5,0) -> 0 | J9: =IF(A9="mayo",'01_Score_Mayo'!B8,0) -> 0 | K9: =IF(A9="mayo",'01_Score_Mayo'!I11,AVERAGE(IFERROR(B9/MAX(1,B9+C9),0),IFERROR(G9/25,0),IFERROR(H9/5,0))*100) -> 1.3333333 | L9: =IF(K9>=90,"⭐ Dominio",IF(K9>=70,"🟢 Cumple",IF(K9>=40,"🟡 En proceso","🔴 Riesgo"))) -> 🔴 Riesgo | M9: =IF(A9="mayo","Cierre Mayo",IF(A9='18_Conciliacion_Bancaria_V2'!$B$3,'18_Conciliacion_Bancaria_V2'!B28,"Pendiente")) -> Pendiente | N9: =IF(L9="🔴 Riesgo","Revisar prioridad mensual",IF(L9="🟡 En proceso","Completar registros y cierre","Mantener sistema")) -> Revisar prioridad mensual
A10: octubre | B10: =SUMIF('11_Ingresos'!$K$5:$K$204,A10,'11_Ingresos'!$C$5:$C$204) -> 0 | C10: =SUMIFS('12_Gastos'!$D$5:$D$403,'12_Gastos'!$I$5:$I$403,A10,'12_Gastos'!$J$5:$J$403,"Gasto real") -> 0 | D10: =IF(A10='18_Conciliacion_Bancaria_V2'!$B$3,'18_Conciliacion_Bancaria_V2'!B12,IF(A10="mayo",'15_Conciliacion'!B12,0)) -> 0 | E10: =IF(A10='18_Conciliacion_Bancaria_V2'!$B$3,'18_Conciliacion_Bancaria_V2'!B22,IF(A10="mayo",'15_Conciliacion'!B22,0)) -> 0 | F10: =IF(A10='18_Conciliacion_Bancaria_V2'!$B$3,'18_Conciliacion_Bancaria_V2'!B26,IF(A10="mayo",'15_Conciliacion'!B26,0)) -> 0 | G10: =COUNTA('40_Estudio_Empresas'!C3:C204) -> 1 | H10: =COUNTIF('32_Oportunidades'!A5:A204,"?*") -> 0 | I10: =IF(A10="mayo",'01_Score_Mayo'!B5,0) -> 0 | J10: =IF(A10="mayo",'01_Score_Mayo'!B8,0) -> 0 | K10: =IF(A10="mayo",'01_Score_Mayo'!I11,AVERAGE(IFERROR(B10/MAX(1,B10+C10),0),IFERROR(G10/25,0),IFERROR(H10/5,0))*100) -> 1.3333333 | L10: =IF(K10>=90,"⭐ Dominio",IF(K10>=70,"🟢 Cumple",IF(K10>=40,"🟡 En proceso","🔴 Riesgo"))) -> 🔴 Riesgo | M10: =IF(A10="mayo","Cierre Mayo",IF(A10='18_Conciliacion_Bancaria_V2'!$B$3,'18_Conciliacion_Bancaria_V2'!B28,"Pendiente")) -> Pendiente | N10: =IF(L10="🔴 Riesgo","Revisar prioridad mensual",IF(L10="🟡 En proceso","Completar registros y cierre","Mantener sistema")) -> Revisar prioridad mensual
A11: noviembre | B11: =SUMIF('11_Ingresos'!$K$5:$K$204,A11,'11_Ingresos'!$C$5:$C$204) -> 0 | C11: =SUMIFS('12_Gastos'!$D$5:$D$403,'12_Gastos'!$I$5:$I$403,A11,'12_Gastos'!$J$5:$J$403,"Gasto real") -> 0 | D11: =IF(A11='18_Conciliacion_Bancaria_V2'!$B$3,'18_Conciliacion_Bancaria_V2'!B12,IF(A11="mayo",'15_Conciliacion'!B12,0)) -> 0 | E11: =IF(A11='18_Conciliacion_Bancaria_V2'!$B$3,'18_Conciliacion_Bancaria_V2'!B22,IF(A11="mayo",'15_Conciliacion'!B22,0)) -> 0 | F11: =IF(A11='18_Conciliacion_Bancaria_V2'!$B$3,'18_Conciliacion_Bancaria_V2'!B26,IF(A11="mayo",'15_Conciliacion'!B26,0)) -> 0 | G11: =COUNTA('40_Estudio_Empresas'!C3:C204) -> 1 | H11: =COUNTIF('32_Oportunidades'!A5:A204,"?*") -> 0 | I11: =IF(A11="mayo",'01_Score_Mayo'!B5,0) -> 0 | J11: =IF(A11="mayo",'01_Score_Mayo'!B8,0) -> 0 | K11: =IF(A11="mayo",'01_Score_Mayo'!I11,AVERAGE(IFERROR(B11/MAX(1,B11+C11),0),IFERROR(G11/25,0),IFERROR(H11/5,0))*100) -> 1.3333333 | L11: =IF(K11>=90,"⭐ Dominio",IF(K11>=70,"🟢 Cumple",IF(K11>=40,"🟡 En proceso","🔴 Riesgo"))) -> 🔴 Riesgo | M11: =IF(A11="mayo","Cierre Mayo",IF(A11='18_Conciliacion_Bancaria_V2'!$B$3,'18_Conciliacion_Bancaria_V2'!B28,"Pendiente")) -> Pendiente | N11: =IF(L11="🔴 Riesgo","Revisar prioridad mensual",IF(L11="🟡 En proceso","Completar registros y cierre","Mantener sistema")) -> Revisar prioridad mensual
A12: diciembre | B12: =SUMIF('11_Ingresos'!$K$5:$K$204,A12,'11_Ingresos'!$C$5:$C$204) -> 0 | C12: =SUMIFS('12_Gastos'!$D$5:$D$403,'12_Gastos'!$I$5:$I$403,A12,'12_Gastos'!$J$5:$J$403,"Gasto real") -> 0 | D12: =IF(A12='18_Conciliacion_Bancaria_V2'!$B$3,'18_Conciliacion_Bancaria_V2'!B12,IF(A12="mayo",'15_Conciliacion'!B12,0)) -> 0 | E12: =IF(A12='18_Conciliacion_Bancaria_V2'!$B$3,'18_Conciliacion_Bancaria_V2'!B22,IF(A12="mayo",'15_Conciliacion'!B22,0)) -> 0 | F12: =IF(A12='18_Conciliacion_Bancaria_V2'!$B$3,'18_Conciliacion_Bancaria_V2'!B26,IF(A12="mayo",'15_Conciliacion'!B26,0)) -> 0 | G12: =COUNTA('40_Estudio_Empresas'!C3:C204) -> 1 | H12: =COUNTIF('32_Oportunidades'!A5:A204,"?*") -> 0 | I12: =IF(A12="mayo",'01_Score_Mayo'!B5,0) -> 0 | J12: =IF(A12="mayo",'01_Score_Mayo'!B8,0) -> 0 | K12: =IF(A12="mayo",'01_Score_Mayo'!I11,AVERAGE(IFERROR(B12/MAX(1,B12+C12),0),IFERROR(G12/25,0),IFERROR(H12/5,0))*100) -> 1.3333333 | L12: =IF(K12>=90,"⭐ Dominio",IF(K12>=70,"🟢 Cumple",IF(K12>=40,"🟡 En proceso","🔴 Riesgo"))) -> 🔴 Riesgo | M12: =IF(A12="mayo","Cierre Mayo",IF(A12='18_Conciliacion_Bancaria_V2'!$B$3,'18_Conciliacion_Bancaria_V2'!B28,"Pendiente")) -> Pendiente | N12: =IF(L12="🔴 Riesgo","Revisar prioridad mensual",IF(L12="🟡 En proceso","Completar registros y cierre","Mantener sistema")) -> Revisar prioridad mensual

Sheet SEC_02_FINANZAS
A1: FINANZAS
A2: Sección operativa visible. Las hojas históricas/duplicadas fueron enviadas al final y ocultadas.

Sheet 10_Patrimonio_Financiero
A1: 10 PATRIMONIO FINANCIERO — CONSOLIDADO V7.1
A2: Consolida liquidez real, inversiones y deudas. Inversiones NO incluyen caja para evitar doble conteo.
A4: Bloque | B4: Cuenta / Activo | C4: Tipo | D4: Moneda | E4: Valor origen | F4: Tipo cambio | G4: Valor CLP | H4: Estado | I4: Comentario
A5: ACTIVO | B5: Liquidez inicial / cuentas | C5: Caja/Banco | D5: CLP | E5: ='10_Apertura'!C9 -> 13858 | F5: 950 | G5: =IF(E5="","",IF(D5="USD",E5*F5,E5)) -> 13858 | H5: Activo | I5: Desde 10_Apertura; actualizar luego con conciliación real
A6: ACTIVO | B6: Inversiones / posiciones actuales | C6: Inversiones | D6: CLP | E6: ='08_Rentabilidad_Inversiones'!V5 -> 236224 | F6: 950 | G6: =IF(E6="","",IF(D6="USD",E6*F6,E6)) -> 236224 | H6: Activo | I6: Desde 08 Rentabilidad: no incluye caja
A7: ACTIVO | B7: Otros activos manuales | C7: Otro | D7: CLP | E7: 0 | F7: 950 | G7: =IF(E7="","",IF(D7="USD",E7*F7,E7)) -> 0 | H7: Pendiente | I7: Editable
A8: PASIVO | B8: Deudas actuales | C8: Deuda | D8: CLP | E8: ='13_Deudas'!O8 -> -653763 | F8: 950 | G8: =IF(E8="","",IF(D8="USD",E8*F8,E8)) -> -653763 | H8: Activo | I8: Desde 13 Deudas
A10: Resumen | B10: Valor CLP | C10: Estado
A11: Total activos | B11: =SUMIF(A5:A8,"ACTIVO",G5:G8) -> 250082 | C11: =IF(B11>0,"🟢 Activo","🔴 Sin activos") -> 🟢 Activo
A12: Total pasivos | B12: =SUMIF(A5:A8,"PASIVO",G5:G8) -> -653763 | C12: =IF(B12=0,"🟢 Sin deuda",IF(B12/B11<0.3,"🟡 Controlable","🔴 Alta")) -> 🟡 Controlable
A13: Patrimonio neto | B13: =B11-B12 -> 903845 | C13: =IF(B13>0,"🟢 Positivo","🔴 Negativo") -> 🟢 Positivo
A14: Inversiones / activos % | B14: =IFERROR(G6/B11,0) -> 0.94458618 | C14: =IF(B14>=0.2,"🟢 Capital invertido","🟡 Bajo") -> 🟢 Capital invertido
A15: Deuda / activos % | B15: =IFERROR(B12/B11,0) -> -2.6141945 | C15: =IF(B15<0.3,"🟢 Controlado",IF(B15<0.6,"🟡 Atención","🔴 Riesgo")) -> 🟢 Controlado

Sheet 11_Ingresos
A1: 11 Ingresos
A2: Registro de ingresos reales + distribución automática 55/20/15/10 por cada ingreso.
A4: Fecha | B4: Tipo | C4: Monto | D4: Vida Real 55% | E4: Capital 20% | F4: Deuda 15% | G4: Expansión 10% | H4: Semana | I4: Movimiento | J4: Comentario | K4: Mes | M4: Resumen ingresos
A5: 46143 | B5: Sueldo | C5: 366477 | D5: =IF(C5="","",C5*0.55) -> 201562.35 | E5: =IF(C5="","",C5*0.2) -> 73295.4 | F5: =IF(C5="","",C5*0.15) -> 54971.55 | G5: =IF(C5="","",C5*0.1) -> 36647.7 | H5: =IF(A5="","", "Semana "&(WEEKNUM(A5,2)-WEEKNUM(DATE(YEAR(A5),MONTH(A5),1),2)+1)) -> Semana 1 | I5: Sueldo Base | J5: Liquidacion de abril | K5: =IF(A5="","",IF(MONTH(A5)=5,"mayo",IF(MONTH(A5)=4,"abril",TEXT(A5,"mmmm")))) -> mayo | M5: Total ingresos | N5: =SUMIFS(C5:C204,K5:K204,"mayo") -> 1130484
A6: 46120 | B6: Turno Extra | C6: 62000 | D6: =IF(C6="","",C6*0.55) -> 34100 | E6: =IF(C6="","",C6*0.2) -> 12400 | F6: =IF(C6="","",C6*0.15) -> 9300 | G6: =IF(C6="","",C6*0.1) -> 6200 | H6: =IF(A6="","", "Semana "&(WEEKNUM(A6,2)-WEEKNUM(DATE(YEAR(A6),MONTH(A6),1),2)+1)) -> Semana 2 | I6: Turnos extras | J6: Pagados en abril | K6: =IF(A6="","",IF(MONTH(A6)=5,"mayo",IF(MONTH(A6)=4,"abril",TEXT(A6,"mmmm")))) -> abril | M6: Vida Real 55% | N6: =SUMIFS(D5:D204,K5:K204,"mayo") -> 621766.2
A7: 46127 | B7: Otro | C7: 100000 | D7: =IF(C7="","",C7*0.55) -> 55000 | E7: =IF(C7="","",C7*0.2) -> 20000 | F7: =IF(C7="","",C7*0.15) -> 15000 | G7: =IF(C7="","",C7*0.1) -> 10000 | H7: =IF(A7="","", "Semana "&(WEEKNUM(A7,2)-WEEKNUM(DATE(YEAR(A7),MONTH(A7),1),2)+1)) -> Semana 3 | I7: Anticipo | J7: Pagados en abril | K7: =IF(A7="","",IF(MONTH(A7)=5,"mayo",IF(MONTH(A7)=4,"abril",TEXT(A7,"mmmm")))) -> abril | M7: Capital 20% | N7: =SUMIFS(E5:E204,K5:K204,"mayo") -> 226096.8
A8: 46134 | B8: Turno Extra | C8: 120000 | D8: =IF(C8="","",C8*0.55) -> 66000 | E8: =IF(C8="","",C8*0.2) -> 24000 | F8: =IF(C8="","",C8*0.15) -> 18000 | G8: =IF(C8="","",C8*0.1) -> 12000 | H8: =IF(A8="","", "Semana "&(WEEKNUM(A8,2)-WEEKNUM(DATE(YEAR(A8),MONTH(A8),1),2)+1)) -> Semana 4 | I8: Turnos extras | J8: Pagados en abril | K8: =IF(A8="","",IF(MONTH(A8)=5,"mayo",IF(MONTH(A8)=4,"abril",TEXT(A8,"mmmm")))) -> abril | M8: Deuda 15% | N8: =SUMIFS(F5:F204,K5:K204,"mayo") -> 169572.6
A9: 46146 | B9: Bono | C9: 63000 | D9: =IF(C9="","",C9*0.55) -> 34650 | E9: =IF(C9="","",C9*0.2) -> 12600 | F9: =IF(C9="","",C9*0.15) -> 9450 | G9: =IF(C9="","",C9*0.1) -> 6300 | H9: =IF(A9="","", "Semana "&(WEEKNUM(A9,2)-WEEKNUM(DATE(YEAR(A9),MONTH(A9),1),2)+1)) -> Semana 2 | I9: Colaciones de Abril | J9: Pagados en mayo | K9: =IF(A9="","",IF(MONTH(A9)=5,"mayo",IF(MONTH(A9)=4,"abril",TEXT(A9,"mmmm")))) -> mayo | M9: Expansión 10% | N9: =SUMIFS(G5:G204,K5:K204,"mayo") -> 113048.4
A10: 46147 | B10: Arriendo | C10: 162700 | D10: =IF(C10="","",C10*0.55) -> 89485 | E10: =IF(C10="","",C10*0.2) -> 32540 | F10: =IF(C10="","",C10*0.15) -> 24405 | G10: =IF(C10="","",C10*0.1) -> 16270 | H10: =IF(A10="","", "Semana "&(WEEKNUM(A10,2)-WEEKNUM(DATE(YEAR(A10),MONTH(A10),1),2)+1)) -> Semana 2 | I10: Pago Arriendo Restaurante | J10: Pagados en mayo | K10: =IF(A10="","",IF(MONTH(A10)=5,"mayo",IF(MONTH(A10)=4,"abril",TEXT(A10,"mmmm")))) -> mayo | M10: Ingreso proyectado | N10: ='10_Apertura'!$B$33 -> 1160000
A11: 46148 | B11: Otro | C11: 2200 | D11: =IF(C11="","",C11*0.55) -> 1210 | E11: =IF(C11="","",C11*0.2) -> 440 | F11: =IF(C11="","",C11*0.15) -> 330 | G11: =IF(C11="","",C11*0.1) -> 220 | H11: =IF(A11="","", "Semana "&(WEEKNUM(A11,2)-WEEKNUM(DATE(YEAR(A11),MONTH(A11),1),2)+1)) -> Semana 2 | I11: Transferncia | J11: Transferencia de Angela | K11: =IF(A11="","",IF(MONTH(A11)=5,"mayo",IF(MONTH(A11)=4,"abril",TEXT(A11,"mmmm")))) -> mayo | M11: Variación vs proyectado | N11: =N5-N10 -> -29516
A12: 46149 | B12: Reembolso | C12: 81107 | D12: =IF(C12="","",C12*0.55) -> 44608.85 | E12: =IF(C12="","",C12*0.2) -> 16221.4 | F12: =IF(C12="","",C12*0.15) -> 12166.05 | G12: =IF(C12="","",C12*0.1) -> 8110.7 | H12: =IF(A12="","", "Semana "&(WEEKNUM(A12,2)-WEEKNUM(DATE(YEAR(A12),MONTH(A12),1),2)+1)) -> Semana 2 | I12: Transferncia | J12: Tranferencia diferencia de sueldo debido | K12: =IF(A12="","",IF(MONTH(A12)=5,"mayo",IF(MONTH(A12)=4,"abril",TEXT(A12,"mmmm")))) -> mayo
A13: 46149 | B13: Otro | C13: 170000 | D13: =IF(C13="","",C13*0.55) -> 93500 | E13: =IF(C13="","",C13*0.2) -> 34000 | F13: =IF(C13="","",C13*0.15) -> 25500 | G13: =IF(C13="","",C13*0.1) -> 17000 | H13: =IF(A13="","", "Semana "&(WEEKNUM(A13,2)-WEEKNUM(DATE(YEAR(A13),MONTH(A13),1),2)+1)) -> Semana 2 | I13: Transferncia | J13: Tranferencia de mi papa para supermercado | K13: =IF(A13="","",IF(MONTH(A13)=5,"mayo",IF(MONTH(A13)=4,"abril",TEXT(A13,"mmmm")))) -> mayo
A14: 46156 | B14: Turno Extra | C14: 40000 | D14: =IF(C14="","",C14*0.55) -> 22000 | E14: =IF(C14="","",C14*0.2) -> 8000 | F14: =IF(C14="","",C14*0.15) -> 6000 | G14: =IF(C14="","",C14*0.1) -> 4000 | H14: =IF(A14="","", "Semana "&(WEEKNUM(A14,2)-WEEKNUM(DATE(YEAR(A14),MONTH(A14),1),2)+1)) -> Semana 3 | I14: Transferncia | J14: A mi cuenta | K14: =IF(A14="","",IF(MONTH(A14)=5,"mayo",IF(MONTH(A14)=4,"abril",TEXT(A14,"mmmm")))) -> mayo | M14: Por semana
A15: 46157 | B15: Otro | C15: 100000 | D15: =IF(C15="","",C15*0.55) -> 55000 | E15: =IF(C15="","",C15*0.2) -> 20000 | F15: =IF(C15="","",C15*0.15) -> 15000 | G15: =IF(C15="","",C15*0.1) -> 10000 | H15: =IF(A15="","", "Semana "&(WEEKNUM(A15,2)-WEEKNUM(DATE(YEAR(A15),MONTH(A15),1),2)+1)) -> Semana 3 | I15: Transferncia | J15: Quincena de Mayo | K15: =IF(A15="","",IF(MONTH(A15)=5,"mayo",IF(MONTH(A15)=4,"abril",TEXT(A15,"mmmm")))) -> mayo | M15: Semana 1 | N15: =SUMIFS(C$5:C$204,K$5:K$204,"mayo",H$5:H$204,M15) -> 366477
A16: 46162 | B16: Turno Extra | C16: 80000 | D16: =IF(C16="","",C16*0.55) -> 44000 | E16: =IF(C16="","",C16*0.2) -> 16000 | F16: =IF(C16="","",C16*0.15) -> 12000 | G16: =IF(C16="","",C16*0.1) -> 8000 | H16: =IF(A16="","", "Semana "&(WEEKNUM(A16,2)-WEEKNUM(DATE(YEAR(A16),MONTH(A16),1),2)+1)) -> Semana 4 | I16: Transferncia | J16: A mi cuenta | K16: =IF(A16="","",IF(MONTH(A16)=5,"mayo",IF(MONTH(A16)=4,"abril",TEXT(A16,"mmmm")))) -> mayo | M16: Semana 2 | N16: =SUMIFS(C$5:C$204,K$5:K$204,"mayo",H$5:H$204,M16) -> 479007
A17: 46169 | B17: Otro | C17: 65000 | D17: =IF(C17="","",C17*0.55) -> 35750 | E17: =IF(C17="","",C17*0.2) -> 13000 | F17: =IF(C17="","",C17*0.15) -> 9750 | G17: =IF(C17="","",C17*0.1) -> 6500 | H17: =IF(A17="","", "Semana "&(WEEKNUM(A17,2)-WEEKNUM(DATE(YEAR(A17),MONTH(A17),1),2)+1)) -> Semana 5 | I17: Transferncia | J17: A mi cuenta | K17: =IF(A17="","",IF(MONTH(A17)=5,"mayo",IF(MONTH(A17)=4,"abril",TEXT(A17,"mmmm")))) -> mayo | M17: Semana 3 | N17: =SUMIFS(C$5:C$204,K$5:K$204,"mayo",H$5:H$204,M17) -> 140000
A18: 46174 | B18: Sueldo | C18: 490876 | D18: =IF(C18="","",C18*0.55) -> 269981.8 | E18: =IF(C18="","",C18*0.2) -> 98175.2 | F18: =IF(C18="","",C18*0.15) -> 73631.4 | G18: =IF(C18="","",C18*0.1) -> 49087.6 | H18: =IF(A18="","", "Semana "&(WEEKNUM(A18,2)-WEEKNUM(DATE(YEAR(A18),MONTH(A18),1),2)+1)) -> Semana 1 | I18: Transferncia | J18: A mi cuenta | K18: =IF(A18="","",IF(MONTH(A18)=5,"mayo",IF(MONTH(A18)=4,"abril",TEXT(A18,"mmmm")))) -> junio | M18: Semana 4 | N18: =SUMIFS(C$5:C$204,K$5:K$204,"mayo",H$5:H$204,M18) -> 80000
A19: 46174 | B19: Otro | C19: 7000 | D19: =IF(C19="","",C19*0.55) -> 3850 | E19: =IF(C19="","",C19*0.2) -> 1400 | F19: =IF(C19="","",C19*0.15) -> 1050 | G19: =IF(C19="","",C19*0.1) -> 700 | H19: =IF(A19="","", "Semana "&(WEEKNUM(A19,2)-WEEKNUM(DATE(YEAR(A19),MONTH(A19),1),2)+1)) -> Semana 1 | I19: Transferncia | J19: A mi cuenta | K19: =IF(A19="","",IF(MONTH(A19)=5,"mayo",IF(MONTH(A19)=4,"abril",TEXT(A19,"mmmm")))) -> junio | M19: Semana 5 | N19: =SUMIFS(C$5:C$204,K$5:K$204,"mayo",H$5:H$204,M19) -> 65000
A20: 46174 | B20: Otro | C20: 77000 | D20: =IF(C20="","",C20*0.55) -> 42350 | E20: =IF(C20="","",C20*0.2) -> 15400 | F20: =IF(C20="","",C20*0.15) -> 11550 | G20: =IF(C20="","",C20*0.1) -> 7700 | H20: =IF(A20="","", "Semana "&(WEEKNUM(A20,2)-WEEKNUM(DATE(YEAR(A20),MONTH(A20),1),2)+1)) -> Semana 1 | I20: Transferncia | J20: A mi cuenta | K20: =IF(A20="","",IF(MONTH(A20)=5,"mayo",IF(MONTH(A20)=4,"abril",TEXT(A20,"mmmm")))) -> junio
A21: 46174 | B21: Otro | C21: 26000 | D21: =IF(C21="","",C21*0.55) -> 14300 | E21: =IF(C21="","",C21*0.2) -> 5200 | F21: =IF(C21="","",C21*0.15) -> 3900 | G21: =IF(C21="","",C21*0.1) -> 2600 | H21: =IF(A21="","", "Semana "&(WEEKNUM(A21,2)-WEEKNUM(DATE(YEAR(A21),MONTH(A21),1),2)+1)) -> Semana 1 | I21: Transferncia | J21: A mi cuenta | K21: =IF(A21="","",IF(MONTH(A21)=5,"mayo",IF(MONTH(A21)=4,"abril",TEXT(A21,"mmmm")))) -> junio
A22: 46174 | B22: Bono | C22: 97152 | D22: =IF(C22="","",C22*0.55) -> 53433.6 | E22: =IF(C22="","",C22*0.2) -> 19430.4 | F22: =IF(C22="","",C22*0.15) -> 14572.8 | G22: =IF(C22="","",C22*0.1) -> 9715.2 | H22: =IF(A22="","", "Semana "&(WEEKNUM(A22,2)-WEEKNUM(DATE(YEAR(A22),MONTH(A22),1),2)+1)) -> Semana 1 | I22: Transferncia | J22: A mi cuenta | K22: =IF(A22="","",IF(MONTH(A22)=5,"mayo",IF(MONTH(A22)=4,"abril",TEXT(A22,"mmmm")))) -> junio | M22: Por tipo
A23: 46174 | B23: Bono | C23: 72000 | D23: =IF(C23="","",C23*0.55) -> 39600 | E23: =IF(C23="","",C23*0.2) -> 14400 | F23: =IF(C23="","",C23*0.15) -> 10800 | G23: =IF(C23="","",C23*0.1) -> 7200 | H23: =IF(A23="","", "Semana "&(WEEKNUM(A23,2)-WEEKNUM(DATE(YEAR(A23),MONTH(A23),1),2)+1)) -> Semana 1 | I23: Transferncia | J23: A mi cuenta | K23: =IF(A23="","",IF(MONTH(A23)=5,"mayo",IF(MONTH(A23)=4,"abril",TEXT(A23,"mmmm")))) -> junio | M23: Sueldo | N23: =SUMIFS(C$5:C$204,K$5:K$204,"mayo",B$5:B$204,M23) -> 366477
A24: 46177 | B24: Otro | C24: 50000 | D24: =IF(C24="","",C24*0.55) -> 27500 | E24: =IF(C24="","",C24*0.2) -> 10000 | F24: =IF(C24="","",C24*0.15) -> 7500 | G24: =IF(C24="","",C24*0.1) -> 5000 | H24: =IF(A24="","", "Semana "&(WEEKNUM(A24,2)-WEEKNUM(DATE(YEAR(A24),MONTH(A24),1),2)+1)) -> Semana 1 | I24: Transferncia | J24: A mi cuenta | K24: =IF(A24="","",IF(MONTH(A24)=5,"mayo",IF(MONTH(A24)=4,"abril",TEXT(A24,"mmmm")))) -> junio | M24: Bono | N24: =SUMIFS(C$5:C$204,K$5:K$204,"mayo",B$5:B$204,M24) -> 63000
A25: 46187 | B25: Otro | C25: 5000 | D25: =IF(C25="","",C25*0.55) -> 2750 | E25: =IF(C25="","",C25*0.2) -> 1000 | F25: =IF(C25="","",C25*0.15) -> 750 | G25: =IF(C25="","",C25*0.1) -> 500 | H25: =IF(A25="","", "Semana "&(WEEKNUM(A25,2)-WEEKNUM(DATE(YEAR(A25),MONTH(A25),1),2)+1)) -> Semana 2 | I25: Transferncia | J25: A mi cuenta | K25: =IF(A25="","",IF(MONTH(A25)=5,"mayo",IF(MONTH(A25)=4,"abril",TEXT(A25,"mmmm")))) -> junio | M25: Turno Extra | N25: =SUMIFS(C$5:C$204,K$5:K$204,"mayo",B$5:B$204,M25) -> 120000
A26: 46188 | B26: Otro | C26: 40000 | D26: =IF(C26="","",C26*0.55) -> 22000 | E26: =IF(C26="","",C26*0.2) -> 8000 | F26: =IF(C26="","",C26*0.15) -> 6000 | G26: =IF(C26="","",C26*0.1) -> 4000 | H26: =IF(A26="","", "Semana "&(WEEKNUM(A26,2)-WEEKNUM(DATE(YEAR(A26),MONTH(A26),1),2)+1)) -> Semana 3 | I26: Transferncia | J26: A mi cuenta | K26: =IF(A26="","",IF(MONTH(A26)=5,"mayo",IF(MONTH(A26)=4,"abril",TEXT(A26,"mmmm")))) -> junio | M26: Arriendo | N26: =SUMIFS(C$5:C$204,K$5:K$204,"mayo",B$5:B$204,M26) -> 162700
A27: 46188 | B27: Otro | C27: 20000 | D27: =IF(C27="","",C27*0.55) -> 11000 | E27: =IF(C27="","",C27*0.2) -> 4000 | F27: =IF(C27="","",C27*0.15) -> 3000 | G27: =IF(C27="","",C27*0.1) -> 2000 | H27: =IF(A27="","", "Semana "&(WEEKNUM(A27,2)-WEEKNUM(DATE(YEAR(A27),MONTH(A27),1),2)+1)) -> Semana 3 | I27: Transferncia | J27: A mi cuenta | K27: =IF(A27="","",IF(MONTH(A27)=5,"mayo",IF(MONTH(A27)=4,"abril",TEXT(A27,"mmmm")))) -> junio | M27: Colaciones | N27: =SUMIFS(C$5:C$204,K$5:K$204,"mayo",B$5:B$204,M27) -> 0
A28: 46188 | B28: Otro | C28: 70000 | D28: =IF(C28="","",C28*0.55) -> 38500 | E28: =IF(C28="","",C28*0.2) -> 14000 | F28: =IF(C28="","",C28*0.15) -> 10500 | G28: =IF(C28="","",C28*0.1) -> 7000 | H28: =IF(A28="","", "Semana "&(WEEKNUM(A28,2)-WEEKNUM(DATE(YEAR(A28),MONTH(A28),1),2)+1)) -> Semana 3 | I28: Transferncia | J28: A mi cuenta | K28: =IF(A28="","",IF(MONTH(A28)=5,"mayo",IF(MONTH(A28)=4,"abril",TEXT(A28,"mmmm")))) -> junio | M28: Reembolso | N28: =SUMIFS(C$5:C$204,K$5:K$204,"mayo",B$5:B$204,M28) -> 81107
A29: 46188 | B29: Otro | C29: 15000 | D29: =IF(C29="","",C29*0.55) -> 8250 | E29: =IF(C29="","",C29*0.2) -> 3000 | F29: =IF(C29="","",C29*0.15) -> 2250 | G29: =IF(C29="","",C29*0.1) -> 1500 | H29: =IF(A29="","", "Semana "&(WEEKNUM(A29,2)-WEEKNUM(DATE(YEAR(A29),MONTH(A29),1),2)+1)) -> Semana 3 | I29: Transferncia | J29: A mi cuenta | K29: =IF(A29="","",IF(MONTH(A29)=5,"mayo",IF(MONTH(A29)=4,"abril",TEXT(A29,"mmmm")))) -> junio | M29: Venta | N29: =SUMIFS(C$5:C$204,K$5:K$204,"mayo",B$5:B$204,M29) -> 0
A30: 46195 | B30: Otro | C30: 220000 | D30: =IF(C30="","",C30*0.55) -> 121000 | E30: =IF(C30="","",C30*0.2) -> 44000 | F30: =IF(C30="","",C30*0.15) -> 33000 | G30: =IF(C30="","",C30*0.1) -> 22000 | H30: =IF(A30="","", "Semana "&(WEEKNUM(A30,2)-WEEKNUM(DATE(YEAR(A30),MONTH(A30),1),2)+1)) -> Semana 4 | I30: Efectivo | J30: Cobro de un cheque | K30: =IF(A30="","",IF(MONTH(A30)=5,"mayo",IF(MONTH(A30)=4,"abril",TEXT(A30,"mmmm")))) -> junio | M30: Otro | N30: =SUMIFS(C$5:C$204,K$5:K$204,"mayo",B$5:B$204,M30) -> 337200
A31: 46196 | B31: Venta | C31: 60000 | D31: =IF(C31="","",C31*0.55) -> 33000 | E31: =IF(C31="","",C31*0.2) -> 12000 | F31: =IF(C31="","",C31*0.15) -> 9000 | G31: =IF(C31="","",C31*0.1) -> 6000 | H31: =IF(A31="","", "Semana "&(WEEKNUM(A31,2)-WEEKNUM(DATE(YEAR(A31),MONTH(A31),1),2)+1)) -> Semana 4 | I31: Efectivo | J31: Venta de pie | K31: =IF(A31="","",IF(MONTH(A31)=5,"mayo",IF(MONTH(A31)=4,"abril",TEXT(A31,"mmmm")))) -> junio
A32: 46202 | B32: Sueldo | C32: 680000 | D32: =IF(C32="","",C32*0.55) -> 374000 | E32: =IF(C32="","",C32*0.2) -> 136000 | F32: =IF(C32="","",C32*0.15) -> 102000 | G32: =IF(C32="","",C32*0.1) -> 68000 | H32: =IF(A32="","", "Semana "&(WEEKNUM(A32,2)-WEEKNUM(DATE(YEAR(A32),MONTH(A32),1),2)+1)) -> Semana 5 | I32: Transferncia | J32: Cuenta Falabella | K32: =IF(A32="","",IF(MONTH(A32)=5,"mayo",IF(MONTH(A32)=4,"abril",TEXT(A32,"mmmm")))) -> junio
D33: =IF(C33="","",C33*0.55) | E33: =IF(C33="","",C33*0.2) | F33: =IF(C33="","",C33*0.15) | G33: =IF(C33="","",C33*0.1) | H33: =IF(A33="","", "Semana "&(WEEKNUM(A33,2)-WEEKNUM(DATE(YEAR(A33),MONTH(A33),1),2)+1)) | K33: =IF(A33="","",IF(MONTH(A33)=5,"mayo",IF(MONTH(A33)=4,"abril",TEXT(A33,"mmmm"))))
D34: =IF(C34="","",C34*0.55) | E34: =IF(C34="","",C34*0.2) | F34: =IF(C34="","",C34*0.15) | G34: =IF(C34="","",C34*0.1) | H34: =IF(A34="","", "Semana "&(WEEKNUM(A34,2)-WEEKNUM(DATE(YEAR(A34),MONTH(A34),1),2)+1)) | K34: =IF(A34="","",IF(MONTH(A34)=5,"mayo",IF(MONTH(A34)=4,"abril",TEXT(A34,"mmmm"))))
D35: =IF(C35="","",C35*0.55) | E35: =IF(C35="","",C35*0.2) | F35: =IF(C35="","",C35*0.15) | G35: =IF(C35="","",C35*0.1) | H35: =IF(A35="","", "Semana "&(WEEKNUM(A35,2)-WEEKNUM(DATE(YEAR(A35),MONTH(A35),1),2)+1)) | K35: =IF(A35="","",IF(MONTH(A35)=5,"mayo",IF(MONTH(A35)=4,"abril",TEXT(A35,"mmmm"))))
D36: =IF(C36="","",C36*0.55) | E36: =IF(C36="","",C36*0.2) | F36: =IF(C36="","",C36*0.15) | G36: =IF(C36="","",C36*0.1) | H36: =IF(A36="","", "Semana "&(WEEKNUM(A36,2)-WEEKNUM(DATE(YEAR(A36),MONTH(A36),1),2)+1)) | K36: =IF(A36="","",IF(MONTH(A36)=5,"mayo",IF(MONTH(A36)=4,"abril",TEXT(A36,"mmmm"))))
D37: =IF(C37="","",C37*0.55) | E37: =IF(C37="","",C37*0.2) | F37: =IF(C37="","",C37*0.15) | G37: =IF(C37="","",C37*0.1) | H37: =IF(A37="","", "Semana "&(WEEKNUM(A37,2)-WEEKNUM(DATE(YEAR(A37),MONTH(A37),1),2)+1)) | K37: =IF(A37="","",IF(MONTH(A37)=5,"mayo",IF(MONTH(A37)=4,"abril",TEXT(A37,"mmmm"))))
D38: =IF(C38="","",C38*0.55) | E38: =IF(C38="","",C38*0.2) | F38: =IF(C38="","",C38*0.15) | G38: =IF(C38="","",C38*0.1) | H38: =IF(A38="","", "Semana "&(WEEKNUM(A38,2)-WEEKNUM(DATE(YEAR(A38),MONTH(A38),1),2)+1)) | K38: =IF(A38="","",IF(MONTH(A38)=5,"mayo",IF(MONTH(A38)=4,"abril",TEXT(A38,"mmmm"))))
D39: =IF(C39="","",C39*0.55) | E39: =IF(C39="","",C39*0.2) | F39: =IF(C39="","",C39*0.15) | G39: =IF(C39="","",C39*0.1) | H39: =IF(A39="","", "Semana "&(WEEKNUM(A39,2)-WEEKNUM(DATE(YEAR(A39),MONTH(A39),1),2)+1)) | K39: =IF(A39="","",IF(MONTH(A39)=5,"mayo",IF(MONTH(A39)=4,"abril",TEXT(A39,"mmmm"))))
D40: =IF(C40="","",C40*0.55) | E40: =IF(C40="","",C40*0.2) | F40: =IF(C40="","",C40*0.15) | G40: =IF(C40="","",C40*0.1) | H40: =IF(A40="","", "Semana "&(WEEKNUM(A40,2)-WEEKNUM(DATE(YEAR(A40),MONTH(A40),1),2)+1)) | K40: =IF(A40="","",IF(MONTH(A40)=5,"mayo",IF(MONTH(A40)=4,"abril",TEXT(A40,"mmmm"))))
D41: =IF(C41="","",C41*0.55) | E41: =IF(C41="","",C41*0.2) | F41: =IF(C41="","",C41*0.15) | G41: =IF(C41="","",C41*0.1) | H41: =IF(A41="","", "Semana "&(WEEKNUM(A41,2)-WEEKNUM(DATE(YEAR(A41),MONTH(A41),1),2)+1)) | K41: =IF(A41="","",IF(MONTH(A41)=5,"mayo",IF(MONTH(A41)=4,"abril",TEXT(A41,"mmmm"))))
D42: =IF(C42="","",C42*0.55) | E42: =IF(C42="","",C42*0.2) | F42: =IF(C42="","",C42*0.15) | G42: =IF(C42="","",C42*0.1) | H42: =IF(A42="","", "Semana "&(WEEKNUM(A42,2)-WEEKNUM(DATE(YEAR(A42),MONTH(A42),1),2)+1)) | K42: =IF(A42="","",IF(MONTH(A42)=5,"mayo",IF(MONTH(A42)=4,"abril",TEXT(A42,"mmmm"))))
D43: =IF(C43="","",C43*0.55) | E43: =IF(C43="","",C43*0.2) | F43: =IF(C43="","",C43*0.15) | G43: =IF(C43="","",C43*0.1) | H43: =IF(A43="","", "Semana "&(WEEKNUM(A43,2)-WEEKNUM(DATE(YEAR(A43),MONTH(A43),1),2)+1)) | K43: =IF(A43="","",IF(MONTH(A43)=5,"mayo",IF(MONTH(A43)=4,"abril",TEXT(A43,"mmmm"))))
D44: =IF(C44="","",C44*0.55) | E44: =IF(C44="","",C44*0.2) | F44: =IF(C44="","",C44*0.15) | G44: =IF(C44="","",C44*0.1) | H44: =IF(A44="","", "Semana "&(WEEKNUM(A44,2)-WEEKNUM(DATE(YEAR(A44),MONTH(A44),1),2)+1)) | K44: =IF(A44="","",IF(MONTH(A44)=5,"mayo",IF(MONTH(A44)=4,"abril",TEXT(A44,"mmmm"))))
... D204: =IF(C204="","",C204*0.55) | E204: =IF(C204="","",C204*0.2) | F204: =IF(C204="","",C204*0.15) | G204: =IF(C204="","",C204*0.1) | H204: =IF(A204="","", "Semana "&(WEEKNUM(A204,2)-WEEKNUM(DATE(YEAR(A204),MONTH(A204),1),2)+1)) | K204: =IF(A204="","",IF(MONTH(A204)=5,"mayo",IF(MONTH(A204)=4,"abril",TEXT(A204,"mmmm"))))

Sheet 12_Gastos
A1: 12 Gastos
A2: Registro de gastos con categoría, necesidad, área de presupuesto y semana.
A4: Fecha | B4: Categoría | C4: Detalle | D4: Monto | E4: Necesario S/N | F4: Área presupuesto | G4: Semana | H4: Comentario | I4: Mes | J4: Tipo movimiento | K4: Resumen gastos
A5: 46143 | B5: Alimentación | C5: Transferencia bancaria | D5: 20000 | E5: Sí | F5: Operación | G5: =IF(A5="","", "Semana "&(WEEKNUM(A5,2)-WEEKNUM(DATE(YEAR(A5),MONTH(A5),1),2)+1)) -> Semana 1 | H5: Tranferencia para compra supermercado | I5: =IF(A5="","",IF(MONTH(A5)=5,"mayo",IF(MONTH(A5)=4,"abril",TEXT(A5,"mmmm")))) -> mayo | J5: Histórico/Apertura | K5: Total salidas mes activo | L5: =SUMIFS($D$5:$D$403,$I$5:$I$403,'18_Conciliacion_Bancaria_V2'!$B$3,$J$5:$J$403,"Gasto real")+SUMIFS($D$5:$D$403,$I$5:$I$403,'18_Conciliacion_Bancaria_V2'!$B$3,$J$5:$J$403,"Movimiento patrimonial") -> 535069
A6: 46143 | B6: Telefonía | C6: Pago en red | D6: 202695 | E6: Sí | F6: Deuda | G6: =IF(A6="","", "Semana "&(WEEKNUM(A6,2)-WEEKNUM(DATE(YEAR(A6),MONTH(A6),1),2)+1)) -> Semana 1 | H6: Se adeudaban dos meses telefonos cortados | I6: =IF(A6="","",IF(MONTH(A6)=5,"mayo",IF(MONTH(A6)=4,"abril",TEXT(A6,"mmmm")))) -> mayo | J6: Histórico/Apertura | K6: Salidas necesarias | L6: =SUMIFS($D$5:$D$403,$I$5:$I$403,'18_Conciliacion_Bancaria_V2'!$B$3,$E$5:$E$403,"Sí")+SUMIFS($D$5:$D$403,$I$5:$I$403,'18_Conciliacion_Bancaria_V2'!$B$3,$E$5:$E$403,"si") -> 706503
A7: 46143 | B7: Alimentación | C7: Pago en red | D7: 3690 | E7: Sí | F7: Trabajo | G7: =IF(A7="","", "Semana "&(WEEKNUM(A7,2)-WEEKNUM(DATE(YEAR(A7),MONTH(A7),1),2)+1)) -> Semana 1 | H7: Colacion trabajo | I7: =IF(A7="","",IF(MONTH(A7)=5,"mayo",IF(MONTH(A7)=4,"abril",TEXT(A7,"mmmm")))) -> mayo | J7: Histórico/Apertura | K7: Salidas no necesarias | L7: =SUMIFS($D$5:$D$403,$I$5:$I$403,'18_Conciliacion_Bancaria_V2'!$B$3,$E$5:$E$403,"No")+SUMIFS($D$5:$D$403,$I$5:$I$403,'18_Conciliacion_Bancaria_V2'!$B$3,$E$5:$E$403,"no") -> 186920
A8: 46143 | B8: Alimentación | C8: Pago en red | D8: 900 | E8: No | F8: Trabajo | G8: =IF(A8="","", "Semana "&(WEEKNUM(A8,2)-WEEKNUM(DATE(YEAR(A8),MONTH(A8),1),2)+1)) -> Semana 1 | H8: Me dio hambre en el turno | I8: =IF(A8="","",IF(MONTH(A8)=5,"mayo",IF(MONTH(A8)=4,"abril",TEXT(A8,"mmmm")))) -> mayo | J8: Histórico/Apertura | K8: % no necesario | L8: =IFERROR(L7/L5,0) -> 0.34933812
A9: 46143 | B9: Suscripción | C9: Pago destacame | D9: 3900 | E9: Sí | F9: Operación | G9: =IF(A9="","", "Semana "&(WEEKNUM(A9,2)-WEEKNUM(DATE(YEAR(A9),MONTH(A9),1),2)+1)) -> Semana 1 | H9: Para tener el detalle de mis acreedores | I9: =IF(A9="","",IF(MONTH(A9)=5,"mayo",IF(MONTH(A9)=4,"abril",TEXT(A9,"mmmm")))) -> mayo | J9: Histórico/Apertura
A10: 46143 | B10: Suscripción | C10: Pago en red | D10: 1790 | E10: No | F10: Operación | G10: =IF(A10="","", "Semana "&(WEEKNUM(A10,2)-WEEKNUM(DATE(YEAR(A10),MONTH(A10),1),2)+1)) -> Semana 1 | H10: Juego del telefono | I10: =IF(A10="","",IF(MONTH(A10)=5,"mayo",IF(MONTH(A10)=4,"abril",TEXT(A10,"mmmm")))) -> mayo | J10: Histórico/Apertura
A11: 46127 | B11: Trabajo | C11: Anticipo | D11: 100000 | E11: Sí | F11: Trabajo | G11: =IF(A11="","", "Semana "&(WEEKNUM(A11,2)-WEEKNUM(DATE(YEAR(A11),MONTH(A11),1),2)+1)) -> Semana 3 | H11: Quincena mensual | I11: =IF(A11="","",IF(MONTH(A11)=5,"mayo",IF(MONTH(A11)=4,"abril",TEXT(A11,"mmmm")))) -> abril | J11: Histórico/Apertura | K11: Por área presupuesto
A12: 46143 | B12: Trabajo | C12: Turnos extras | D12: 182000 | E12: Sí | F12: Trabajo | G12: =IF(A12="","", "Semana "&(WEEKNUM(A12,2)-WEEKNUM(DATE(YEAR(A12),MONTH(A12),1),2)+1)) -> Semana 1 | H12: Turnos extras que ya me pagaron | I12: =IF(A12="","",IF(MONTH(A12)=5,"mayo",IF(MONTH(A12)=4,"abril",TEXT(A12,"mmmm")))) -> mayo | J12: Histórico/Apertura | K12: Operación | L12: =SUMIFS(D$5:D$403,I$5:I$403,"mayo",F$5:F$403,K12) -> 631698
A13: 46143 | B13: Alimentación | C13: Once | D13: 5190 | E13: Sí | F13: Trabajo | G13: =IF(A13="","", "Semana "&(WEEKNUM(A13,2)-WEEKNUM(DATE(YEAR(A13),MONTH(A13),1),2)+1)) -> Semana 1 | H13: Una empanada y un jugo antes de entrar a trabajar | I13: =IF(A13="","",IF(MONTH(A13)=5,"mayo",IF(MONTH(A13)=4,"abril",TEXT(A13,"mmmm")))) -> mayo | J13: Histórico/Apertura | K13: Caja | L13: =SUMIFS(D$5:D$403,I$5:I$403,"mayo",F$5:F$403,K13) -> 40000
A14: 46143 | B14: Suscripción | C14: Pago Red | D14: 1790 | E14: Sí | F14: Red / Empresas / Holding | G14: =IF(A14="","", "Semana "&(WEEKNUM(A14,2)-WEEKNUM(DATE(YEAR(A14),MONTH(A14),1),2)+1)) -> Semana 1 | H14: 100 gb google one google llc | I14: =IF(A14="","",IF(MONTH(A14)=5,"mayo",IF(MONTH(A14)=4,"abril",TEXT(A14,"mmmm")))) -> mayo | J14: Histórico/Apertura | K14: Inversión | L14: =SUMIFS(D$5:D$403,I$5:I$403,"mayo",F$5:F$403,K14) -> 101000
A15: 46144 | B15: Otros | C15: Transferencia bancaria | D15: 56000 | E15: Sí | F15: Operación | G15: =IF(A15="","", "Semana "&(WEEKNUM(A15,2)-WEEKNUM(DATE(YEAR(A15),MONTH(A15),1),2)+1)) -> Semana 1 | H15: Transeferncia para comida de gatos | I15: =IF(A15="","",IF(MONTH(A15)=5,"mayo",IF(MONTH(A15)=4,"abril",TEXT(A15,"mmmm")))) -> mayo | J15: Histórico/Apertura | K15: Deuda | L15: =SUMIFS(D$5:D$403,I$5:I$403,"mayo",F$5:F$403,K15) -> 202695
A16: 46144 | B16: Transporte | C16: Carga on line Tarjeta Bip | D16: 10000 | E16: Sí | F16: Trabajo | G16: =IF(A16="","", "Semana "&(WEEKNUM(A16,2)-WEEKNUM(DATE(YEAR(A16),MONTH(A16),1),2)+1)) -> Semana 1 | H16: SE cargo para transporte, verificar saldo real | I16: =IF(A16="","",IF(MONTH(A16)=5,"mayo",IF(MONTH(A16)=4,"abril",TEXT(A16,"mmmm")))) -> mayo | J16: Histórico/Apertura | K16: Expansión | L16: =SUMIFS(D$5:D$403,I$5:I$403,"mayo",F$5:F$403,K16) -> 0
A17: 46144 | B17: Alimentación | C17: Pago Red | D17: 1000 | E17: Sí | F17: Trabajo | G17: =IF(A17="","", "Semana "&(WEEKNUM(A17,2)-WEEKNUM(DATE(YEAR(A17),MONTH(A17),1),2)+1)) -> Semana 1 | H17: Galletas para colacion | I17: =IF(A17="","",IF(MONTH(A17)=5,"mayo",IF(MONTH(A17)=4,"abril",TEXT(A17,"mmmm")))) -> mayo | J17: Histórico/Apertura | K17: Universidad | L17: =SUMIFS(D$5:D$403,I$5:I$403,"mayo",F$5:F$403,K17) -> 0
A18: 46144 | B18: Alimentación | C18: Pago Red | D18: 2180 | E18: Sí | F18: Trabajo | G18: =IF(A18="","", "Semana "&(WEEKNUM(A18,2)-WEEKNUM(DATE(YEAR(A18),MONTH(A18),1),2)+1)) -> Semana 1 | H18: Yogurt oara colacion | I18: =IF(A18="","",IF(MONTH(A18)=5,"mayo",IF(MONTH(A18)=4,"abril",TEXT(A18,"mmmm")))) -> mayo | J18: Histórico/Apertura | K18: Salud | L18: =SUMIFS(D$5:D$403,I$5:I$403,"mayo",F$5:F$403,K18) -> 41659
A19: 46144 | B19: Suscripción | C19: Pago Red | D19: 4950 | E19: No | F19: Operación | G19: =IF(A19="","", "Semana "&(WEEKNUM(A19,2)-WEEKNUM(DATE(YEAR(A19),MONTH(A19),1),2)+1)) -> Semana 1 | H19: Spotify | I19: =IF(A19="","",IF(MONTH(A19)=5,"mayo",IF(MONTH(A19)=4,"abril",TEXT(A19,"mmmm")))) -> mayo | J19: Histórico/Apertura | K19: Trabajo | L19: =SUMIFS(D$5:D$403,I$5:I$403,"mayo",F$5:F$403,K19) -> 252227
A20: 46145 | B20: Suscripción | C20: Pago Red | D20: 8490 | E20: Sí | F20: Red / Empresas / Holding | G20: =IF(A20="","", "Semana "&(WEEKNUM(A20,2)-WEEKNUM(DATE(YEAR(A20),MONTH(A20),1),2)+1)) -> Semana 1 | H20: Microsoft Office | I20: =IF(A20="","",IF(MONTH(A20)=5,"mayo",IF(MONTH(A20)=4,"abril",TEXT(A20,"mmmm")))) -> mayo | J20: Histórico/Apertura | K20: Red / Empresas / Holding | L20: =SUMIFS(D$5:D$403,I$5:I$403,"mayo",F$5:F$403,K20) -> 69738
A21: 46146 | B21: Alimentación | C21: Pago Red | D21: 13447 | E21: Sí | F21: Operación | G21: =IF(A21="","", "Semana "&(WEEKNUM(A21,2)-WEEKNUM(DATE(YEAR(A21),MONTH(A21),1),2)+1)) -> Semana 2 | H21: Supermecado Lider | I21: =IF(A21="","",IF(MONTH(A21)=5,"mayo",IF(MONTH(A21)=4,"abril",TEXT(A21,"mmmm")))) -> mayo | J21: Histórico/Apertura
A22: 46146 | B22: Alimentación | C22: Pago Red | D22: 5000 | E22: Sí | F22: Operación | G22: =IF(A22="","", "Semana "&(WEEKNUM(A22,2)-WEEKNUM(DATE(YEAR(A22),MONTH(A22),1),2)+1)) -> Semana 2 | H22: Transferencia andrea Verduras | I22: =IF(A22="","",IF(MONTH(A22)=5,"mayo",IF(MONTH(A22)=4,"abril",TEXT(A22,"mmmm")))) -> mayo | J22: Histórico/Apertura
A23: 46146 | B23: MGC | C23: Pago Red | D23: 6210 | E23: Sí | F23: Red / Empresas / Holding | G23: =IF(A23="","", "Semana "&(WEEKNUM(A23,2)-WEEKNUM(DATE(YEAR(A23),MONTH(A23),1),2)+1)) -> Semana 2 | H23: Pago de cuentas de email | I23: =IF(A23="","",IF(MONTH(A23)=5,"mayo",IF(MONTH(A23)=4,"abril",TEXT(A23,"mmmm")))) -> mayo | J23: Histórico/Apertura | K23: Por semana
A24: 46146 | B24: Alimentación | C24: Pago Red | D24: 27360 | E24: Sí | F24: Operación | G24: =IF(A24="","", "Semana "&(WEEKNUM(A24,2)-WEEKNUM(DATE(YEAR(A24),MONTH(A24),1),2)+1)) -> Semana 2 | H24: Spermecado Alvi, Leche, te y yogurt | I24: =IF(A24="","",IF(MONTH(A24)=5,"mayo",IF(MONTH(A24)=4,"abril",TEXT(A24,"mmmm")))) -> mayo | J24: Histórico/Apertura | K24: Semana 1 | L24: =SUMIFS(D$5:D$403,I$5:I$403,"mayo",G$5:G$403,K24) -> 504575
A25: 46147 | B25: Alimentación | C25: Pago Red | D25: 2470 | E25: Sí | F25: Trabajo | G25: =IF(A25="","", "Semana "&(WEEKNUM(A25,2)-WEEKNUM(DATE(YEAR(A25),MONTH(A25),1),2)+1)) -> Semana 2 | H25: Compra galletas | I25: =IF(A25="","",IF(MONTH(A25)=5,"mayo",IF(MONTH(A25)=4,"abril",TEXT(A25,"mmmm")))) -> mayo | J25: Histórico/Apertura | K25: Semana 2 | L25: =SUMIFS(D$5:D$403,I$5:I$403,"mayo",G$5:G$403,K25) -> 479907
A26: 46147 | B26: Alimentación | C26: pago Red | D26: 1310 | E26: Sí | F26: Trabajo | G26: =IF(A26="","", "Semana "&(WEEKNUM(A26,2)-WEEKNUM(DATE(YEAR(A26),MONTH(A26),1),2)+1)) -> Semana 2 | H26: Frutas | I26: =IF(A26="","",IF(MONTH(A26)=5,"mayo",IF(MONTH(A26)=4,"abril",TEXT(A26,"mmmm")))) -> mayo | J26: Histórico/Apertura | K26: Semana 3 | L26: =SUMIFS(D$5:D$403,I$5:I$403,"mayo",G$5:G$403,K26) -> 223148
A27: 46147 | B27: Otros | C27: Transferencia bancaria | D27: 20000 | E27: Sí | F27: Operación | G27: =IF(A27="","", "Semana "&(WEEKNUM(A27,2)-WEEKNUM(DATE(YEAR(A27),MONTH(A27),1),2)+1)) -> Semana 2 | H27: Retiro Fondos APV banco estado | I27: =IF(A27="","",IF(MONTH(A27)=5,"mayo",IF(MONTH(A27)=4,"abril",TEXT(A27,"mmmm")))) -> mayo | J27: Histórico/Apertura | K27: Semana 4 | L27: =SUMIFS(D$5:D$403,I$5:I$403,"mayo",G$5:G$403,K27) -> 65266
A28: 46147 | B28: Otros | C28: Transferencia bancaria | D28: 40000 | E28: si | F28: Caja | G28: =IF(A28="","", "Semana "&(WEEKNUM(A28,2)-WEEKNUM(DATE(YEAR(A28),MONTH(A28),1),2)+1)) -> Semana 2 | H28: Fondo a caja | I28: =IF(A28="","",IF(MONTH(A28)=5,"mayo",IF(MONTH(A28)=4,"abril",TEXT(A28,"mmmm")))) -> mayo | J28: Histórico/Apertura | K28: Semana 5 | L28: =SUMIFS(D$5:D$403,I$5:I$403,"mayo",G$5:G$403,K28) -> 66121
A29: 46147 | B29: Inversión | C29: Transferencia bancaria | D29: 47000 | E29: Sí | F29: Inversión | G29: =IF(A29="","", "Semana "&(WEEKNUM(A29,2)-WEEKNUM(DATE(YEAR(A29),MONTH(A29),1),2)+1)) -> Semana 2 | H29: Transferencia a Racional | I29: =IF(A29="","",IF(MONTH(A29)=5,"mayo",IF(MONTH(A29)=4,"abril",TEXT(A29,"mmmm")))) -> mayo | J29: Histórico/Apertura
A30: 46147 | B30: Inversión | C30: Transferencia bancaria | D30: 8000 | E30: si | F30: Inversión | G30: =IF(A30="","", "Semana "&(WEEKNUM(A30,2)-WEEKNUM(DATE(YEAR(A30),MONTH(A30),1),2)+1)) -> Semana 2 | H30: Transferencia a Racional | I30: =IF(A30="","",IF(MONTH(A30)=5,"mayo",IF(MONTH(A30)=4,"abril",TEXT(A30,"mmmm")))) -> mayo | J30: Histórico/Apertura
A31: 46148 | B31: Inversión | C31: Transferencia bancaria | D31: 8000 | E31: Sí | F31: Inversión | G31: =IF(A31="","", "Semana "&(WEEKNUM(A31,2)-WEEKNUM(DATE(YEAR(A31),MONTH(A31),1),2)+1)) -> Semana 2 | H31: Transferencia a Racional | I31: =IF(A31="","",IF(MONTH(A31)=5,"mayo",IF(MONTH(A31)=4,"abril",TEXT(A31,"mmmm")))) -> mayo | J31: Histórico/Apertura | K31: Control CFO
A32: 46148 | B32: Alimentación | C32: Pago Red | D32: 5300 | E32: Sí | F32: Operación | G32: =IF(A32="","", "Semana "&(WEEKNUM(A32,2)-WEEKNUM(DATE(YEAR(A32),MONTH(A32),1),2)+1)) -> Semana 2 | H32: Compra de pan | I32: =IF(A32="","",IF(MONTH(A32)=5,"mayo",IF(MONTH(A32)=4,"abril",TEXT(A32,"mmmm")))) -> mayo | J32: Histórico/Apertura | K32: Gasto operativo real | L32: =SUMIFS(D$5:D$403,I$5:I$403,"mayo",J$5:J$403,"Gasto real") -> 0
A33: 46148 | B33: Alimentación | C33: Pago Red | D33: 9700 | E33: No | F33: Operación | G33: =IF(A33="","", "Semana "&(WEEKNUM(A33,2)-WEEKNUM(DATE(YEAR(A33),MONTH(A33),1),2)+1)) -> Semana 2 | H33: Empanadas, calzones rotos | I33: =IF(A33="","",IF(MONTH(A33)=5,"mayo",IF(MONTH(A33)=4,"abril",TEXT(A33,"mmmm")))) -> mayo | J33: Histórico/Apertura | K33: Movimiento patrimonial | L33: =SUMIFS(D$5:D$403,I$5:I$403,"mayo",J$5:J$403,"Movimiento patrimonial") -> 0
A34: 46148 | B34: Suscripción | C34: Pago Red | D34: 2290 | E34: No | F34: Trabajo | G34: =IF(A34="","", "Semana "&(WEEKNUM(A34,2)-WEEKNUM(DATE(YEAR(A34),MONTH(A34),1),2)+1)) -> Semana 2 | H34: Scooters eliminar suscripcion | I34: =IF(A34="","",IF(MONTH(A34)=5,"mayo",IF(MONTH(A34)=4,"abril",TEXT(A34,"mmmm")))) -> mayo | J34: Histórico/Apertura | K34: Histórico/Apertura excluido | L34: =SUMIFS(D$5:D$403,I$5:I$403,"abril") -> 100000
A35: 46149 | B35: Alimentación | C35: Pago Red | D35: 7430 | E35: si | F35: Operación | G35: =IF(A35="","", "Semana "&(WEEKNUM(A35,2)-WEEKNUM(DATE(YEAR(A35),MONTH(A35),1),2)+1)) -> Semana 2 | H35: Compra de polli, verduras | I35: =IF(A35="","",IF(MONTH(A35)=5,"mayo",IF(MONTH(A35)=4,"abril",TEXT(A35,"mmmm")))) -> mayo | J35: Histórico/Apertura
A36: 46149 | B36: Alimentación | C36: Pago Red | D36: 3830 | E36: si | F36: Operación | G36: =IF(A36="","", "Semana "&(WEEKNUM(A36,2)-WEEKNUM(DATE(YEAR(A36),MONTH(A36),1),2)+1)) -> Semana 2 | H36: Pan | I36: =IF(A36="","",IF(MONTH(A36)=5,"mayo",IF(MONTH(A36)=4,"abril",TEXT(A36,"mmmm")))) -> mayo | J36: Histórico/Apertura
A37: 46149 | B37: Alimentación | C37: Pago Red | D37: 220460 | E37: si | F37: Operación | G37: =IF(A37="","", "Semana "&(WEEKNUM(A37,2)-WEEKNUM(DATE(YEAR(A37),MONTH(A37),1),2)+1)) -> Semana 2 | H37: Compra mercaderia Alvi | I37: =IF(A37="","",IF(MONTH(A37)=5,"mayo",IF(MONTH(A37)=4,"abril",TEXT(A37,"mmmm")))) -> mayo | J37: Histórico/Apertura
A38: 46150 | B38: Alimentación | C38: Pago Red | D38: 20000 | E38: si | F38: Operación | G38: =IF(A38="","", "Semana "&(WEEKNUM(A38,2)-WEEKNUM(DATE(YEAR(A38),MONTH(A38),1),2)+1)) -> Semana 2 | H38: Feria | I38: =IF(A38="","",IF(MONTH(A38)=5,"mayo",IF(MONTH(A38)=4,"abril",TEXT(A38,"mmmm")))) -> mayo | J38: Histórico/Apertura
A39: 46150 | B39: Transporte | C39: Pago Red | D39: 4000 | E39: No | F39: Trabajo | G39: =IF(A39="","", "Semana "&(WEEKNUM(A39,2)-WEEKNUM(DATE(YEAR(A39),MONTH(A39),1),2)+1)) -> Semana 2 | H39: Scooters eliminar suscripcion | I39: =IF(A39="","",IF(MONTH(A39)=5,"mayo",IF(MONTH(A39)=4,"abril",TEXT(A39,"mmmm")))) -> mayo | J39: Histórico/Apertura
A40: 46150 | B40: Otros | C40: Pago Red | D40: 2200 | E40: si | F40: Trabajo | G40: =IF(A40="","", "Semana "&(WEEKNUM(A40,2)-WEEKNUM(DATE(YEAR(A40),MONTH(A40),1),2)+1)) -> Semana 2 | H40: Dedua con Leandro Trabajo | I40: =IF(A40="","",IF(MONTH(A40)=5,"mayo",IF(MONTH(A40)=4,"abril",TEXT(A40,"mmmm")))) -> mayo | J40: Histórico/Apertura
A41: 46150 | B41: Otros | C41: Pago Red | D41: 2900 | E41: No | F41: Operación | G41: =IF(A41="","", "Semana "&(WEEKNUM(A41,2)-WEEKNUM(DATE(YEAR(A41),MONTH(A41),1),2)+1)) -> Semana 2 | H41: Juego del telefono | I41: =IF(A41="","",IF(MONTH(A41)=5,"mayo",IF(MONTH(A41)=4,"abril",TEXT(A41,"mmmm")))) -> mayo | J41: Histórico/Apertura
A42: 46151 | B42: Alimentación | C42: Pago Red | D42: 5000 | E42: si | F42: Operación | G42: =IF(A42="","", "Semana "&(WEEKNUM(A42,2)-WEEKNUM(DATE(YEAR(A42),MONTH(A42),1),2)+1)) -> Semana 2 | H42: Pan | I42: =IF(A42="","",IF(MONTH(A42)=5,"mayo",IF(MONTH(A42)=4,"abril",TEXT(A42,"mmmm")))) -> mayo | J42: Histórico/Apertura
A43: 46152 | B43: Alimentación | C43: Pago Red | D43: 3000 | E43: si | F43: Operación | G43: =IF(A43="","", "Semana "&(WEEKNUM(A43,2)-WEEKNUM(DATE(YEAR(A43),MONTH(A43),1),2)+1)) -> Semana 2 | H43: Pan | I43: =IF(A43="","",IF(MONTH(A43)=5,"mayo",IF(MONTH(A43)=4,"abril",TEXT(A43,"mmmm")))) -> mayo | J43: Histórico/Apertura
A44: 46152 | B44: Transporte | C44: Pago Red | D44: 10000 | E44: si | F44: Trabajo | G44: =IF(A44="","", "Semana "&(WEEKNUM(A44,2)-WEEKNUM(DATE(YEAR(A44),MONTH(A44),1),2)+1)) -> Semana 2 | H44: Tarjeta Bip | I44: =IF(A44="","",IF(MONTH(A44)=5,"mayo",IF(MONTH(A44)=4,"abril",TEXT(A44,"mmmm")))) -> mayo | J44: Histórico/Apertura
A45: 46152 | B45: Alimentación | C45: Pago Red | D45: 5000 | E45: si | F45: Operación | G45: =IF(A45="","", "Semana "&(WEEKNUM(A45,2)-WEEKNUM(DATE(YEAR(A45),MONTH(A45),1),2)+1)) -> Semana 2 | H45: Transferencia a Angela | I45: =IF(A45="","",IF(MONTH(A45)=5,"mayo",IF(MONTH(A45)=4,"abril",TEXT(A45,"mmmm")))) -> mayo | J45: Histórico/Apertura
A46: 46153 | B46: MGC | C46: Pago Red | D46: 7900 | E46: Sí | F46: Red / Empresas / Holding | G46: =IF(A46="","", "Semana "&(WEEKNUM(A46,2)-WEEKNUM(DATE(YEAR(A46),MONTH(A46),1),2)+1)) -> Semana 3 | H46: Suscripcion Canvas | I46: =IF(A46="","",IF(MONTH(A46)=5,"mayo",IF(MONTH(A46)=4,"abril",TEXT(A46,"mmmm")))) -> mayo | J46: Histórico/Apertura
... A98: 46177 | B98: Otros | C98: Pago Red | D98: 1500 | E98: No | F98: Operación | G98: =IF(A98="","", "Semana "&(WEEKNUM(A98,2)-WEEKNUM(DATE(YEAR(A98),MONTH(A98),1),2)+1)) -> Semana 1 | H98: Golosina | I98: =IF(A98="","",IF(MONTH(A98)=5,"mayo",IF(MONTH(A98)=4,"abril",TEXT(A98,"mmmm")))) -> junio | J98: Gasto real
A99: 46178 | B99: Transporte | C99: Pago Red | D99: 4000 | E99: Sí | F99: Operación | G99: =IF(A99="","", "Semana "&(WEEKNUM(A99,2)-WEEKNUM(DATE(YEAR(A99),MONTH(A99),1),2)+1)) -> Semana 1 | H99: Colectivo | I99: =IF(A99="","",IF(MONTH(A99)=5,"mayo",IF(MONTH(A99)=4,"abril",TEXT(A99,"mmmm")))) -> junio | J99: =IF(A99="","",IF(I99='18_Conciliacion_Bancaria_V2'!$B$3,IF(OR(B99="Inversión",F99="Inversión",F99="Caja",ISNUMBER(SEARCH("Transferencia a Racional",H99)),ISNUMBER(SEARCH("Fondo a caja",H99)),ISNUMBER(SEARCH("APV",H99)),ISNUMBER(SEARCH("Racional",H99))),"Movimiento patrimonial","Gasto real"),"Histórico/Apertura")) -> Gasto real
A100: 46178 | B100: Trabajo | C100: Pago Red | D100: 36240 | E100: si | F100: Trabajo | G100: =IF(A100="","", "Semana "&(WEEKNUM(A100,2)-WEEKNUM(DATE(YEAR(A100),MONTH(A100),1),2)+1)) -> Semana 1 | H100: Compra de parka | I100: =IF(A100="","",IF(MONTH(A100)=5,"mayo",IF(MONTH(A100)=4,"abril",TEXT(A100,"mmmm")))) -> junio | J100: Gasto real
A101: 46178 | B101: Trabajo | C101: Pago Red | D101: 16990 | E101: Sí | F101: Trabajo | G101: =IF(A101="","", "Semana "&(WEEKNUM(A101,2)-WEEKNUM(DATE(YEAR(A101),MONTH(A101),1),2)+1)) -> Semana 1 | H101: Compra pantalon | I101: =IF(A101="","",IF(MONTH(A101)=5,"mayo",IF(MONTH(A101)=4,"abril",TEXT(A101,"mmmm")))) -> junio | J101: Gasto real
A102: 46178 | B102: Otros | C102: Pago Red | D102: 21500 | E102: No | F102: Operación | G102: =IF(A102="","", "Semana "&(WEEKNUM(A102,2)-WEEKNUM(DATE(YEAR(A102),MONTH(A102),1),2)+1)) -> Semana 1 | H102: Once en jumbo | I102: =IF(A102="","",IF(MONTH(A102)=5,"mayo",IF(MONTH(A102)=4,"abril",TEXT(A102,"mmmm")))) -> junio | J102: Gasto real
A103: 46178 | B103: Alimentación | C103: Pago Red | D103: 2520 | E103: Sí | F103: Operación | G103: =IF(A103="","", "Semana "&(WEEKNUM(A103,2)-WEEKNUM(DATE(YEAR(A103),MONTH(A103),1),2)+1)) -> Semana 1 | H103: pan | I103: =IF(A103="","",IF(MONTH(A103)=5,"mayo",IF(MONTH(A103)=4,"abril",TEXT(A103,"mmmm")))) -> junio | J103: Gasto real
A104: 46178 | B104: Trabajo | C104: Pago Red | D104: 19980 | E104: Sí | F104: Trabajo | G104: =IF(A104="","", "Semana "&(WEEKNUM(A104,2)-WEEKNUM(DATE(YEAR(A104),MONTH(A104),1),2)+1)) -> Semana 1 | H104: Compra de dos camisas | I104: =IF(A104="","",IF(MONTH(A104)=5,"mayo",IF(MONTH(A104)=4,"abril",TEXT(A104,"mmmm")))) -> junio | J104: Gasto real
A105: 46178 | B105: Inversión | C105: Pago Red | D105: 10000 | E105: Sí | F105: Inversión | G105: =IF(A105="","", "Semana "&(WEEKNUM(A105,2)-WEEKNUM(DATE(YEAR(A105),MONTH(A105),1),2)+1)) -> Semana 1 | H105: Apv | I105: =IF(A105="","",IF(MONTH(A105)=5,"mayo",IF(MONTH(A105)=4,"abril",TEXT(A105,"mmmm")))) -> junio | J105: Movimiento patrimonial
A106: 46181 | B106: Alimentación | C106: Pago Red | D106: 7010 | E106: Sí | F106: Operación | G106: =IF(A106="","", "Semana "&(WEEKNUM(A106,2)-WEEKNUM(DATE(YEAR(A106),MONTH(A106),1),2)+1)) -> Semana 2 | H106: Compra en Alvi | I106: =IF(A106="","",IF(MONTH(A106)=5,"mayo",IF(MONTH(A106)=4,"abril",TEXT(A106,"mmmm")))) -> junio | J106: Gasto real
A107: 46181 | B107: Alimentación | C107: Pago Red | D107: 7550 | E107: Sí | F107: Operación | G107: =IF(A107="","", "Semana "&(WEEKNUM(A107,2)-WEEKNUM(DATE(YEAR(A107),MONTH(A107),1),2)+1)) -> Semana 2 | H107: pan | I107: =IF(A107="","",IF(MONTH(A107)=5,"mayo",IF(MONTH(A107)=4,"abril",TEXT(A107,"mmmm")))) -> junio | J107: Gasto real
A108: 46181 | B108: Alimentación | C108: Pago Red | D108: 3500 | E108: Sí | F108: Operación | G108: =IF(A108="","", "Semana "&(WEEKNUM(A108,2)-WEEKNUM(DATE(YEAR(A108),MONTH(A108),1),2)+1)) -> Semana 2 | H108: Compra en Alvi | I108: =IF(A108="","",IF(MONTH(A108)=5,"mayo",IF(MONTH(A108)=4,"abril",TEXT(A108,"mmmm")))) -> junio | J108: Gasto real
A109: 46181 | B109: Suscripción | C109: Pago Red | D109: 33500 | E109: No | F109: Operación | G109: =IF(A109="","", "Semana "&(WEEKNUM(A109,2)-WEEKNUM(DATE(YEAR(A109),MONTH(A109),1),2)+1)) -> Semana 2 | H109: Suscripcion de CV lite (Suscripcion eliminada) | I109: =IF(A109="","",IF(MONTH(A109)=5,"mayo",IF(MONTH(A109)=4,"abril",TEXT(A109,"mmmm")))) -> junio | J109: Gasto real
A110: 46181 | B110: Alimentación | C110: Pago Red | D110: 5000 | E110: Sí | F110: Operación | G110: =IF(A110="","", "Semana "&(WEEKNUM(A110,2)-WEEKNUM(DATE(YEAR(A110),MONTH(A110),1),2)+1)) -> Semana 2 | H110: pan | I110: =IF(A110="","",IF(MONTH(A110)=5,"mayo",IF(MONTH(A110)=4,"abril",TEXT(A110,"mmmm")))) -> junio | J110: Gasto real
A111: 46187 | B111: Suscripción | C111: Pago Red | D111: 4950 | E111: Sí | F111: Operación | G111: =IF(A111="","", "Semana "&(WEEKNUM(A111,2)-WEEKNUM(DATE(YEAR(A111),MONTH(A111),1),2)+1)) -> Semana 2 | H111: Suscripcion Spotify | I111: =IF(A111="","",IF(MONTH(A111)=5,"mayo",IF(MONTH(A111)=4,"abril",TEXT(A111,"mmmm")))) -> junio | J111: Gasto real
... A134: 46199 | B134: Transporte | C134: Efectivo | D134: 2500 | E134: Sí | F134: Trabajo | G134: =IF(A134="","", "Semana "&(WEEKNUM(A134,2)-WEEKNUM(DATE(YEAR(A134),MONTH(A134),1),2)+1)) -> Semana 4 | H134: Didi | I134: =IF(A134="","",IF(MONTH(A134)=5,"mayo",IF(MONTH(A134)=4,"abril",TEXT(A134,"mmmm")))) -> junio | J134: Gasto real
A135: 46199 | B135: Transporte | C135: Efectivo | D135: 2300 | E135: Sí | F135: Trabajo | G135: =IF(A135="","", "Semana "&(WEEKNUM(A135,2)-WEEKNUM(DATE(YEAR(A135),MONTH(A135),1),2)+1)) -> Semana 4 | H135: Uber para trabajar | I135: =IF(A135="","",IF(MONTH(A135)=5,"mayo",IF(MONTH(A135)=4,"abril",TEXT(A135,"mmmm")))) -> junio
A136: 46200 | B136: Transporte | C136: Efectivo | D136: 2200 | E136: Sí | F136: Trabajo | G136: =IF(A136="","", "Semana "&(WEEKNUM(A136,2)-WEEKNUM(DATE(YEAR(A136),MONTH(A136),1),2)+1)) -> Semana 4 | H136: Didi | I136: =IF(A136="","",IF(MONTH(A136)=5,"mayo",IF(MONTH(A136)=4,"abril",TEXT(A136,"mmmm")))) -> junio
A137: 46200 | B137: Alimentación | C137: Pago Red | D137: 5000 | E137: No | F137: Operación | G137: =IF(A137="","", "Semana "&(WEEKNUM(A137,2)-WEEKNUM(DATE(YEAR(A137),MONTH(A137),1),2)+1)) -> Semana 4 | H137: Papas fritas y una bebida ultima noche | I137: =IF(A137="","",IF(MONTH(A137)=5,"mayo",IF(MONTH(A137)=4,"abril",TEXT(A137,"mmmm")))) -> junio
A138: 46200 | B138: Transporte | C138: Pago Red | D138: 3000 | E138: Sí | F138: Trabajo | G138: =IF(A138="","", "Semana "&(WEEKNUM(A138,2)-WEEKNUM(DATE(YEAR(A138),MONTH(A138),1),2)+1)) -> Semana 4 | H138: Tarjeta Bip | I138: =IF(A138="","",IF(MONTH(A138)=5,"mayo",IF(MONTH(A138)=4,"abril",TEXT(A138,"mmmm")))) -> junio
A139: 46200 | B139: Transporte | C139: Efectivo | D139: 3200 | E139: Sí | F139: Trabajo | G139: =IF(A139="","", "Semana "&(WEEKNUM(A139,2)-WEEKNUM(DATE(YEAR(A139),MONTH(A139),1),2)+1)) -> Semana 4 | H139: Uber para trabajar | I139: =IF(A139="","",IF(MONTH(A139)=5,"mayo",IF(MONTH(A139)=4,"abril",TEXT(A139,"mmmm")))) -> junio
A140: 46201 | B140: Otros | C140: Pago Red | D140: 800 | E140: No | F140: Operación | G140: =IF(A140="","", "Semana "&(WEEKNUM(A140,2)-WEEKNUM(DATE(YEAR(A140),MONTH(A140),1),2)+1)) -> Semana 4 | H140: Juego del telefono | I140: =IF(A140="","",IF(MONTH(A140)=5,"mayo",IF(MONTH(A140)=4,"abril",TEXT(A140,"mmmm")))) -> junio
A141: 46202 | B141: Otros | C141: Pago Red | D141: 3100 | E141: No | F141: Operación | G141: =IF(A141="","", "Semana "&(WEEKNUM(A141,2)-WEEKNUM(DATE(YEAR(A141),MONTH(A141),1),2)+1)) -> Semana 5 | H141: Juego del telefono | I141: =IF(A141="","",IF(MONTH(A141)=5,"mayo",IF(MONTH(A141)=4,"abril",TEXT(A141,"mmmm")))) -> junio
B142: Alimentación | C142: Pago Red | D142: 22155 | E142: Sí | F142: Operación | G142: =IF(A142="","", "Semana "&(WEEKNUM(A142,2)-WEEKNUM(DATE(YEAR(A142),MONTH(A142),1),2)+1)) | H142: Carniceria | I142: =IF(A142="","",IF(MONTH(A142)=5,"mayo",IF(MONTH(A142)=4,"abril",TEXT(A142,"mmmm"))))
B143: Alimentación | C143: Pago Red | D143: 40240 | E143: Sí | F143: Operación | G143: =IF(A143="","", "Semana "&(WEEKNUM(A143,2)-WEEKNUM(DATE(YEAR(A143),MONTH(A143),1),2)+1)) | H143: Fiambreria | I143: =IF(A143="","",IF(MONTH(A143)=5,"mayo",IF(MONTH(A143)=4,"abril",TEXT(A143,"mmmm"))))
B144: Alimentación | C144: Pago Red | D144: 13580 | E144: Sí | F144: Operación | G144: =IF(A144="","", "Semana "&(WEEKNUM(A144,2)-WEEKNUM(DATE(YEAR(A144),MONTH(A144),1),2)+1)) | H144: pan y otros | I144: =IF(A144="","",IF(MONTH(A144)=5,"mayo",IF(MONTH(A144)=4,"abril",TEXT(A144,"mmmm"))))
B145: Otros | C145: Pago Red | D145: 16981 | E145: No | F145: Operación | G145: =IF(A145="","", "Semana "&(WEEKNUM(A145,2)-WEEKNUM(DATE(YEAR(A145),MONTH(A145),1),2)+1)) | H145: sandwuichera para trabajo | I145: =IF(A145="","",IF(MONTH(A145)=5,"mayo",IF(MONTH(A145)=4,"abril",TEXT(A145,"mmmm"))))
G146: =IF(A146="","", "Semana "&(WEEKNUM(A146,2)-WEEKNUM(DATE(YEAR(A146),MONTH(A146),1),2)+1)) | I146: =IF(A146="","",IF(MONTH(A146)=5,"mayo",IF(MONTH(A146)=4,"abril",TEXT(A146,"mmmm"))))
G147: =IF(A147="","", "Semana "&(WEEKNUM(A147,2)-WEEKNUM(DATE(YEAR(A147),MONTH(A147),1),2)+1)) | I147: =IF(A147="","",IF(MONTH(A147)=5,"mayo",IF(MONTH(A147)=4,"abril",TEXT(A147,"mmmm"))))
G148: =IF(A148="","", "Semana "&(WEEKNUM(A148,2)-WEEKNUM(DATE(YEAR(A148),MONTH(A148),1),2)+1)) | I148: =IF(A148="","",IF(MONTH(A148)=5,"mayo",IF(MONTH(A148)=4,"abril",TEXT(A148,"mmmm"))))
G149: =IF(A149="","", "Semana "&(WEEKNUM(A149,2)-WEEKNUM(DATE(YEAR(A149),MONTH(A149),1),2)+1)) | I149: =IF(A149="","",IF(MONTH(A149)=5,"mayo",IF(MONTH(A149)=4,"abril",TEXT(A149,"mmmm"))))
G150: =IF(A150="","", "Semana "&(WEEKNUM(A150,2)-WEEKNUM(DATE(YEAR(A150),MONTH(A150),1),2)+1)) | I150: =IF(A150="","",IF(MONTH(A150)=5,"mayo",IF(MONTH(A150)=4,"abril",TEXT(A150,"mmmm"))))
G151: =IF(A151="","", "Semana "&(WEEKNUM(A151,2)-WEEKNUM(DATE(YEAR(A151),MONTH(A151),1),2)+1)) | I151: =IF(A151="","",IF(MONTH(A151)=5,"mayo",IF(MONTH(A151)=4,"abril",TEXT(A151,"mmmm"))))
G152: =IF(A152="","", "Semana "&(WEEKNUM(A152,2)-WEEKNUM(DATE(YEAR(A152),MONTH(A152),1),2)+1)) | I152: =IF(A152="","",IF(MONTH(A152)=5,"mayo",IF(MONTH(A152)=4,"abril",TEXT(A152,"mmmm"))))
G153: =IF(A153="","", "Semana "&(WEEKNUM(A153,2)-WEEKNUM(DATE(YEAR(A153),MONTH(A153),1),2)+1)) | I153: =IF(A153="","",IF(MONTH(A153)=5,"mayo",IF(MONTH(A153)=4,"abril",TEXT(A153,"mmmm"))))
G154: =IF(A154="","", "Semana "&(WEEKNUM(A154,2)-WEEKNUM(DATE(YEAR(A154),MONTH(A154),1),2)+1)) | I154: =IF(A154="","",IF(MONTH(A154)=5,"mayo",IF(MONTH(A154)=4,"abril",TEXT(A154,"mmmm"))))
G155: =IF(A155="","", "Semana "&(WEEKNUM(A155,2)-WEEKNUM(DATE(YEAR(A155),MONTH(A155),1),2)+1)) | I155: =IF(A155="","",IF(MONTH(A155)=5,"mayo",IF(MONTH(A155)=4,"abril",TEXT(A155,"mmmm"))))
G156: =IF(A156="","", "Semana "&(WEEKNUM(A156,2)-WEEKNUM(DATE(YEAR(A156),MONTH(A156),1),2)+1)) | I156: =IF(A156="","",IF(MONTH(A156)=5,"mayo",IF(MONTH(A156)=4,"abril",TEXT(A156,"mmmm"))))
G157: =IF(A157="","", "Semana "&(WEEKNUM(A157,2)-WEEKNUM(DATE(YEAR(A157),MONTH(A157),1),2)+1)) | I157: =IF(A157="","",IF(MONTH(A157)=5,"mayo",IF(MONTH(A157)=4,"abril",TEXT(A157,"mmmm"))))
... G403: =IF(A403="","", "Semana "&(WEEKNUM(A403,2)-WEEKNUM(DATE(YEAR(A403),MONTH(A403),1),2)+1)) | I403: =IF(A403="","",IF(MONTH(A403)=5,"mayo",IF(MONTH(A403)=4,"abril",TEXT(A403,"mmmm"))))

Sheet 13_Deudas
A1: 13 DEUDAS — V6 CONSOLIDADO
A2: Control de deuda inicial, pagos, cargos, saldo pendiente, estado y próximo paso. Conectado a Dashboard y Balance.
A4: Fecha | B4: Acreedor | C4: Deuda inicial | D4: Movimiento | E4: Monto pagado | F4: Cargo / Interés | G4: Saldo manual | H4: Saldo pendiente | I4: Cuotas | J4: Estado | K4: Próximo paso | L4: Comentario | N4: Resumen deuda | O4: Valor
A5: 46146 | B5: movistar | C5: 202695 | D5: Pago | E5: 202695 | G5: =IF(B5="","",C5-SUMIFS(E:E,B:B,B5)+SUMIFS(F:F,B:B,B5)) -> -157323 | H5: =IF(B5="","",IF(G5<>"",G5,MAX(C5+F5-E5,0))) -> -157323 | I5: 0 | J5: =IF(B5="","",IF(H5<=0,"Cumplido",IF(H5<=50000,"Atención","Pendiente"))) -> Cumplido | K5: Esperar la proxima cuenta | L5: Telefonos al dia | N5: Deuda inicial total | O5: =SUM(C5:C204) -> 1511482
A6: 46146 | B6: DonWeb | C6: 6210 | D6: Pago | E6: 6210 | F6: 0 | G6: =IF(B6="","",C6-SUMIFS(E:E,B:B,B6)+SUMIFS(F:F,B:B,B6)) -> 0 | H6: =IF(B6="","",IF(G6<>"",G6,MAX(C6+F6-E6,0))) -> 0 | I6: 0 | J6: =IF(B6="","",IF(H6<=0,"Cumplido",IF(H6<=50000,"Atención","Pendiente"))) -> Cumplido | K6: Esperar proxima boleta | L6: Correos corporativo al dia | N6: Pagos mayo | O6: =SUMIFS(E:E,A:A,">="&DATE(2026,5,1),A:A,"<"&DATE(2026,6,1)) -> 208905
A7: 46174 | B7: Universidad | C7: 213692 | D7: Pago | E7: 213692 | G7: =IF(B7="","",C7-SUMIFS(E:E,B:B,B7)+SUMIFS(F:F,B:B,B7)) -> -213692 | H7: =IF(B7="","",IF(G7<>"",G7,MAX(C7+F7-E7,0))) -> -213692 | I7: 12 | J7: =IF(B7="","",IF(H7<=0,"Cumplido",IF(H7<=50000,"Atención","Pendiente"))) -> Cumplido | K7: Esperar proxima boleta | L7: Ingenieria Industrial | N7: Cargos / intereses | O7: =SUM(F5:F204) -> 103211
A8: 46174 | B8: movistar | C8: 116193 | D8: Pago | E8: 116193 | G8: =IF(B8="","",C8-SUMIFS(E:E,B:B,B8)+SUMIFS(F:F,B:B,B8)) -> -243825 | H8: =IF(B8="","",IF(G8<>"",G8,MAX(C8+F8-E8,0))) -> -243825 | J8: =IF(B8="","",IF(H8<=0,"Cumplido",IF(H8<=50000,"Atención","Pendiente"))) -> Cumplido | K8: Esperar la proxima cuenta | L8: Telefonos | N8: Saldo deuda actual | O8: =SUM(H5:H204) -> -653763
A9: 46188 | B9: Entel | C9: 71589 | D9: Pago | E9: 71589 | G9: =IF(B9="","",C9-SUMIFS(E:E,B:B,B9)+SUMIFS(F:F,B:B,B9)) -> -45300 | H9: =IF(B9="","",IF(G9<>"",G9,MAX(C9+F9-E9,0))) -> -45300 | J9: =IF(B9="","",IF(H9<=0,"Cumplido",IF(H9<=50000,"Atención","Pendiente"))) -> Cumplido | K9: Esperar la proxima cuenta | L9: Internet y tv | N9: Reducción neta deuda | O9: =O5-O8 -> 2165245
B10: DonWeb | C10: 6210 | D10: Cargo | G10: =IF(B10="","",C10-SUMIFS(E:E,B:B,B10)+SUMIFS(F:F,B:B,B10)) -> 0 | H10: =IF(B10="","",IF(G10<>"",G10,MAX(C10+F10-E10,0))) -> 0 | J10: 🔴 Riesgo | L10: Correos corporativos
B11: Hites | C11: 551053 | D11: Renegociación | F11: 103211 | G11: =IF(B11="","",C11-SUMIFS(E:E,B:B,B11)+SUMIFS(F:F,B:B,B11)) -> 654264 | H11: =IF(B11="","",IF(G11<>"",G11,MAX(C11+F11-E11,0))) -> 654264 | I11: 24 | J11: =IF(B11="","",IF(H11<=0,"Cumplido",IF(H11<=50000,"Atención","Pendiente"))) -> Pendiente | L11: Tarjeta Hites
A12: 46189 | B12: ChatGP | C12: 21859 | D12: Cargo | E12: 21859 | G12: =IF(B12="","",C12-SUMIFS(E:E,B:B,B12)+SUMIFS(F:F,B:B,B12)) -> -21859 | H12: =IF(B12="","",IF(G12<>"",G12,MAX(C12+F12-E12,0))) -> -21859 | I12: 0 | J12: =IF(B12="","",IF(H12<=0,"Cumplido",IF(H12<=50000,"Atención","Pendiente"))) -> Cumplido | K12: Esperar la proxima cuenta | L12: ChatGP
A13: 46208 | B13: Universidad | C13: 213692 | D13: Pago | E13: 213692 | G13: =IF(B13="","",C13-SUMIFS(E:E,B:B,B13)+SUMIFS(F:F,B:B,B13)) -> -213692 | H13: =IF(B13="","",IF(G13<>"",G13,MAX(C13+F13-E13,0))) -> -213692 | I13: 12 | J13: 🟡 En proceso | K13: Cuota numero 3 | L13: Ingenieria Industrial
A14: 46208 | B14: movistar | C14: 41130 | D14: Pago | E14: 41130 | G14: =IF(B14="","",C14-SUMIFS(E:E,B:B,B14)+SUMIFS(F:F,B:B,B14)) -> -318888 | H14: =IF(B14="","",IF(G14<>"",G14,MAX(C14+F14-E14,0))) -> -318888 | I14: 0 | J14: 🟢 Cumplido | K14: Boleta mes de Junio | L14: Telefonos
A15: 46213 | B15: Entel | C15: 45300 | D15: Pago | E15: 45300 | G15: =IF(B15="","",C15-SUMIFS(E:E,B:B,B15)+SUMIFS(F:F,B:B,B15)) -> -71589 | H15: =IF(B15="","",IF(G15<>"",G15,MAX(C15+F15-E15,0))) -> -71589 | I15: 0 | J15: 🟢 Cumplido | K15: Boleta mes de Junio | L15: Internet y tv
A16: 46213 | B16: ChatGP | C16: 21859 | D16: Cargo | E16: 21859 | G16: =IF(B16="","",C16-SUMIFS(E:E,B:B,B16)+SUMIFS(F:F,B:B,B16)) -> -21859 | H16: =IF(B16="","",IF(G16<>"",G16,MAX(C16+F16-E16,0))) -> -21859 | I16: 0 | J16: 🟡 En proceso | K16: Esperar la proxima cuenta | L16: ChatGP
G17: =IF(B17="","",C17-SUMIFS(E:E,B:B,B17)+SUMIFS(F:F,B:B,B17)) | H17: =IF(B17="","",IF(G17<>"",G17,MAX(C17+F17-E17,0))) | J17: =IF(B17="","",IF(H17<=0,"Cumplido",IF(H17<=50000,"Atención","Pendiente")))
G18: =IF(B18="","",C18-SUMIFS(E:E,B:B,B18)+SUMIFS(F:F,B:B,B18)) | H18: =IF(B18="","",IF(G18<>"",G18,MAX(C18+F18-E18,0))) | J18: =IF(B18="","",IF(H18<=0,"Cumplido",IF(H18<=50000,"Atención","Pendiente")))
G19: =IF(B19="","",C19-SUMIFS(E:E,B:B,B19)+SUMIFS(F:F,B:B,B19)) | H19: =IF(B19="","",IF(G19<>"",G19,MAX(C19+F19-E19,0))) | J19: =IF(B19="","",IF(H19<=0,"Cumplido",IF(H19<=50000,"Atención","Pendiente")))
G20: =IF(B20="","",C20-SUMIFS(E:E,B:B,B20)+SUMIFS(F:F,B:B,B20)) | H20: =IF(B20="","",IF(G20<>"",G20,MAX(C20+F20-E20,0))) | J20: =IF(B20="","",IF(H20<=0,"Cumplido",IF(H20<=50000,"Atención","Pendiente")))
G21: =IF(B21="","",C21-SUMIFS(E:E,B:B,B21)+SUMIFS(F:F,B:B,B21)) | H21: =IF(B21="","",IF(G21<>"",G21,MAX(C21+F21-E21,0))) | J21: =IF(B21="","",IF(H21<=0,"Cumplido",IF(H21<=50000,"Atención","Pendiente")))
G22: =IF(B22="","",C22-SUMIFS(E:E,B:B,B22)+SUMIFS(F:F,B:B,B22)) | H22: =IF(B22="","",IF(G22<>"",G22,MAX(C22+F22-E22,0))) | J22: =IF(B22="","",IF(H22<=0,"Cumplido",IF(H22<=50000,"Atención","Pendiente")))
G23: =IF(B23="","",C23-SUMIFS(E:E,B:B,B23)+SUMIFS(F:F,B:B,B23)) | H23: =IF(B23="","",IF(G23<>"",G23,MAX(C23+F23-E23,0))) | J23: =IF(B23="","",IF(H23<=0,"Cumplido",IF(H23<=50000,"Atención","Pendiente")))
G24: =IF(B24="","",C24-SUMIFS(E:E,B:B,B24)+SUMIFS(F:F,B:B,B24)) | H24: =IF(B24="","",IF(G24<>"",G24,MAX(C24+F24-E24,0))) | J24: =IF(B24="","",IF(H24<=0,"Cumplido",IF(H24<=50000,"Atención","Pendiente")))
G25: =IF(B25="","",C25-SUMIFS(E:E,B:B,B25)+SUMIFS(F:F,B:B,B25)) | H25: =IF(B25="","",IF(G25<>"",G25,MAX(C25+F25-E25,0))) | J25: =IF(B25="","",IF(H25<=0,"Cumplido",IF(H25<=50000,"Atención","Pendiente")))
G26: =IF(B26="","",C26-SUMIFS(E:E,B:B,B26)+SUMIFS(F:F,B:B,B26)) | H26: =IF(B26="","",IF(G26<>"",G26,MAX(C26+F26-E26,0))) | J26: =IF(B26="","",IF(H26<=0,"Cumplido",IF(H26<=50000,"Atención","Pendiente")))
G27: =IF(B27="","",C27-SUMIFS(E:E,B:B,B27)+SUMIFS(F:F,B:B,B27)) | H27: =IF(B27="","",IF(G27<>"",G27,MAX(C27+F27-E27,0))) | J27: =IF(B27="","",IF(H27<=0,"Cumplido",IF(H27<=50000,"Atención","Pendiente")))
G28: =IF(B28="","",C28-SUMIFS(E:E,B:B,B28)+SUMIFS(F:F,B:B,B28)) | H28: =IF(B28="","",IF(G28<>"",G28,MAX(C28+F28-E28,0))) | J28: =IF(B28="","",IF(H28<=0,"Cumplido",IF(H28<=50000,"Atención","Pendiente")))
... G50: =IF(B50="","",C50-SUMIFS(E:E,B:B,B50)+SUMIFS(F:F,B:B,B50)) | H50: =IF(B50="","",IF(G50<>"",G50,MAX(C50+F50-E50,0))) | J50: =IF(B50="","",IF(H50<=0,"Cumplido",IF(H50<=50000,"Atención","Pendiente")))
H51: =IF(B51="","",IF(G51<>"",G51,MAX(C51+F51-E51,0))) | J51: =IF(B51="","",IF(H51<=0,"Cumplido",IF(H51<=50000,"Atención","Pendiente")))
H52: =IF(B52="","",IF(G52<>"",G52,MAX(C52+F52-E52,0))) | J52: =IF(B52="","",IF(H52<=0,"Cumplido",IF(H52<=50000,"Atención","Pendiente")))
H53: =IF(B53="","",IF(G53<>"",G53,MAX(C53+F53-E53,0))) | J53: =IF(B53="","",IF(H53<=0,"Cumplido",IF(H53<=50000,"Atención","Pendiente")))
H54: =IF(B54="","",IF(G54<>"",G54,MAX(C54+F54-E54,0))) | J54: =IF(B54="","",IF(H54<=0,"Cumplido",IF(H54<=50000,"Atención","Pendiente")))
H55: =IF(B55="","",IF(G55<>"",G55,MAX(C55+F55-E55,0))) | J55: =IF(B55="","",IF(H55<=0,"Cumplido",IF(H55<=50000,"Atención","Pendiente")))
H56: =IF(B56="","",IF(G56<>"",G56,MAX(C56+F56-E56,0))) | J56: =IF(B56="","",IF(H56<=0,"Cumplido",IF(H56<=50000,"Atención","Pendiente")))
H57: =IF(B57="","",IF(G57<>"",G57,MAX(C57+F57-E57,0))) | J57: =IF(B57="","",IF(H57<=0,"Cumplido",IF(H57<=50000,"Atención","Pendiente")))
H58: =IF(B58="","",IF(G58<>"",G58,MAX(C58+F58-E58,0))) | J58: =IF(B58="","",IF(H58<=0,"Cumplido",IF(H58<=50000,"Atención","Pendiente")))
H59: =IF(B59="","",IF(G59<>"",G59,MAX(C59+F59-E59,0))) | J59: =IF(B59="","",IF(H59<=0,"Cumplido",IF(H59<=50000,"Atención","Pendiente")))
H60: =IF(B60="","",IF(G60<>"",G60,MAX(C60+F60-E60,0))) | J60: =IF(B60="","",IF(H60<=0,"Cumplido",IF(H60<=50000,"Atención","Pendiente")))
H61: =IF(B61="","",IF(G61<>"",G61,MAX(C61+F61-E61,0))) | J61: =IF(B61="","",IF(H61<=0,"Cumplido",IF(H61<=50000,"Atención","Pendiente")))
H62: =IF(B62="","",IF(G62<>"",G62,MAX(C62+F62-E62,0))) | J62: =IF(B62="","",IF(H62<=0,"Cumplido",IF(H62<=50000,"Atención","Pendiente")))
... H204: =IF(B204="","",IF(G204<>"",G204,MAX(C204+F204-E204,0))) | J204: =IF(B204="","",IF(H204<=0,"Cumplido",IF(H204<=50000,"Atención","Pendiente")))

Sheet 14_Inversiones
A1: 14 INVERSIONES — LIBRO MAESTRO DE MOVIMIENTOS V7.1
A2: Movimiento ≠ Posición ≠ Rentabilidad ≠ Patrimonio. Cantidad/acciones y precio unitario por movimiento son opcionales si el broker los entrega; la rentabilidad se calcula con 09_Posicion_Actual.
A4: Fecha | B4: Activo | C4: Tipo movimiento | D4: Moneda | E4: Monto movimiento | F4: Cantidad/Acciones | G4: Precio ETF/Unitario | H4: Tipo cambio | I4: Valor movimiento CLP | J4: Broker/Cuenta | K4: Cuenta origen/destino | L4: Mes | M4: Trimestre | N4: Año | O4: Estado | P4: Comentario | Q4: Fuente | R4: ID
A5: 46122 | B5: TQQQ | C5: Compra | D5: USD | E5: 30 | F5: =E5/G5 -> 0.61012813 | G5: 49.17 | H5: 950 | I5: =IF(E5="","",IF(D5="USD",E5*H5,E5)) -> 28500 | J5: Racional | K5: Racional | L5: =IF(A5="","",LOWER(TEXT(A5,"mmmm"))) -> abril | M5: =IF(A5="","",IF(MONTH(A5)<=3,"T1",IF(MONTH(A5)<=6,"T2",IF(MONTH(A5)<=9,"T3","T4")))) -> T2 | N5: =IF(A5="","","Año "&YEAR(A5)-2025) -> Año 1 | O5: Migrado | P5: Compra TQQQ USD 30 | Q5: Racional/captura | R5: =IF(B5="","",TEXT(A5,"yyyymmdd")&"-"&B5&"-"&ROW()) -> 20260410-TQQQ-5
A6: 46148 | B6: TQQQ | C6: Compra | D6: USD | E6: 20 | F6: =E6/G6 -> 0.2794467 | G6: 71.57 | H6: 950 | I6: =IF(E6="","",IF(D6="USD",E6*H6,E6)) -> 19000 | J6: Racional | K6: Racional | L6: =IF(A6="","",LOWER(TEXT(A6,"mmmm"))) -> mayo | M6: =IF(A6="","",IF(MONTH(A6)<=3,"T1",IF(MONTH(A6)<=6,"T2",IF(MONTH(A6)<=9,"T3","T4")))) -> T2 | N6: =IF(A6="","","Año "&YEAR(A6)-2025) -> Año 1 | O6: Migrado | P6: Compra TQQQ USD 20 | Q6: Racional/captura | R6: =IF(B6="","",TEXT(A6,"yyyymmdd")&"-"&B6&"-"&ROW()) -> 20260506-TQQQ-6
A7: 46164 | B7: TQQQ | C7: Compra | D7: USD | E7: 10 | F7: =E7/G7 -> 0.12846865 | G7: 77.84 | H7: 950 | I7: =IF(E7="","",IF(D7="USD",E7*H7,E7)) -> 9500 | J7: Racional | K7: Racional | L7: =IF(A7="","",LOWER(TEXT(A7,"mmmm"))) -> mayo | M7: =IF(A7="","",IF(MONTH(A7)<=3,"T1",IF(MONTH(A7)<=6,"T2",IF(MONTH(A7)<=9,"T3","T4")))) -> T2 | N7: =IF(A7="","","Año "&YEAR(A7)-2025) -> Año 1 | O7: Migrado | P7: Compra TQQQ USD 10 | Q7: Racional/captura | R7: =IF(B7="","",TEXT(A7,"yyyymmdd")&"-"&B7&"-"&ROW()) -> 20260522-TQQQ-7
A8: 46148 | B8: SOXX | C8: Compra | D8: USD | E8: 30.6 | F8: =E8/G8 -> 0.060370509 | G8: 506.87 | H8: 950 | I8: =IF(E8="","",IF(D8="USD",E8*H8,E8)) -> 29070 | J8: Racional | K8: Racional | L8: =IF(A8="","",LOWER(TEXT(A8,"mmmm"))) -> mayo | M8: =IF(A8="","",IF(MONTH(A8)<=3,"T1",IF(MONTH(A8)<=6,"T2",IF(MONTH(A8)<=9,"T3","T4")))) -> T2 | N8: =IF(A8="","","Año "&YEAR(A8)-2025) -> Año 1 | O8: Migrado | P8: Compra SOXX USD 30 | Q8: Racional/captura | R8: =IF(B8="","",TEXT(A8,"yyyymmdd")&"-"&B8&"-"&ROW()) -> 20260506-SOXX-8
A9: 46148 | B9: SOXX | C9: Compra | D9: USD | E9: 10 | F9: =E9/G9 -> 0.019728925 | G9: 506.87 | H9: 950 | I9: =IF(E9="","",IF(D9="USD",E9*H9,E9)) -> 9500 | J9: Racional | K9: Racional | L9: =IF(A9="","",LOWER(TEXT(A9,"mmmm"))) -> mayo | M9: =IF(A9="","",IF(MONTH(A9)<=3,"T1",IF(MONTH(A9)<=6,"T2",IF(MONTH(A9)<=9,"T3","T4")))) -> T2 | N9: =IF(A9="","","Año "&YEAR(A9)-2025) -> Año 1 | O9: Migrado | P9: Compra SOXX USD 10 | Q9: Racional/captura | R9: =IF(B9="","",TEXT(A9,"yyyymmdd")&"-"&B9&"-"&ROW()) -> 20260506-SOXX-9
A10: 46164 | B10: SOXX | C10: Compra | D10: USD | E10: 14 | F10: =E10/G10 -> 0.026054752 | G10: 537.33 | H10: 950 | I10: =IF(E10="","",IF(D10="USD",E10*H10,E10)) -> 13300 | J10: Racional | K10: Racional | L10: =IF(A10="","",LOWER(TEXT(A10,"mmmm"))) -> mayo | M10: =IF(A10="","",IF(MONTH(A10)<=3,"T1",IF(MONTH(A10)<=6,"T2",IF(MONTH(A10)<=9,"T3","T4")))) -> T2 | N10: =IF(A10="","","Año "&YEAR(A10)-2025) -> Año 1 | O10: Migrado | P10: Compra SOXX USD 14 | Q10: Racional/captura | R10: =IF(B10="","",TEXT(A10,"yyyymmdd")&"-"&B10&"-"&ROW()) -> 20260522-SOXX-10
A11: 46148 | B11: Inversiones generales 2 | C11: Aporte | D11: CLP | E11: 8000 | H11: 950 | I11: =IF(E11="","",IF(D11="USD",E11*H11,E11)) -> 8000 | J11: Racional | K11: Racional | L11: =IF(A11="","",LOWER(TEXT(A11,"mmmm"))) -> mayo | M11: =IF(A11="","",IF(MONTH(A11)<=3,"T1",IF(MONTH(A11)<=6,"T2",IF(MONTH(A11)<=9,"T3","T4")))) -> T2 | N11: =IF(A11="","","Año "&YEAR(A11)-2025) -> Año 1 | O11: Migrado | P11: Aporte inversiones generales 2 | Q11: V6.8 | R11: =IF(B11="","",TEXT(A11,"yyyymmdd")&"-"&B11&"-"&ROW()) -> 20260506-Inversiones generales 2-11
A12: 46154 | B12: Inversiones generales 2 | C12: Ajuste | D12: CLP | E12: 30000 | H12: 950 | I12: =IF(E12="","",IF(D12="USD",E12*H12,E12)) -> 30000 | J12: Racional | K12: Racional | L12: =IF(A12="","",LOWER(TEXT(A12,"mmmm"))) -> mayo | M12: =IF(A12="","",IF(MONTH(A12)<=3,"T1",IF(MONTH(A12)<=6,"T2",IF(MONTH(A12)<=9,"T3","T4")))) -> T2 | N12: =IF(A12="","","Año "&YEAR(A12)-2025) -> Año 1 | O12: Migrado | P12: Ajuste registrado | Q12: V6.8 | R12: =IF(B12="","",TEXT(A12,"yyyymmdd")&"-"&B12&"-"&ROW()) -> 20260512-Inversiones generales 2-12
A13: 46154 | B13: Inversiones generales 2 | C13: Retiro | D13: CLP | E13: 20000 | H13: 950 | I13: =IF(E13="","",IF(D13="USD",E13*H13,E13)) -> 20000 | J13: Racional | K13: Racional | L13: =IF(A13="","",LOWER(TEXT(A13,"mmmm"))) -> mayo | M13: =IF(A13="","",IF(MONTH(A13)<=3,"T1",IF(MONTH(A13)<=6,"T2",IF(MONTH(A13)<=9,"T3","T4")))) -> T2 | N13: =IF(A13="","","Año "&YEAR(A13)-2025) -> Año 1 | O13: Migrado | P13: Retiro registrado | Q13: V6.8 | R13: =IF(B13="","",TEXT(A13,"yyyymmdd")&"-"&B13&"-"&ROW()) -> 20260512-Inversiones generales 2-13
A14: 46157 | B14: Inversiones generales 2 | C14: Retiro | D14: CLP | E14: 20000 | H14: 950 | I14: =IF(E14="","",IF(D14="USD",E14*H14,E14)) -> 20000 | J14: Racional | K14: Racional | L14: =IF(A14="","",LOWER(TEXT(A14,"mmmm"))) -> mayo | M14: =IF(A14="","",IF(MONTH(A14)<=3,"T1",IF(MONTH(A14)<=6,"T2",IF(MONTH(A14)<=9,"T3","T4")))) -> T2 | N14: =IF(A14="","","Año "&YEAR(A14)-2025) -> Año 1 | O14: Migrado | P14: Retiro inversiones generales 2 | Q14: V6.8 | R14: =IF(B14="","",TEXT(A14,"yyyymmdd")&"-"&B14&"-"&ROW()) -> 20260515-Inversiones generales 2-14
A15: 46157 | B15: Inversiones generales 2 | C15: Aporte | D15: CLP | E15: 18000 | H15: 950 | I15: =IF(E15="","",IF(D15="USD",E15*H15,E15)) -> 18000 | J15: Racional | K15: Racional | L15: =IF(A15="","",LOWER(TEXT(A15,"mmmm"))) -> mayo | M15: =IF(A15="","",IF(MONTH(A15)<=3,"T1",IF(MONTH(A15)<=6,"T2",IF(MONTH(A15)<=9,"T3","T4")))) -> T2 | N15: =IF(A15="","","Año "&YEAR(A15)-2025) -> Año 1 | O15: Migrado | P15: Aporte inversiones generales 2 | Q15: V6.8 | R15: =IF(B15="","",TEXT(A15,"yyyymmdd")&"-"&B15&"-"&ROW()) -> 20260515-Inversiones generales 2-15
A16: 46157 | B16: Inversiones generales 3 | C16: Aporte | D16: CLP | E16: 20000 | H16: 950 | I16: =IF(E16="","",IF(D16="USD",E16*H16,E16)) -> 20000 | J16: Racional | K16: Racional | L16: =IF(A16="","",LOWER(TEXT(A16,"mmmm"))) -> mayo | M16: =IF(A16="","",IF(MONTH(A16)<=3,"T1",IF(MONTH(A16)<=6,"T2",IF(MONTH(A16)<=9,"T3","T4")))) -> T2 | N16: =IF(A16="","","Año "&YEAR(A16)-2025) -> Año 1 | O16: Migrado | P16: Aporte inversiones generales 3 | Q16: V6.8 | R16: =IF(B16="","",TEXT(A16,"yyyymmdd")&"-"&B16&"-"&ROW()) -> 20260515-Inversiones generales 3-16
A17: 46148 | B17: APV banco estado | C17: Retiro | D17: CLP | E17: 20000 | H17: 950 | I17: =IF(E17="","",IF(D17="USD",E17*H17,E17)) -> 20000 | J17: Banco Estado | K17: Banco Estado | L17: =IF(A17="","",LOWER(TEXT(A17,"mmmm"))) -> mayo | M17: =IF(A17="","",IF(MONTH(A17)<=3,"T1",IF(MONTH(A17)<=6,"T2",IF(MONTH(A17)<=9,"T3","T4")))) -> T2 | N17: =IF(A17="","","Año "&YEAR(A17)-2025) -> Año 1 | O17: Migrado | P17: Retiro APV $20.000 | Q17: V6.8 | R17: =IF(B17="","",TEXT(A17,"yyyymmdd")&"-"&B17&"-"&ROW()) -> 20260506-APV banco estado-17
A18: 46148 | B18: APV banco estado | C18: Aporte | D18: CLP | E18: 10000 | H18: 950 | I18: =IF(E18="","",IF(D18="USD",E18*H18,E18)) -> 10000 | J18: Banco Estado | K18: Banco Estado | L18: =IF(A18="","",LOWER(TEXT(A18,"mmmm"))) -> mayo | M18: =IF(A18="","",IF(MONTH(A18)<=3,"T1",IF(MONTH(A18)<=6,"T2",IF(MONTH(A18)<=9,"T3","T4")))) -> T2 | N18: =IF(A18="","","Año "&YEAR(A18)-2025) -> Año 1 | O18: Migrado | P18: Aporte APV $10.000 | Q18: V6.8 | R18: =IF(B18="","",TEXT(A18,"yyyymmdd")&"-"&B18&"-"&ROW()) -> 20260506-APV banco estado-18
A19: 46175 | B19: Inversiones generales 3 | C19: Retiro | D19: USD | E19: 33.42 | H19: 950 | I19: =IF(E19="","",IF(D19="USD",E19*H19,E19)) -> 31749 | J19: Racional | K19: Racional | L19: =IF(A19="","",LOWER(TEXT(A19,"mmmm"))) -> junio | M19: =IF(A19="","",IF(MONTH(A19)<=3,"T1",IF(MONTH(A19)<=6,"T2",IF(MONTH(A19)<=9,"T3","T4")))) -> T2 | N19: =IF(A19="","","Año "&YEAR(A19)-2025) -> Año 1 | O19: Migrado | P19: Aporte a ETF | R19: =IF(B19="","",TEXT(A19,"yyyymmdd")&"-"&B19&"-"&ROW()) -> 20260602-Inversiones generales 3-19
A20: 46175 | B20: TQQQ | C20: Compra | D20: USD | E20: 58.4 | F20: =E20/G20 -> 0.6695712 | G20: 87.22 | H20: 950 | I20: =IF(E20="","",IF(D20="USD",E20*H20,E20)) -> 55480 | J20: Racional | K20: Racional | L20: =IF(A20="","",LOWER(TEXT(A20,"mmmm"))) -> junio | M20: =IF(A20="","",IF(MONTH(A20)<=3,"T1",IF(MONTH(A20)<=6,"T2",IF(MONTH(A20)<=9,"T3","T4")))) -> T2 | N20: =IF(A20="","","Año "&YEAR(A20)-2025) -> Año 1 | O20: Migrado | P20: Compra ETF | R20: =IF(B20="","",TEXT(A20,"yyyymmdd")&"-"&B20&"-"&ROW()) -> 20260602-TQQQ-20
A21: 46175 | B21: TQQQ | C21: Compra | D21: USD | E21: 57.97 | F21: =E21/G21 -> 0.66464114 | G21: 87.22 | H21: 950 | I21: =IF(E21="","",IF(D21="USD",E21*H21,E21)) -> 55071.5 | J21: Racional | K21: Racional | L21: =IF(A21="","",LOWER(TEXT(A21,"mmmm"))) -> junio | M21: =IF(A21="","",IF(MONTH(A21)<=3,"T1",IF(MONTH(A21)<=6,"T2",IF(MONTH(A21)<=9,"T3","T4")))) -> T2 | N21: =IF(A21="","","Año "&YEAR(A21)-2025) -> Año 1 | O21: Migrado | P21: Compra ETF | R21: =IF(B21="","",TEXT(A21,"yyyymmdd")&"-"&B21&"-"&ROW()) -> 20260602-TQQQ-21
A22: 46175 | B22: TQQQ | C22: Aporte | D22: CLP | E22: 50000 | I22: =IF(E22="","",IF(D22="USD",E22*H22,E22)) -> 50000 | J22: Racional | K22: Racional | L22: =IF(A22="","",LOWER(TEXT(A22,"mmmm"))) -> junio | M22: =IF(A22="","",IF(MONTH(A22)<=3,"T1",IF(MONTH(A22)<=6,"T2",IF(MONTH(A22)<=9,"T3","T4")))) -> T2 | N22: =IF(A22="","","Año "&YEAR(A22)-2025) -> Año 1 | O22: Migrado | P22: Aporte compra de acciones | R22: =IF(B22="","",TEXT(A22,"yyyymmdd")&"-"&B22&"-"&ROW()) -> 20260602-TQQQ-22
A23: 46178 | B23: APV banco estado | C23: Aporte | D23: CLP | E23: 10000 | I23: =IF(E23="","",IF(D23="USD",E23*H23,E23)) -> 10000 | J23: Banco Estado | K23: Banco Estado | L23: =IF(A23="","",LOWER(TEXT(A23,"mmmm"))) -> junio | M23: =IF(A23="","",IF(MONTH(A23)<=3,"T1",IF(MONTH(A23)<=6,"T2",IF(MONTH(A23)<=9,"T3","T4")))) -> T2 | N23: =IF(A23="","","Año "&YEAR(A23)-2025) -> Año 1 | O23: Migrado | P23: Descuento desde mi cuenta banco estado | R23: =IF(B23="","",TEXT(A23,"yyyymmdd")&"-"&B23&"-"&ROW()) -> 20260605-APV banco estado-23
A24: 46189 | B24: APV banco estado | C24: Retiro | D24: CLP | E24: 15000 | I24: =IF(E24="","",IF(D24="USD",E24*H24,E24)) -> 15000 | K24: Banco Estado | L24: =IF(A24="","",LOWER(TEXT(A24,"mmmm"))) -> junio | M24: =IF(A24="","",IF(MONTH(A24)<=3,"T1",IF(MONTH(A24)<=6,"T2",IF(MONTH(A24)<=9,"T3","T4")))) -> T2 | N24: =IF(A24="","","Año "&YEAR(A24)-2025) -> Año 1 | O24: Registrado | P24: Descuento dese del Banco | Q24: Banco Estado | R24: =IF(B24="","",TEXT(A24,"yyyymmdd")&"-"&B24&"-"&ROW()) -> 20260616-APV banco estado-24
I25: =IF(E25="","",IF(D25="USD",E25*H25,E25)) | L25: =IF(A25="","",LOWER(TEXT(A25,"mmmm"))) | M25: =IF(A25="","",IF(MONTH(A25)<=3,"T1",IF(MONTH(A25)<=6,"T2",IF(MONTH(A25)<=9,"T3","T4")))) | N25: =IF(A25="","","Año "&YEAR(A25)-2025) | R25: =IF(B25="","",TEXT(A25,"yyyymmdd")&"-"&B25&"-"&ROW())
I26: =IF(E26="","",IF(D26="USD",E26*H26,E26)) | L26: =IF(A26="","",LOWER(TEXT(A26,"mmmm"))) | M26: =IF(A26="","",IF(MONTH(A26)<=3,"T1",IF(MONTH(A26)<=6,"T2",IF(MONTH(A26)<=9,"T3","T4")))) | N26: =IF(A26="","","Año "&YEAR(A26)-2025) | R26: =IF(B26="","",TEXT(A26,"yyyymmdd")&"-"&B26&"-"&ROW())
I27: =IF(E27="","",IF(D27="USD",E27*H27,E27)) | L27: =IF(A27="","",LOWER(TEXT(A27,"mmmm"))) | M27: =IF(A27="","",IF(MONTH(A27)<=3,"T1",IF(MONTH(A27)<=6,"T2",IF(MONTH(A27)<=9,"T3","T4")))) | N27: =IF(A27="","","Año "&YEAR(A27)-2025) | R27: =IF(B27="","",TEXT(A27,"yyyymmdd")&"-"&B27&"-"&ROW())
I28: =IF(E28="","",IF(D28="USD",E28*H28,E28)) | L28: =IF(A28="","",LOWER(TEXT(A28,"mmmm"))) | M28: =IF(A28="","",IF(MONTH(A28)<=3,"T1",IF(MONTH(A28)<=6,"T2",IF(MONTH(A28)<=9,"T3","T4")))) | N28: =IF(A28="","","Año "&YEAR(A28)-2025) | R28: =IF(B28="","",TEXT(A28,"yyyymmdd")&"-"&B28&"-"&ROW())
I29: =IF(E29="","",IF(D29="USD",E29*H29,E29)) | L29: =IF(A29="","",LOWER(TEXT(A29,"mmmm"))) | M29: =IF(A29="","",IF(MONTH(A29)<=3,"T1",IF(MONTH(A29)<=6,"T2",IF(MONTH(A29)<=9,"T3","T4")))) | N29: =IF(A29="","","Año "&YEAR(A29)-2025) | R29: =IF(B29="","",TEXT(A29,"yyyymmdd")&"-"&B29&"-"&ROW())
I30: =IF(E30="","",IF(D30="USD",E30*H30,E30)) | L30: =IF(A30="","",LOWER(TEXT(A30,"mmmm"))) | M30: =IF(A30="","",IF(MONTH(A30)<=3,"T1",IF(MONTH(A30)<=6,"T2",IF(MONTH(A30)<=9,"T3","T4")))) | N30: =IF(A30="","","Año "&YEAR(A30)-2025) | R30: =IF(B30="","",TEXT(A30,"yyyymmdd")&"-"&B30&"-"&ROW())
I31: =IF(E31="","",IF(D31="USD",E31*H31,E31)) | L31: =IF(A31="","",LOWER(TEXT(A31,"mmmm"))) | M31: =IF(A31="","",IF(MONTH(A31)<=3,"T1",IF(MONTH(A31)<=6,"T2",IF(MONTH(A31)<=9,"T3","T4")))) | N31: =IF(A31="","","Año "&YEAR(A31)-2025) | R31: =IF(B31="","",TEXT(A31,"yyyymmdd")&"-"&B31&"-"&ROW())
I32: =IF(E32="","",IF(D32="USD",E32*H32,E32)) | L32: =IF(A32="","",LOWER(TEXT(A32,"mmmm"))) | M32: =IF(A32="","",IF(MONTH(A32)<=3,"T1",IF(MONTH(A32)<=6,"T2",IF(MONTH(A32)<=9,"T3","T4")))) | N32: =IF(A32="","","Año "&YEAR(A32)-2025) | R32: =IF(B32="","",TEXT(A32,"yyyymmdd")&"-"&B32&"-"&ROW())
I33: =IF(E33="","",IF(D33="USD",E33*H33,E33)) | L33: =IF(A33="","",LOWER(TEXT(A33,"mmmm"))) | M33: =IF(A33="","",IF(MONTH(A33)<=3,"T1",IF(MONTH(A33)<=6,"T2",IF(MONTH(A33)<=9,"T3","T4")))) | N33: =IF(A33="","","Año "&YEAR(A33)-2025) | R33: =IF(B33="","",TEXT(A33,"yyyymmdd")&"-"&B33&"-"&ROW())
I34: =IF(E34="","",IF(D34="USD",E34*H34,E34)) | L34: =IF(A34="","",LOWER(TEXT(A34,"mmmm"))) | M34: =IF(A34="","",IF(MONTH(A34)<=3,"T1",IF(MONTH(A34)<=6,"T2",IF(MONTH(A34)<=9,"T3","T4")))) | N34: =IF(A34="","","Año "&YEAR(A34)-2025) | R34: =IF(B34="","",TEXT(A34,"yyyymmdd")&"-"&B34&"-"&ROW())
I35: =IF(E35="","",IF(D35="USD",E35*H35,E35)) | L35: =IF(A35="","",LOWER(TEXT(A35,"mmmm"))) | M35: =IF(A35="","",IF(MONTH(A35)<=3,"T1",IF(MONTH(A35)<=6,"T2",IF(MONTH(A35)<=9,"T3","T4")))) | N35: =IF(A35="","","Año "&YEAR(A35)-2025) | R35: =IF(B35="","",TEXT(A35,"yyyymmdd")&"-"&B35&"-"&ROW())
I36: =IF(E36="","",IF(D36="USD",E36*H36,E36)) | L36: =IF(A36="","",LOWER(TEXT(A36,"mmmm"))) | M36: =IF(A36="","",IF(MONTH(A36)<=3,"T1",IF(MONTH(A36)<=6,"T2",IF(MONTH(A36)<=9,"T3","T4")))) | N36: =IF(A36="","","Año "&YEAR(A36)-2025) | R36: =IF(B36="","",TEXT(A36,"yyyymmdd")&"-"&B36&"-"&ROW())
... I203: =IF(E203="","",IF(D203="USD",E203*H203,E203)) | L203: =IF(A203="","",LOWER(TEXT(A203,"mmmm"))) | M203: =IF(A203="","",IF(MONTH(A203)<=3,"T1",IF(MONTH(A203)<=6,"T2",IF(MONTH(A203)<=9,"T3","T4")))) | N203: =IF(A203="","","Año "&YEAR(A203)-2025) | R203: =IF(B203="","",TEXT(A203,"yyyymmdd")&"-"&B203&"-"&ROW())

Sheet 09_Posicion_Actual
A1: 09 POSICIÓN ACTUAL — RACIONAL / BANCO / APV / EFECTIVO V7.1
A2: Actualizar una vez al mes. Precio ETF/unitario es la cotización de 1 unidad; valor actual moneda origen es tu posición real. SOXX corregido: valor inversión USD 60,89, no USD 574,19.
A4: Fecha actualización | B4: Activo | C4: Clase | D4: Moneda | E4: Cantidad/Acciones | F4: Precio ETF/Unitario | G4: Valor actual moneda origen | H4: Tipo cambio | I4: Valor actual CLP | J4: Costo promedio | K4: Costo total estimado | L4: Broker/Cuenta | M4: Fuente | N4: Estado | O4: Comentario | P4: Mes | Q4: ID
A5: 46174 | B5: TQQQ | C5: ETF | D5: USD | E5: 1.0205122 | F5: 84.62 | G5: 86.29 | H5: 950 | I5: =IF(G5="","",IF(D5="USD",G5*H5,G5)) -> 81975.5 | J5: 58.79 | K5: 60 | L5: Racional | M5: Captura Racional | N5: Actualizado | O5: Valor inversión real; precio ETF no es ganancia | P5: junio | Q5: =IF(B5="","",TEXT(A5,"yyyymmdd")&"-"&B5) -> 20260601-TQQQ
A6: 46174 | B6: SOXX | C6: ETF | D6: USD | E6: 0.10614771 | F6: 573.62 | G6: 60.89 | H6: 950 | I6: =IF(G6="","",IF(D6="USD",G6*H6,G6)) -> 57845.5 | J6: 508.73 | K6: 54 | L6: Racional | M6: Captura Racional | N6: Actualizado | O6: Valor corregido: USD 60,89 | P6: junio | Q6: =IF(B6="","",TEXT(A6,"yyyymmdd")&"-"&B6) -> 20260601-SOXX
A7: 46174 | B7: APV banco estado | C7: APV | D7: CLP | G7: 26000 | H7: 950 | I7: =IF(G7="","",IF(D7="USD",G7*H7,G7)) -> 26000 | L7: Banco Estado | M7: Manual | N7: Actualizado | O7: Completar valor real si cambia | P7: junio | Q7: =IF(B7="","",TEXT(A7,"yyyymmdd")&"-"&B7) -> 20260601-APV banco estado
A8: 46174 | B8: Inversiones generales 2 | C8: Fondo/Cuenta | D8: CLP | G8: 50403 | H8: 950 | I8: =IF(G8="","",IF(D8="USD",G8*H8,G8)) -> 50403 | L8: Racional | M8: Manual | N8: Actualizado | O8: Valor referencial desde V6.8 | P8: junio | Q8: =IF(B8="","",TEXT(A8,"yyyymmdd")&"-"&B8) -> 20260601-Inversiones generales 2
A9: 46174 | B9: Inversiones generales 3 | C9: Fondo/Cuenta | D9: CLP | G9: 20000 | H9: 950 | I9: =IF(G9="","",IF(D9="USD",G9*H9,G9)) -> 20000 | L9: Racional | M9: Manual | N9: Actualizado | O9: Valor referencial desde V6.8 | P9: junio | Q9: =IF(B9="","",TEXT(A9,"yyyymmdd")&"-"&B9) -> 20260601-Inversiones generales 3
A10: 46175 | B10: TQQQ | C10: ETF | D10: USD | E10: 1.3093327 | F10: 87.22 | G10: 77.53 | H10: 950 | I10: =IF(G10="","",IF(D10="USD",G10*H10,G10)) -> 73653.5 | J10: 87.22 | L10: Racional | M10: Manual | N10: Actualizado | O10: Valor real a la fecha | P10: junio | Q10: =IF(B10="","",TEXT(A10,"yyyymmdd")&"-"&B10) -> 20260602-TQQQ
I11: =IF(G11="","",IF(D11="USD",G11*H11,G11)) | Q11: =IF(B11="","",TEXT(A11,"yyyymmdd")&"-"&B11)
I12: =IF(G12="","",IF(D12="USD",G12*H12,G12)) | Q12: =IF(B12="","",TEXT(A12,"yyyymmdd")&"-"&B12)
I13: =IF(G13="","",IF(D13="USD",G13*H13,G13)) | Q13: =IF(B13="","",TEXT(A13,"yyyymmdd")&"-"&B13)
I14: =IF(G14="","",IF(D14="USD",G14*H14,G14)) | Q14: =IF(B14="","",TEXT(A14,"yyyymmdd")&"-"&B14)
I15: =IF(G15="","",IF(D15="USD",G15*H15,G15)) | Q15: =IF(B15="","",TEXT(A15,"yyyymmdd")&"-"&B15)
I16: =IF(G16="","",IF(D16="USD",G16*H16,G16)) | Q16: =IF(B16="","",TEXT(A16,"yyyymmdd")&"-"&B16)
I17: =IF(G17="","",IF(D17="USD",G17*H17,G17)) | Q17: =IF(B17="","",TEXT(A17,"yyyymmdd")&"-"&B17)
I18: =IF(G18="","",IF(D18="USD",G18*H18,G18)) | Q18: =IF(B18="","",TEXT(A18,"yyyymmdd")&"-"&B18)
I19: =IF(G19="","",IF(D19="USD",G19*H19,G19)) | Q19: =IF(B19="","",TEXT(A19,"yyyymmdd")&"-"&B19)
I20: =IF(G20="","",IF(D20="USD",G20*H20,G20)) | Q20: =IF(B20="","",TEXT(A20,"yyyymmdd")&"-"&B20)
I21: =IF(G21="","",IF(D21="USD",G21*H21,G21)) | Q21: =IF(B21="","",TEXT(A21,"yyyymmdd")&"-"&B21)
I22: =IF(G22="","",IF(D22="USD",G22*H22,G22)) | Q22: =IF(B22="","",TEXT(A22,"yyyymmdd")&"-"&B22)
... I204: =IF(G204="","",IF(D204="USD",G204*H204,G204)) | Q204: =IF(B204="","",TEXT(A204,"yyyymmdd")&"-"&B204)

Sheet 15_Historial_Diario
A1: 15 HISTORIAL DIARIO — ETF / APV / CAJA (MANUAL)
A2: Hoja manual: registrar rentabilidad diaria ETF, precio actual ETF, APV/Fondos/Caja cuando corresponda. La columna Patrimonio Total CLP es automática.
A4: Fecha | B4: Mes | C4: TQQQ % diario | D4: TQQQ Precio USD | E4: SOXX % diario | F4: SOXX Precio USD | G4: APV Banco Estado CLP | H4: Inv. Generales 2 CLP | I4: Inv. Generales 3 CLP | J4: Caja CLP | K4: Tipo Cambio | L4: Patrimonio Total CLP | M4: Nota
A5: 46143 | B5: May | C5: 0.0277 | D5: 65.3 | E5: 0.0093 | F5: 465.75 | K5: 950 | L5: =IF(A5="","",IFERROR(SUMIFS('14_Inversiones'!$F:$F,'14_Inversiones'!$B:$B,"TQQQ",'14_Inversiones'!$C:$C,"Compra",'14_Inversiones'!$A:$A,"<="&A5)*D5*K5,0)+IFERROR(SUMIFS('14_Inversiones'!$F:$F,'14_Inversiones'!$B:$B,"SOXX",'14_Inversiones'!$C:$C,"Compra",'14_Inversiones'!$A:$A,"<="&A5)*F5*K5,0)+IF(G5<>"",G5,0)+IF(H5<>"",H5,0)+IF(I5<>"",I5,0)+IF(J5<>"",J5,0)) -> 37849.298 | M5: Importado desde MOVIMIENTOS etf.xlsx
A6: 46144 | B6: May | K6: 950 | L6: =IF(A6="","",IFERROR(SUMIFS('14_Inversiones'!$F:$F,'14_Inversiones'!$B:$B,"TQQQ",'14_Inversiones'!$C:$C,"Compra",'14_Inversiones'!$A:$A,"<="&A6)*D6*K6,0)+IFERROR(SUMIFS('14_Inversiones'!$F:$F,'14_Inversiones'!$B:$B,"SOXX",'14_Inversiones'!$C:$C,"Compra",'14_Inversiones'!$A:$A,"<="&A6)*F6*K6,0)+IF(G6<>"",G6,0)+IF(H6<>"",H6,0)+IF(I6<>"",I6,0)+IF(J6<>"",J6,0)) -> 0
A7: 46145 | B7: May | K7: 950 | L7: =IF(A7="","",IFERROR(SUMIFS('14_Inversiones'!$F:$F,'14_Inversiones'!$B:$B,"TQQQ",'14_Inversiones'!$C:$C,"Compra",'14_Inversiones'!$A:$A,"<="&A7)*D7*K7,0)+IFERROR(SUMIFS('14_Inversiones'!$F:$F,'14_Inversiones'!$B:$B,"SOXX",'14_Inversiones'!$C:$C,"Compra",'14_Inversiones'!$A:$A,"<="&A7)*F7*K7,0)+IF(G7<>"",G7,0)+IF(H7<>"",H7,0)+IF(I7<>"",I7,0)+IF(J7<>"",J7,0)) -> 0
A8: 46146 | B8: May | C8: -0.006 | D8: 64.91 | E8: -0.0079 | F8: 462.06 | K8: 950 | L8: =IF(A8="","",IFERROR(SUMIFS('14_Inversiones'!$F:$F,'14_Inversiones'!$B:$B,"TQQQ",'14_Inversiones'!$C:$C,"Compra",'14_Inversiones'!$A:$A,"<="&A8)*D8*K8,0)+IFERROR(SUMIFS('14_Inversiones'!$F:$F,'14_Inversiones'!$B:$B,"SOXX",'14_Inversiones'!$C:$C,"Compra",'14_Inversiones'!$A:$A,"<="&A8)*F8*K8,0)+IF(G8<>"",G8,0)+IF(H8<>"",H8,0)+IF(I8<>"",I8,0)+IF(J8<>"",J8,0)) -> 37623.246 | M8: Importado desde MOVIMIENTOS etf.xlsx
A9: 46147 | B9: May | C9: 0.0382 | D9: 67.39 | E9: 0.0447 | F9: 482.73 | K9: 950 | L9: =IF(A9="","",IFERROR(SUMIFS('14_Inversiones'!$F:$F,'14_Inversiones'!$B:$B,"TQQQ",'14_Inversiones'!$C:$C,"Compra",'14_Inversiones'!$A:$A,"<="&A9)*D9*K9,0)+IFERROR(SUMIFS('14_Inversiones'!$F:$F,'14_Inversiones'!$B:$B,"SOXX",'14_Inversiones'!$C:$C,"Compra",'14_Inversiones'!$A:$A,"<="&A9)*F9*K9,0)+IF(G9<>"",G9,0)+IF(H9<>"",H9,0)+IF(I9<>"",I9,0)+IF(J9<>"",J9,0)) -> 39060.708 | M9: Importado desde MOVIMIENTOS etf.xlsx
A10: 46148 | B10: May | C10: 0.062 | D10: 71.57 | E10: 0.05 | F10: 506.87 | K10: 950 | L10: =IF(A10="","",IFERROR(SUMIFS('14_Inversiones'!$F:$F,'14_Inversiones'!$B:$B,"TQQQ",'14_Inversiones'!$C:$C,"Compra",'14_Inversiones'!$A:$A,"<="&A10)*D10*K10,0)+IFERROR(SUMIFS('14_Inversiones'!$F:$F,'14_Inversiones'!$B:$B,"SOXX",'14_Inversiones'!$C:$C,"Compra",'14_Inversiones'!$A:$A,"<="&A10)*F10*K10,0)+IF(G10<>"",G10,0)+IF(H10<>"",H10,0)+IF(I10<>"",I10,0)+IF(J10<>"",J10,0)) -> 99053.527 | M10: Importado desde MOVIMIENTOS etf.xlsx
A11: 46149 | B11: May | C11: -0.0032 | D11: 71.34 | E11: -0.0286 | F11: 492.36 | K11: 950 | L11: =IF(A11="","",IFERROR(SUMIFS('14_Inversiones'!$F:$F,'14_Inversiones'!$B:$B,"TQQQ",'14_Inversiones'!$C:$C,"Compra",'14_Inversiones'!$A:$A,"<="&A11)*D11*K11,0)+IFERROR(SUMIFS('14_Inversiones'!$F:$F,'14_Inversiones'!$B:$B,"SOXX",'14_Inversiones'!$C:$C,"Compra",'14_Inversiones'!$A:$A,"<="&A11)*F11*K11,0)+IF(G11<>"",G11,0)+IF(H11<>"",H11,0)+IF(I11<>"",I11,0)+IF(J11<>"",J11,0)) -> 97755.024 | M11: Importado desde MOVIMIENTOS etf.xlsx
A12: 46150 | B12: May | C12: 0.0692 | D12: 76.28 | E12: 0.0567 | F12: 520.3 | K12: 950 | L12: =IF(A12="","",IFERROR(SUMIFS('14_Inversiones'!$F:$F,'14_Inversiones'!$B:$B,"TQQQ",'14_Inversiones'!$C:$C,"Compra",'14_Inversiones'!$A:$A,"<="&A12)*D12*K12,0)+IFERROR(SUMIFS('14_Inversiones'!$F:$F,'14_Inversiones'!$B:$B,"SOXX",'14_Inversiones'!$C:$C,"Compra",'14_Inversiones'!$A:$A,"<="&A12)*F12*K12,0)+IF(G12<>"",G12,0)+IF(H12<>"",H12,0)+IF(I12<>"",I12,0)+IF(J12<>"",J12,0)) -> 104055.88 | M12: Importado desde MOVIMIENTOS etf.xlsx
A13: 46151 | B13: May | K13: 950 | L13: =IF(A13="","",IFERROR(SUMIFS('14_Inversiones'!$F:$F,'14_Inversiones'!$B:$B,"TQQQ",'14_Inversiones'!$C:$C,"Compra",'14_Inversiones'!$A:$A,"<="&A13)*D13*K13,0)+IFERROR(SUMIFS('14_Inversiones'!$F:$F,'14_Inversiones'!$B:$B,"SOXX",'14_Inversiones'!$C:$C,"Compra",'14_Inversiones'!$A:$A,"<="&A13)*F13*K13,0)+IF(G13<>"",G13,0)+IF(H13<>"",H13,0)+IF(I13<>"",I13,0)+IF(J13<>"",J13,0)) -> 0
A14: 46152 | B14: May | K14: 950 | L14: =IF(A14="","",IFERROR(SUMIFS('14_Inversiones'!$F:$F,'14_Inversiones'!$B:$B,"TQQQ",'14_Inversiones'!$C:$C,"Compra",'14_Inversiones'!$A:$A,"<="&A14)*D14*K14,0)+IFERROR(SUMIFS('14_Inversiones'!$F:$F,'14_Inversiones'!$B:$B,"SOXX",'14_Inversiones'!$C:$C,"Compra",'14_Inversiones'!$A:$A,"<="&A14)*F14*K14,0)+IF(G14<>"",G14,0)+IF(H14<>"",H14,0)+IF(I14<>"",I14,0)+IF(J14<>"",J14,0)) -> 0
A15: 46153 | B15: May | C15: 0.0089 | D15: 76.96 | E15: 0.0239 | F15: 532.76 | K15: 950 | L15: =IF(A15="","",IFERROR(SUMIFS('14_Inversiones'!$F:$F,'14_Inversiones'!$B:$B,"TQQQ",'14_Inversiones'!$C:$C,"Compra",'14_Inversiones'!$A:$A,"<="&A15)*D15*K15,0)+IFERROR(SUMIFS('14_Inversiones'!$F:$F,'14_Inversiones'!$B:$B,"SOXX",'14_Inversiones'!$C:$C,"Compra",'14_Inversiones'!$A:$A,"<="&A15)*F15*K15,0)+IF(G15<>"",G15,0)+IF(H15<>"",H15,0)+IF(I15<>"",I15,0)+IF(J15<>"",J15,0)) -> 105578.68 | M15: Importado desde MOVIMIENTOS etf.xlsx
A16: 46154 | B16: May | C16: -0.026 | D16: 74.96 | E16: -0.0315 | F16: 515.99 | K16: 950 | L16: =IF(A16="","",IFERROR(SUMIFS('14_Inversiones'!$F:$F,'14_Inversiones'!$B:$B,"TQQQ",'14_Inversiones'!$C:$C,"Compra",'14_Inversiones'!$A:$A,"<="&A16)*D16*K16,0)+IFERROR(SUMIFS('14_Inversiones'!$F:$F,'14_Inversiones'!$B:$B,"SOXX",'14_Inversiones'!$C:$C,"Compra",'14_Inversiones'!$A:$A,"<="&A16)*F16*K16,0)+IF(G16<>"",G16,0)+IF(H16<>"",H16,0)+IF(I16<>"",I16,0)+IF(J16<>"",J16,0)) -> 102612.38 | M16: Importado desde MOVIMIENTOS etf.xlsx
A17: 46155 | B17: May | C17: 0.0304 | D17: 77.24 | E17: 0.0238 | F17: 528.29 | K17: 950 | L17: =IF(A17="","",IFERROR(SUMIFS('14_Inversiones'!$F:$F,'14_Inversiones'!$B:$B,"TQQQ",'14_Inversiones'!$C:$C,"Compra",'14_Inversiones'!$A:$A,"<="&A17)*D17*K17,0)+IFERROR(SUMIFS('14_Inversiones'!$F:$F,'14_Inversiones'!$B:$B,"SOXX",'14_Inversiones'!$C:$C,"Compra",'14_Inversiones'!$A:$A,"<="&A17)*F17*K17,0)+IF(G17<>"",G17,0)+IF(H17<>"",H17,0)+IF(I17<>"",I17,0)+IF(J17<>"",J17,0)) -> 105475.16 | M17: Importado desde MOVIMIENTOS etf.xlsx
A18: 46156 | B18: May | C18: 0.0221 | D18: 78.95 | E18: 0.0033 | F18: 530.03 | K18: 950 | L18: =IF(A18="","",IFERROR(SUMIFS('14_Inversiones'!$F:$F,'14_Inversiones'!$B:$B,"TQQQ",'14_Inversiones'!$C:$C,"Compra",'14_Inversiones'!$A:$A,"<="&A18)*D18*K18,0)+IFERROR(SUMIFS('14_Inversiones'!$F:$F,'14_Inversiones'!$B:$B,"SOXX",'14_Inversiones'!$C:$C,"Compra",'14_Inversiones'!$A:$A,"<="&A18)*F18*K18,0)+IF(G18<>"",G18,0)+IF(H18<>"",H18,0)+IF(I18<>"",I18,0)+IF(J18<>"",J18,0)) -> 107052.68 | M18: Importado desde MOVIMIENTOS etf.xlsx
A19: 46157 | B19: May | C19: -0.0457 | D19: 75.34 | E19: -0.0406 | F19: 508.52 | K19: 950 | L19: =IF(A19="","",IFERROR(SUMIFS('14_Inversiones'!$F:$F,'14_Inversiones'!$B:$B,"TQQQ",'14_Inversiones'!$C:$C,"Compra",'14_Inversiones'!$A:$A,"<="&A19)*D19*K19,0)+IFERROR(SUMIFS('14_Inversiones'!$F:$F,'14_Inversiones'!$B:$B,"SOXX",'14_Inversiones'!$C:$C,"Compra",'14_Inversiones'!$A:$A,"<="&A19)*F19*K19,0)+IF(G19<>"",G19,0)+IF(H19<>"",H19,0)+IF(I19<>"",I19,0)+IF(J19<>"",J19,0)) -> 102365.09 | M19: Importado desde MOVIMIENTOS etf.xlsx
A20: 46158 | B20: May | K20: 950 | L20: =IF(A20="","",IFERROR(SUMIFS('14_Inversiones'!$F:$F,'14_Inversiones'!$B:$B,"TQQQ",'14_Inversiones'!$C:$C,"Compra",'14_Inversiones'!$A:$A,"<="&A20)*D20*K20,0)+IFERROR(SUMIFS('14_Inversiones'!$F:$F,'14_Inversiones'!$B:$B,"SOXX",'14_Inversiones'!$C:$C,"Compra",'14_Inversiones'!$A:$A,"<="&A20)*F20*K20,0)+IF(G20<>"",G20,0)+IF(H20<>"",H20,0)+IF(I20<>"",I20,0)+IF(J20<>"",J20,0)) -> 0
A21: 46159 | B21: May | K21: 950 | L21: =IF(A21="","",IFERROR(SUMIFS('14_Inversiones'!$F:$F,'14_Inversiones'!$B:$B,"TQQQ",'14_Inversiones'!$C:$C,"Compra",'14_Inversiones'!$A:$A,"<="&A21)*D21*K21,0)+IFERROR(SUMIFS('14_Inversiones'!$F:$F,'14_Inversiones'!$B:$B,"SOXX",'14_Inversiones'!$C:$C,"Compra",'14_Inversiones'!$A:$A,"<="&A21)*F21*K21,0)+IF(G21<>"",G21,0)+IF(H21<>"",H21,0)+IF(I21<>"",I21,0)+IF(J21<>"",J21,0)) -> 0
A22: 46160 | B22: May | C22: -0.0135 | D22: 74.34 | E22: -0.0249 | F22: 495.87 | K22: 950 | L22: =IF(A22="","",IFERROR(SUMIFS('14_Inversiones'!$F:$F,'14_Inversiones'!$B:$B,"TQQQ",'14_Inversiones'!$C:$C,"Compra",'14_Inversiones'!$A:$A,"<="&A22)*D22*K22,0)+IFERROR(SUMIFS('14_Inversiones'!$F:$F,'14_Inversiones'!$B:$B,"SOXX",'14_Inversiones'!$C:$C,"Compra",'14_Inversiones'!$A:$A,"<="&A22)*F22*K22,0)+IF(G22<>"",G22,0)+IF(H22<>"",H22,0)+IF(I22<>"",I22,0)+IF(J22<>"",J22,0)) -> 100557.4 | M22: Importado desde MOVIMIENTOS etf.xlsx
A23: 46161 | B23: May | C23: -0.0187 | D23: 72.93 | E23: 0.0018 | F23: 496.74 | K23: 950 | L23: =IF(A23="","",IFERROR(SUMIFS('14_Inversiones'!$F:$F,'14_Inversiones'!$B:$B,"TQQQ",'14_Inversiones'!$C:$C,"Compra",'14_Inversiones'!$A:$A,"<="&A23)*D23*K23,0)+IFERROR(SUMIFS('14_Inversiones'!$F:$F,'14_Inversiones'!$B:$B,"SOXX",'14_Inversiones'!$C:$C,"Compra",'14_Inversiones'!$A:$A,"<="&A23)*F23*K23,0)+IF(G23<>"",G23,0)+IF(H23<>"",H23,0)+IF(I23<>"",I23,0)+IF(J23<>"",J23,0)) -> 99432.02 | M23: Importado desde MOVIMIENTOS etf.xlsx
A24: 46162 | B24: May | C24: 0.0491 | D24: 76.51 | E24: 0.0474 | F24: 520.31 | K24: 950 | L24: =IF(A24="","",IFERROR(SUMIFS('14_Inversiones'!$F:$F,'14_Inversiones'!$B:$B,"TQQQ",'14_Inversiones'!$C:$C,"Compra",'14_Inversiones'!$A:$A,"<="&A24)*D24*K24,0)+IFERROR(SUMIFS('14_Inversiones'!$F:$F,'14_Inversiones'!$B:$B,"SOXX",'14_Inversiones'!$C:$C,"Compra",'14_Inversiones'!$A:$A,"<="&A24)*F24*K24,0)+IF(G24<>"",G24,0)+IF(H24<>"",H24,0)+IF(I24<>"",I24,0)+IF(J24<>"",J24,0)) -> 104251.01 | M24: Importado desde MOVIMIENTOS etf.xlsx
A25: 46163 | B25: May | C25: 0.0058 | D25: 76.95 | E25: 0.0085 | F25: 524.71 | K25: 950 | L25: =IF(A25="","",IFERROR(SUMIFS('14_Inversiones'!$F:$F,'14_Inversiones'!$B:$B,"TQQQ",'14_Inversiones'!$C:$C,"Compra",'14_Inversiones'!$A:$A,"<="&A25)*D25*K25,0)+IFERROR(SUMIFS('14_Inversiones'!$F:$F,'14_Inversiones'!$B:$B,"SOXX",'14_Inversiones'!$C:$C,"Compra",'14_Inversiones'!$A:$A,"<="&A25)*F25*K25,0)+IF(G25<>"",G25,0)+IF(H25<>"",H25,0)+IF(I25<>"",I25,0)+IF(J25<>"",J25,0)) -> 104957.67 | M25: Importado desde MOVIMIENTOS etf.xlsx
